Workbook
Name __bookmark_1: #REF!
Name _bdm.029d27569d8f4137b38391c1866e0ecf.edm: #REF!
Name _I1: #REF!
Name _I10: #REF!
Name _I11: #REF!
Name _I12: #REF!
Name _I13: #REF!
Name _I14: #REF!
Name _I15: #REF!
Name _I16: #REF!
Name _I2: #REF!
Name _I3: #REF!
Name _I4: #REF!
Name _I5: #REF!
Name _I6: #REF!
Name _I7: #REF!
Name _I8: #REF!
Name _I9: #REF!
Name _P1: #REF!
Name _P2: #REF!
Name _P3: #REF!
Name _P4: #REF!
Name _P5: #REF!
Name _P6: #REF!
Name _RA9: #REF!
Name _RJ1: #REF!
Name _St1: #REF!
Name _St2: #REF!
Name _St3: #REF!
Name _St4: #REF!
Name _St5: #REF!
Name A: {0.1;0;0.382758620689655;0;0;0;0.258620689655172;0;0.258620689655172}
Name A: {0.1;0;0.382758620689655;0;0;0;0.258620689655172;0;0.258620689655172}
Name A: {0.1;0;0.382758620689655;0;0;0;0.258620689655172;0;0.258620689655172}
Name accounts: #REF!
Name adpt_ext_exp: #REF!
Name adpt_hdct_data: #REF!
Name AP: #REF!
Name AR: #REF!
Name AssumeSuccess: #REF!
Name AtlasReport: #REF!
Name AtlasReport_1: #REF!
Name AtlasReport_2: #REF!
Name BDCustom_OSProd1: 0
Name BDCustom_OSProd2: 1
Name BDCustom_OSProd3: 2
Name BDCustom_OSProd4: 3
Name BDCustom_P1: #REF!
Name BDCustom_P3: #REF!
Name BDEnabler: 0
Name BDScen_Prog1: #REF!
Name BDScen_Prog2: #REF!
Name Benefits: 350
Name Biophysics: #REF!
Name BMS: #REF!
Name BS: [12]Summary!$AA$11
Name BS: [13]Summary!$AA$11
Name Case: #REF!
Name Category: [12]Lists!$D$6:$D$7
Name Category: [13]Lists!$D$6:$D$7

Sheet WFP Details - 2026
A1: Temp Job ID | B1: Function | C1: Department | D1: Requestor / Manager | E1: Employee Type | F1: Level | G1: Title | H1: Location | I1: Functional Priority | J1: Corp. Priority | K1: Target Start Dt | L1: Recruiting Status | M1: Recruiter | N1: Hired Name | O1: HiBob ID | P1: Asset | Q1: Key Capability | R1: Catalyst for Growth (business rationale, key deliverables, etc.) | S1: Milestone / Trigger for Hire | T1: Talent Assessment | U1: Horizon 1 | V1: Tradeoff? | W1: FP&A (CM - Level) | X1: FP&A (CM - Timing) | Y1: FP&A (Note) | Z1: FP&A (255 Approved FTEs) | AA1: FP&A (Dept) | AB1: FP&A (Dept Tie Out) | AC1: FP&A (FTE Name) | AD1: FP&A (Level) | AE1: FP&A (Title) | AF1: FP&A (Hire Date) | AG1: Notes
A2: 1002 | B2: Communications | C2: 930 Communications | D2: Tassos Gianakakos | E2: FTE | F2: 09 - C-Suite | G2: Chief Communications Officer | H2: SSF | K2: 2024 Q3 | L2: Hired | N2: HIRED: Emily Faucette | O2: 10019 | P2: UA | Q2: Communications Leader | W2: 1. In line with Budget | X2: 1. In line with Budget | Y2: Included In Budget (Current FTE) | Z2: x | AA2: =_xlfn.XLOOKUP($A2,'2026 Approved Budget'!$B:$B,'2026 Approved Budget'!C:C) -> 930 Communications | AB2: OK | AC2: =_xlfn.XLOOKUP($A2,'2026 Approved Budget'!$B:$B,'2026 Approved Budget'!D:D) -> Emily Faucette | AD2: =_xlfn.XLOOKUP($A2,'2026 Approved Budget'!$B:$B,'2026 Approved Budget'!E:E) -> 10. C-Suite | AE2: =_xlfn.XLOOKUP($A2,'2026 Approved Budget'!$B:$B,'2026 Approved Budget'!F:F) -> Chief Communications Officer | AF2: =_xlfn.XLOOKUP($A2,'2026 Approved Budget'!$B:$B,'2026 Approved Budget'!H:H) -> 45488
A3: 1003 | B3: Communications | C3: 930 Communications | D3: Emily Faucette | E3: FTE | F3: 07 - Exec. Director | G3: Executive Director, Corporate Communications | H3: PNJ | K3: 2025 Q3 | L3: Hired | M3: Yen | N3: HIRED: Michael Bachner | O3: 10265 | P3: UA | Q3: External Communications (scenario planning, writing, media and website strategy to support data read outs, pipeline developments and corporate milestons) | R3: Pipeline introduction | S3: EC levergae hire to support pipeline introduction and upcoming data readouts | T3: Experienced Leader with proven track record who can hit the ground running, set strategy, mobilize resources and execute directly as needed. Must be willing (and motivated) to roll up sleeves and do the work. | W3: 1. In line with Budget | X3: 1. In line with Budget | Y3: Included In Budget (Current FTE) | Z3: x | AA3: =_xlfn.XLOOKUP($A3,'2026 Approved Budget'!$B:$B,'2026 Approved Budget'!C:C) -> 930 Communications | AB3: OK | AC3: =_xlfn.XLOOKUP($A3,'2026 Approved Budget'!$B:$B,'2026 Approved Budget'!D:D) -> Michael Bachner | AD3: =_xlfn.XLOOKUP($A3,'2026 Approved Budget'!$B:$B,'2026 Approved Budget'!E:E) -> 07. Exec. Director | AE3: =_xlfn.XLOOKUP($A3,'2026 Approved Budget'!$B:$B,'2026 Approved Budget'!F:F) -> Executive Director, External Communications | AF3: =_xlfn.XLOOKUP($A3,'2026 Approved Budget'!$B:$B,'2026 Approved Budget'!H:H) -> 45894
A4: 1004 | B4: Communications | C4: 930 Communications | D4: Emily Faucette | E4: FTE | F4: 07 - Exec. Director | G4: Exec Director, Internal Communication | H4: SSF | I4: 1 | K4: 2026 Q2 | L4: Open | M4: Yen | P4: UA | Q4: Employee communications roadmap to drive internal engagement, connectivity and re-recruitment across sites, partner with on Employer Brand, partner with P&C and IT on intranet startegy | R4: As company grows above 100 across 3 locations, increasinly important to have a seasoned, strategic internal communication expert to build a well thought out plan, including the resources to execute | S4: Pipeline introduction and upcoming data readouts | T4: Experienced Leader with proven track record who can hit the ground running, set strategy, mobilize resources and execute directly as needed. Must be willing (and motivated) to roll up sleeves and do the work. | W4: 3. Upgrade | X4: 2. Delayed | Y4: Included In Budget (Open Role) | Z4: x | AA4: =_xlfn.XLOOKUP($A4,'2026 Approved Budget'!$B:$B,'2026 Approved Budget'!C:C) -> 930 Communications | AB4: OK | AC4: =_xlfn.XLOOKUP($A4,'2026 Approved Budget'!$B:$B,'2026 Approved Budget'!D:D) -> CW: Meredith Kiernan (Convert to FTE Q1 26) | AD4: =_xlfn.XLOOKUP($A4,'2026 Approved Budget'!$B:$B,'2026 Approved Budget'!E:E) -> 06. Sr. Director | AE4: =_xlfn.XLOOKUP($A4,'2026 Approved Budget'!$B:$B,'2026 Approved Budget'!F:F) -> Senior Director, Internal Communication | AF4: =_xlfn.XLOOKUP($A4,'2026 Approved Budget'!$B:$B,'2026 Approved Budget'!H:H) -> 46096
A5: 5001 | B5: Communications | C5: 930 Communications | D5: Emily Faucette | E5: FTE | F5: 06 - Sr. Director | G5: KardiPro Internal and External Communications | H5: Chicago | I5: 2 | K5: 2026 Q1 | L5: Open | M5: Steven | N5: N/A | P5: UA | Q5: As the company launches the OKORO Heart Study and introduces Prolaio publically, we need to have a dedicated communications resource based in Chicago to oversee external communications (press releases, media outreach), partner with marketing on website and social media and develop a cohesive internal communications strategy to connect the Prolaians to each other and Kardigan as appropriate. | R5: Company growth, OKORO study launch, increased external presence and ongoing need to connect Kardigan and Prolaio people and stories as appropriate to drive each business forward. | S5: Kardigan acquiaition, OKORO study launch, first ever ublic presence beyond customer outreach | T5: Experienced Communications leader with proven track record who can hit the ground running, set strategy, mobilize resources and execute directly as needed. Must be willing (and motivated) to roll up sleeves and do the work. Health Tech experience a plus | W5: 1. In line with Budget | X5: 1. In line with Budget | Y5: Included In Budget (Open Role) | Z5: x | AA5: =_xlfn.XLOOKUP($A5,'2026 Approved Budget'!$B:$B,'2026 Approved Budget'!C:C) -> 930 Communications | AB5: OK | AC5: =_xlfn.XLOOKUP($A5,'2026 Approved Budget'!$B:$B,'2026 Approved Budget'!D:D) -> N/A | AD5: =_xlfn.XLOOKUP($A5,'2026 Approved Budget'!$B:$B,'2026 Approved Budget'!E:E) -> 06. Sr. Director | AE5: =_xlfn.XLOOKUP($A5,'2026 Approved Budget'!$B:$B,'2026 Approved Budget'!F:F) -> KardiPro Internal and External Communications | AF5: =_xlfn.XLOOKUP($A5,'2026 Approved Budget'!$B:$B,'2026 Approved Budget'!H:H) -> 46096
A6: 1310 | B6: Development | C6: 205 Executive Development | D6: Tassos Gianakakos | E6: FTE | F6: 09 - C-Suite | G6: CMO and Co-Founder | H6: PNJ | K6: 2024 Q1 | L6: Hired | N6: HIRED: Jay Edelberg | O6: 10002 | P6: UA | Q6: Lead Development Org | W6: 1. In line with Budget | X6: 1. In line with Budget | Y6: Included In Budget (Current FTE) | Z6: x | AA6: =_xlfn.XLOOKUP($A6,'2026 Approved Budget'!$B:$B,'2026 Approved Budget'!C:C) -> 205 Executive Development | AB6: OK | AC6: =_xlfn.XLOOKUP($A6,'2026 Approved Budget'!$B:$B,'2026 Approved Budget'!D:D) -> Jay Edelberg | AD6: =_xlfn.XLOOKUP($A6,'2026 Approved Budget'!$B:$B,'2026 Approved Budget'!E:E) -> 10. C-Suite | AE6: =_xlfn.XLOOKUP($A6,'2026 Approved Budget'!$B:$B,'2026 Approved Budget'!F:F) -> Chief Medical Officer | AF6: =_xlfn.XLOOKUP($A6,'2026 Approved Budget'!$B:$B,'2026 Approved Budget'!H:H) -> 45156
A7: 1068 | B7: Development | C7: 205 Executive Development | D7: Jay Edelberg | E7: FTE | F7: 01 - Below Manager | G7: Senior Executive Assistant | H7: SSF | K7: 2024 Q3 | L7: HIred | N7: HIRED: Jen Yu | O7: 10070 | P7: UA | Q7: Executive assistant - Dev and Quality | W7: 1. In line with Budget | X7: 1. In line with Budget | Y7: Included In Budget (Current FTE) | Z7: x | AA7: =_xlfn.XLOOKUP($A7,'2026 Approved Budget'!$B:$B,'2026 Approved Budget'!C:C) -> 205 Executive Development | AB7: OK | AC7: =_xlfn.XLOOKUP($A7,'2026 Approved Budget'!$B:$B,'2026 Approved Budget'!D:D) -> Jen Yu | AD7: =_xlfn.XLOOKUP($A7,'2026 Approved Budget'!$B:$B,'2026 Approved Budget'!E:E) -> 01. IC / Coordinator | AE7: =_xlfn.XLOOKUP($A7,'2026 Approved Budget'!$B:$B,'2026 Approved Budget'!F:F) -> Executive Assistant | AF7: =_xlfn.XLOOKUP($A7,'2026 Approved Budget'!$B:$B,'2026 Approved Budget'!H:H) -> 45558
A8: 5395 | B8: Development | C8: 205 Executive Development | D8: Jaclyn Patterson | E8: TG | F8: 01 - Below Manager | G8: Senior Executive Assistant | H8: PNJ | K8: 2026 Q1 | L8: Hired | M8: Kim | N8: HIRED: Nichole Mirisis-Franks | P8: UA | Q8: Executive assistant - Dev Ops and GPH's | W8: 4. Incremental Request | X8: 4. Incremental Request | Y8: Incremental Request | AA8: =_xlfn.XLOOKUP($A8,'2026 Approved Budget'!$B:$B,'2026 Approved Budget'!C:C) -> #N/A | AB8: Confirm w/ P&C | AC8: =_xlfn.XLOOKUP($A8,'2026 Approved Budget'!$B:$B,'2026 Approved Budget'!D:D) -> #N/A | AD8: =_xlfn.XLOOKUP($A8,'2026 Approved Budget'!$B:$B,'2026 Approved Budget'!E:E) -> #N/A | AE8: =_xlfn.XLOOKUP($A8,'2026 Approved Budget'!$B:$B,'2026 Approved Budget'!F:F) -> #N/A | AF8: =_xlfn.XLOOKUP($A8,'2026 Approved Budget'!$B:$B,'2026 Approved Budget'!H:H) -> #N/A | AG8: OOBR
A9: 5045 | B9: Development | C9: 215 Clinical Development | D9: Jay Edelberg | E9: FTE | F9: 08 - VP | G9: VP, Clinical Development | H9: PNJ | I9: 1 | J9: Program | K9: 2026 Q2 | M9: Linda | P9: ATA | Q9: Doctorate degree; Clinical oversight of Combination strategy & trial execution, combination strategy CDP development | R9: Development of combination strategy clinical trial program | S9: AVC data @24 weeks in ATA-301 & PoM for KAR-141; Research ACLY data | T9: Experienced Leader | U9: 02 - Data Trigger | W9: 2. Downgrade | X9: 1. In line with Budget | Y9: Included In Budget (Open Role) | Z9: x | AA9: =_xlfn.XLOOKUP($A9,'2026 Approved Budget'!$B:$B,'2026 Approved Budget'!C:C) -> 215 Clinical Development | AB9: OK | AC9: =_xlfn.XLOOKUP($A9,'2026 Approved Budget'!$B:$B,'2026 Approved Budget'!D:D) -> TBD | AD9: =_xlfn.XLOOKUP($A9,'2026 Approved Budget'!$B:$B,'2026 Approved Budget'!E:E) -> 07. Exec. Director | AE9: =_xlfn.XLOOKUP($A9,'2026 Approved Budget'!$B:$B,'2026 Approved Budget'!F:F) -> Executive Director, Clinical Development Lead | AF9: =_xlfn.XLOOKUP($A9,'2026 Approved Budget'!$B:$B,'2026 Approved Budget'!H:H) -> 46188 | AG9: accelerate to Q1 (open rec now)
A10: 1059 | B10: Development | C10: 208 Early Development | D10: Jay Edelberg | E10: FTE | F10: 08 - VP | G10: Vice President, Early Development | H10: PNJ | K10: 2024 Q4 | L10: Hired | N10: HIRED: Yehuda Cohen | O10: 10089 | P10: ATA-TLA-Dani | Q10: Translational Medicine | T10: Experienced Leader | W10: 1. In line with Budget | X10: 1. In line with Budget | Y10: Included In Budget (Current FTE) | Z10: x | AA10: =_xlfn.XLOOKUP($A10,'2026 Approved Budget'!$B:$B,'2026 Approved Budget'!C:C) -> 208 Early Development | AB10: OK | AC10: =_xlfn.XLOOKUP($A10,'2026 Approved Budget'!$B:$B,'2026 Approved Budget'!D:D) -> Yehuda Cohen | AD10: =_xlfn.XLOOKUP($A10,'2026 Approved Budget'!$B:$B,'2026 Approved Budget'!E:E) -> 08. VP | AE10: =_xlfn.XLOOKUP($A10,'2026 Approved Budget'!$B:$B,'2026 Approved Budget'!F:F) -> VP, Head of Early Clinical | AF10: =_xlfn.XLOOKUP($A10,'2026 Approved Budget'!$B:$B,'2026 Approved Budget'!H:H) -> 45600
A11: 1058 | B11: Development | C11: 208 Early Development | D11: Yehuda Cohen | E11: FTE | F11: 06 - Sr. Director | G11: Senior Director, Biomarkers | H11: PNJ | K11: 2025 Q2 | L11: Hired | N11: HIRED: Philippe Coslet | O11: 10223 | P11: ATA-TLA-Dani | Q11: Biomarkers | T11: Experienced Leader | W11: 3. Upgrade | X11: 1. In line with Budget | Y11: Included In Budget (Current FTE) | Z11: x | AA11: =_xlfn.XLOOKUP($A11,'2026 Approved Budget'!$B:$B,'2026 Approved Budget'!C:C) -> 208 Early Development | AB11: OK | AC11: =_xlfn.XLOOKUP($A11,'2026 Approved Budget'!$B:$B,'2026 Approved Budget'!D:D) -> Philippe Costet | AD11: =_xlfn.XLOOKUP($A11,'2026 Approved Budget'!$B:$B,'2026 Approved Budget'!E:E) -> 05. Director | AE11: =_xlfn.XLOOKUP($A11,'2026 Approved Budget'!$B:$B,'2026 Approved Budget'!F:F) -> AD / Director, Biomarkers | AF11: =_xlfn.XLOOKUP($A11,'2026 Approved Budget'!$B:$B,'2026 Approved Budget'!H:H) -> 45804
A12: 1296 | B12: Development | C12: 235 Regulatory | D12: Stu Heminway | E12: FTE | F12: 06 - Sr. Director | G12: Senior Director, Regulatory Operations | H12: SSF | I12: 2 | J12: Program | K12: 2026 Q1 | M12: Yen | P12: ATA-TLA | Q12: Regulatory Operations | S12: NDA Submission leadership/infrastructure/vendors for Filing Teams | U12: 03 - NDA Submission | V12: Keep | W12: 1. In line with Budget | X12: 1. In line with Budget | Y12: Included In Budget (Open Role) | Z12: x | AA12: =_xlfn.XLOOKUP($A12,'2026 Approved Budget'!$B:$B,'2026 Approved Budget'!C:C) -> 235 Regulatory | AB12: OK | AC12: =_xlfn.XLOOKUP($A12,'2026 Approved Budget'!$B:$B,'2026 Approved Budget'!D:D) -> TBD | AD12: =_xlfn.XLOOKUP($A12,'2026 Approved Budget'!$B:$B,'2026 Approved Budget'!E:E) -> 06. Sr. Director | AE12: =_xlfn.XLOOKUP($A12,'2026 Approved Budget'!$B:$B,'2026 Approved Budget'!F:F) -> Senior Director, Regulatory Operations | AF12: =_xlfn.XLOOKUP($A12,'2026 Approved Budget'!$B:$B,'2026 Approved Budget'!H:H) -> 46096 | AG12: most critical 2026 hire
A13: 1355 | B13: Development | C13: 210 Clinical Operations | D13: Jay Edelberg | E13: FTE | F13: 08 - VP | G13: Senior Vice President, Development Operations and Biometrics | H13: PNJ | K13: 2025 Q4 | L13: Hired | N13: HIRED: Jaclyn Patterson | O13: 10275 | P13: UA | T13: Experienced Leader | W13: 1. In line with Budget | X13: 1. In line with Budget | Y13: Included In Budget (Current FTE) | Z13: x | AA13: =_xlfn.XLOOKUP($A13,'2026 Approved Budget'!$B:$B,'2026 Approved Budget'!C:C) -> 210 Clinical Operations | AB13: OK | AC13: =_xlfn.XLOOKUP($A13,'2026 Approved Budget'!$B:$B,'2026 Approved Budget'!D:D) -> Jaclyn Patterson | AD13: =_xlfn.XLOOKUP($A13,'2026 Approved Budget'!$B:$B,'2026 Approved Budget'!E:E) -> 08. VP | AE13: =_xlfn.XLOOKUP($A13,'2026 Approved Budget'!$B:$B,'2026 Approved Budget'!F:F) -> SVP, Development Operations | AF13: =_xlfn.XLOOKUP($A13,'2026 Approved Budget'!$B:$B,'2026 Approved Budget'!H:H) -> 45943
A14: 1372 | B14: Development | C14: 210 Clinical Operations | D14: Jaclyn Patterson | E14: FTE | F14: 07 - Exec. Director | G14: ED, Digital Health Technologies & AI Enablement | H14: PNJ | K14: 2026 Q1 | L14: Hired | M14: Kim | N14: HIRED: Rinol Alaj | O14: 10360 | P14: ATA-TLA-Dani | S14: Now | W14: 3. Upgrade | X14: 3. Accelerated | Y14: Included In Budget (Open Role) | Z14: x | AA14: =_xlfn.XLOOKUP($A14,'2026 Approved Budget'!$B:$B,'2026 Approved Budget'!C:C) -> 210 Clinical Operations | AB14: Confirm w/ P&C | AC14: =_xlfn.XLOOKUP($A14,'2026 Approved Budget'!$B:$B,'2026 Approved Budget'!D:D) -> TBD | AD14: =_xlfn.XLOOKUP($A14,'2026 Approved Budget'!$B:$B,'2026 Approved Budget'!E:E) -> 06. Sr. Director | AE14: =_xlfn.XLOOKUP($A14,'2026 Approved Budget'!$B:$B,'2026 Approved Budget'!F:F) -> ED, Digital Health Technologies & AI Enablement | AF14: =_xlfn.XLOOKUP($A14,'2026 Approved Budget'!$B:$B,'2026 Approved Budget'!H:H) -> 46280 | AG14: keep / key
A15: 1370 | B15: Development | C15: 210 Clinical Operations | D15: Jaclyn Patterson | E15: FTE | F15: 06 - Sr. Director | G15: Sr. Director, Clinical Ops Program Lead, Dani | H15: PNJ | K15: 2024 Q1 | L15: Hired | N15: HIRED: Brianne Leary | O15: 10004 | P15: Dani | U15: 01 - Data Readout | W15: 1. In line with Budget | X15: 1. In line with Budget | Y15: Included In Budget (Current FTE) | Z15: x | AA15: =_xlfn.XLOOKUP($A15,'2026 Approved Budget'!$B:$B,'2026 Approved Budget'!C:C) -> 210 Clinical Operations | AB15: OK | AC15: =_xlfn.XLOOKUP($A15,'2026 Approved Budget'!$B:$B,'2026 Approved Budget'!D:D) -> TBD | AD15: =_xlfn.XLOOKUP($A15,'2026 Approved Budget'!$B:$B,'2026 Approved Budget'!E:E) -> 06. Sr. Director | AE15: =_xlfn.XLOOKUP($A15,'2026 Approved Budget'!$B:$B,'2026 Approved Budget'!F:F) -> Clinical Ops Program Lead Dani | AF15: =_xlfn.XLOOKUP($A15,'2026 Approved Budget'!$B:$B,'2026 Approved Budget'!H:H) -> 46096
A16: 1040 | B16: Development | C16: 210 Clinical Operations | D16: Jaclyn Patterson | E16: FTE | F16: 06 - Sr. Director | G16: Sr. Director, Clinical Operations Program Lead, ATA | H16: PNJ | K16: 2026 Q1 | L16: Hired | M16: Kim | N16: HIRED: Sanjay Patel | O16: 10283 | P16: ATA | T16: Experienced Leader | W16: 1. In line with Budget | X16: 1. In line with Budget | Y16: Included In Budget (Current FTE) | Z16: x | AA16: =_xlfn.XLOOKUP($A16,'2026 Approved Budget'!$B:$B,'2026 Approved Budget'!C:C) -> 210 Clinical Operations | AB16: OK | AC16: =_xlfn.XLOOKUP($A16,'2026 Approved Budget'!$B:$B,'2026 Approved Budget'!D:D) -> Lisa Morello | AD16: =_xlfn.XLOOKUP($A16,'2026 Approved Budget'!$B:$B,'2026 Approved Budget'!E:E) -> 06. Sr. Director | AE16: =_xlfn.XLOOKUP($A16,'2026 Approved Budget'!$B:$B,'2026 Approved Budget'!F:F) -> Clinical Ops Program Lead ATA | AF16: =_xlfn.XLOOKUP($A16,'2026 Approved Budget'!$B:$B,'2026 Approved Budget'!H:H) -> 45943
A17: 1036 | B17: Development | C17: 210 Clinical Operations | D17: Jaclyn Patterson | E17: FTE | F17: 05 - Director | G17: Sr. Director, Clinical Operations Program Lead, TLA | H17: SSF | K17: 2025 Q1 | L17: Hired | M17: Yen | N17: HIRED: Caroline Cooper | O17: 10125 | P17: TLA | Q17: Program Management. BACKFILL: Jim Marco | W17: 1. In line with Budget | X17: 1. In line with Budget | Y17: Included In Budget (Current FTE) | Z17: x | AA17: =_xlfn.XLOOKUP($A17,'2026 Approved Budget'!$B:$B,'2026 Approved Budget'!C:C) -> 210 Clinical Operations | AB17: OK | AC17: =_xlfn.XLOOKUP($A17,'2026 Approved Budget'!$B:$B,'2026 Approved Budget'!D:D) -> Caroline Cooper | AD17: =_xlfn.XLOOKUP($A17,'2026 Approved Budget'!$B:$B,'2026 Approved Budget'!E:E) -> 05. Director | AE17: =_xlfn.XLOOKUP($A17,'2026 Approved Budget'!$B:$B,'2026 Approved Budget'!F:F) -> Director, Clinical Ops Program Lead, TLA | AF17: =_xlfn.XLOOKUP($A17,'2026 Approved Budget'!$B:$B,'2026 Approved Budget'!H:H) -> 45663
A18: 1032 | B18: Development | C18: 210 Clinical Operations | D18: Brianne Leary | E18: FTE | F18: 05 - Director | G18: Director, Development Business Operations | H18: SSF | K18: 2025 Q2 | L18: Hired | N18: HIRED: Andrea Koh | O18: 10204 | P18: Dani | Q18: Clinical Contracts (CRO/vendors/sites) | T18: Experienced Leader | W18: 1. In line with Budget | X18: 1. In line with Budget | Y18: Included In Budget (Current FTE) | Z18: x | AA18: =_xlfn.XLOOKUP($A18,'2026 Approved Budget'!$B:$B,'2026 Approved Budget'!C:C) -> 210 Clinical Operations | AB18: OK | AC18: =_xlfn.XLOOKUP($A18,'2026 Approved Budget'!$B:$B,'2026 Approved Budget'!D:D) -> Andrea Koh | AD18: =_xlfn.XLOOKUP($A18,'2026 Approved Budget'!$B:$B,'2026 Approved Budget'!E:E) -> 05. Director | AE18: =_xlfn.XLOOKUP($A18,'2026 Approved Budget'!$B:$B,'2026 Approved Budget'!F:F) -> Director, Dev Business Operations | AF18: =_xlfn.XLOOKUP($A18,'2026 Approved Budget'!$B:$B,'2026 Approved Budget'!H:H) -> 45775
A19: 1044 | B19: Development | C19: 210 Clinical Operations | D19: Brianne Leary | E19: FTE | F19: 04 - Assoc. Director | G19: Associate Director, Clinical Program Lead | H19: SSF | K19: 2024 Q3 | L19: Hired | N19: HIRED: Mindy Worsham | O19: 10079 | P19: UA | Q19: Program Management; Phase 3 planning | T19: Emerging Leader | W19: 1. In line with Budget | X19: 1. In line with Budget | Y19: Included In Budget (Current FTE) | Z19: x | AA19: =_xlfn.XLOOKUP($A19,'2026 Approved Budget'!$B:$B,'2026 Approved Budget'!C:C) -> 210 Clinical Operations | AB19: OK | AC19: =_xlfn.XLOOKUP($A19,'2026 Approved Budget'!$B:$B,'2026 Approved Budget'!D:D) -> Mindy Worsham | AD19: =_xlfn.XLOOKUP($A19,'2026 Approved Budget'!$B:$B,'2026 Approved Budget'!E:E) -> 04. AD / Staff Scientist | AE19: =_xlfn.XLOOKUP($A19,'2026 Approved Budget'!$B:$B,'2026 Approved Budget'!F:F) -> Director, Clinical Operations Excellence | AF19: =_xlfn.XLOOKUP($A19,'2026 Approved Budget'!$B:$B,'2026 Approved Budget'!H:H) -> 45558
A20: 1039 | B20: Development | C20: 210 Clinical Operations | D20: Sanjay Patel | E20: FTE | F20: 04 - Assoc. Director | G20: Associate Director, Clinical Trial Lead | H20: SSF | K20: 2024 Q3 | L20: Hired | M20: Yen | N20: HIRED: Mandy Lin | O20: 10081 | P20: ATA | Q20: Clinical Trial Management | W20: 1. In line with Budget | X20: 1. In line with Budget | Y20: Included In Budget (Current FTE) | Z20: x | AA20: =_xlfn.XLOOKUP($A20,'2026 Approved Budget'!$B:$B,'2026 Approved Budget'!C:C) -> 210 Clinical Operations | AB20: OK | AC20: =_xlfn.XLOOKUP($A20,'2026 Approved Budget'!$B:$B,'2026 Approved Budget'!D:D) -> Mandy Lin | AD20: =_xlfn.XLOOKUP($A20,'2026 Approved Budget'!$B:$B,'2026 Approved Budget'!E:E) -> 04. AD / Staff Scientist | AE20: =_xlfn.XLOOKUP($A20,'2026 Approved Budget'!$B:$B,'2026 Approved Budget'!F:F) -> Clinical Trial Lead | AF20: =_xlfn.XLOOKUP($A20,'2026 Approved Budget'!$B:$B,'2026 Approved Budget'!H:H) -> 45558
A21: 1292 | B21: Development | C21: 210 Clinical Operations | D21: Caroline Cooper | E21: FTE | F21: 04 - Assoc. Director | G21: Associate Director, Clinical Trial Lead | H21: SSF | K21: 2024 Q4 | L21: Hired | N21: HIRED: Jody Dosanjh | O21: 10102 | P21: Dani | Q21: Clinical Trial Management | W21: 1. In line with Budget | X21: 1. In line with Budget | Y21: Included In Budget (Current FTE) | Z21: x | AA21: =_xlfn.XLOOKUP($A21,'2026 Approved Budget'!$B:$B,'2026 Approved Budget'!C:C) -> 210 Clinical Operations | AB21: OK | AC21: =_xlfn.XLOOKUP($A21,'2026 Approved Budget'!$B:$B,'2026 Approved Budget'!D:D) -> Jody Dosanjh | AD21: =_xlfn.XLOOKUP($A21,'2026 Approved Budget'!$B:$B,'2026 Approved Budget'!E:E) -> 04. AD / Staff Scientist | AE21: =_xlfn.XLOOKUP($A21,'2026 Approved Budget'!$B:$B,'2026 Approved Budget'!F:F) -> Clinical Trial Lead | AF21: =_xlfn.XLOOKUP($A21,'2026 Approved Budget'!$B:$B,'2026 Approved Budget'!H:H) -> 45628
A22: 1030 | B22: Development | C22: 210 Clinical Operations | D22: Caroline Cooper | E22: FTE | F22: 03 - Sr. Manager | G22: Senior Manager, Clinical Trial Lead | H22: PNJ | K22: 2024 Q2 | L22: Hired | N22: HIRED: Jessica Kim | O22: 10016 | P22: TLA | Q22: Clinical Trial Management. ION904 Clinical Trial Lead. | W22: 1. In line with Budget | X22: 1. In line with Budget | Y22: Included In Budget (Current FTE) | Z22: x | AA22: =_xlfn.XLOOKUP($A22,'2026 Approved Budget'!$B:$B,'2026 Approved Budget'!C:C) -> 210 Clinical Operations | AB22: OK | AC22: =_xlfn.XLOOKUP($A22,'2026 Approved Budget'!$B:$B,'2026 Approved Budget'!D:D) -> Jessica Kim | AD22: =_xlfn.XLOOKUP($A22,'2026 Approved Budget'!$B:$B,'2026 Approved Budget'!E:E) -> 03. Sr. Manager / Sr. Scientist | AE22: =_xlfn.XLOOKUP($A22,'2026 Approved Budget'!$B:$B,'2026 Approved Budget'!F:F) -> Clinical Trial Lead | AF22: =_xlfn.XLOOKUP($A22,'2026 Approved Budget'!$B:$B,'2026 Approved Budget'!H:H) -> 45467
A23: 1046 | B23: Development | C23: 210 Clinical Operations | D23: Sanjay Patel | E23: FTE | F23: 03 - Sr. Manager | G23: Senior Manager, Clinical Trial Lead | H23: SSF | K23: 2025 Q1 | L23: Hired | M23: Yen | N23: HIRED: Tiffany Shu | O23: 10127 | P23: ATA | Q23: Vendor Oversight (CPET, Prolaio, etc) | W23: 1. In line with Budget | X23: 1. In line with Budget | Y23: Included In Budget (Current FTE) | Z23: x | AA23: =_xlfn.XLOOKUP($A23,'2026 Approved Budget'!$B:$B,'2026 Approved Budget'!C:C) -> 210 Clinical Operations | AB23: OK | AC23: =_xlfn.XLOOKUP($A23,'2026 Approved Budget'!$B:$B,'2026 Approved Budget'!D:D) -> Tiffany Shu | AD23: =_xlfn.XLOOKUP($A23,'2026 Approved Budget'!$B:$B,'2026 Approved Budget'!E:E) -> 03. Sr. Manager / Sr. Scientist | AE23: =_xlfn.XLOOKUP($A23,'2026 Approved Budget'!$B:$B,'2026 Approved Budget'!F:F) -> Clinical Trial Manager | AF23: =_xlfn.XLOOKUP($A23,'2026 Approved Budget'!$B:$B,'2026 Approved Budget'!H:H) -> 45663
A24: 1037 | B24: Development | C24: 210 Clinical Operations | D24: Caroline Cooper | E24: FTE | F24: 03 - Sr. Manager | G24: Senior Manager, Clinical Trial Lead | H24: PNJ | K24: 2026 Q1 | L24: Hired | M24: Kim | N24: HIRED: Araceli Melgar | O24: 10358 | P24: TLA | T24: Emerging Leader | U24: 01 - Data Readout | W24: 2. Downgrade | X24: 1. In line with Budget | Y24: Included In Budget (Current FTE) | Z24: x | AA24: =_xlfn.XLOOKUP($A24,'2026 Approved Budget'!$B:$B,'2026 Approved Budget'!C:C) -> 210 Clinical Operations | AB24: OK | AC24: =_xlfn.XLOOKUP($A24,'2026 Approved Budget'!$B:$B,'2026 Approved Budget'!D:D) -> CW: Heather Fraser | AD24: =_xlfn.XLOOKUP($A24,'2026 Approved Budget'!$B:$B,'2026 Approved Budget'!E:E) -> 04. AD / Staff Scientist | AE24: =_xlfn.XLOOKUP($A24,'2026 Approved Budget'!$B:$B,'2026 Approved Budget'!F:F) -> Clinical Trial Lead | AF24: =_xlfn.XLOOKUP($A24,'2026 Approved Budget'!$B:$B,'2026 Approved Budget'!H:H) -> 46006
A25: 1056 | B25: Development | C25: 210 Clinical Operations | D25: Caroline Cooper | E25: FTE | F25: 01 - Below Manager | G25: Associate Manager, Clinical Site Operations | H25: SSF | K25: 2025 Q1 | L25: Hired | N25: HIRED: Rachel Day | O25: 10120 | P25: TLA | Q25: Site Monitoring & Performance. US ATA | W25: 1. In line with Budget | X25: 1. In line with Budget | Y25: Included In Budget (Current FTE) | Z25: x | AA25: =_xlfn.XLOOKUP($A25,'2026 Approved Budget'!$B:$B,'2026 Approved Budget'!C:C) -> 210 Clinical Operations | AB25: OK | AC25: =_xlfn.XLOOKUP($A25,'2026 Approved Budget'!$B:$B,'2026 Approved Budget'!D:D) -> Rachel Day | AD25: =_xlfn.XLOOKUP($A25,'2026 Approved Budget'!$B:$B,'2026 Approved Budget'!E:E) -> 01. IC / Coordinator | AE25: =_xlfn.XLOOKUP($A25,'2026 Approved Budget'!$B:$B,'2026 Approved Budget'!F:F) -> Associate Manager, Clinical Site Operations | AF25: =_xlfn.XLOOKUP($A25,'2026 Approved Budget'!$B:$B,'2026 Approved Budget'!H:H) -> 45663
A26: 1052 | B26: Development | C26: 210 Clinical Operations | D26: Mandy Lin | E26: FTE | F26: 01 - Below Manager | G26: Senior Clinical Trial Associate | H26: SSF | K26: 2025 Q2 | L26: Hired | M26: Yen | N26: HIRED: Vicky Ho | O26: 10157 | P26: ATA | Q26: Clinical project mgmt support | W26: 1. In line with Budget | X26: 1. In line with Budget | Y26: Included In Budget (Current FTE) | Z26: x | AA26: =_xlfn.XLOOKUP($A26,'2026 Approved Budget'!$B:$B,'2026 Approved Budget'!C:C) -> 210 Clinical Operations | AB26: OK | AC26: =_xlfn.XLOOKUP($A26,'2026 Approved Budget'!$B:$B,'2026 Approved Budget'!D:D) -> Vicky Ho | AD26: =_xlfn.XLOOKUP($A26,'2026 Approved Budget'!$B:$B,'2026 Approved Budget'!E:E) -> 01. IC / Coordinator | AE26: =_xlfn.XLOOKUP($A26,'2026 Approved Budget'!$B:$B,'2026 Approved Budget'!F:F) -> Sr. Clinical Trial Associate | AF26: =_xlfn.XLOOKUP($A26,'2026 Approved Budget'!$B:$B,'2026 Approved Budget'!H:H) -> 45831
A27: 1352 | B27: Development | C27: 210 Clinical Operations | D27: Brianne Leary | E27: CW | F27: 05 - Director | G27: Clinical Operations Lead, Early Development | H27: US Remote | K27: 2025 Q2 | L27: Hired - CW | N27: CW: Susan Szambelan | P27: UA | Q27: Clinical Trial Management | W27: N/A - CW | X27: N/A - CW | Y27: N/A (CW) | AA27: =_xlfn.XLOOKUP($A27,'2026 Approved Budget'!$B:$B,'2026 Approved Budget'!C:C) -> #N/A | AB27: N/A (CW) | AC27: =_xlfn.XLOOKUP($A27,'2026 Approved Budget'!$B:$B,'2026 Approved Budget'!D:D) -> #N/A | AD27: =_xlfn.XLOOKUP($A27,'2026 Approved Budget'!$B:$B,'2026 Approved Budget'!E:E) -> #N/A | AE27: =_xlfn.XLOOKUP($A27,'2026 Approved Budget'!$B:$B,'2026 Approved Budget'!F:F) -> #N/A | AF27: =_xlfn.XLOOKUP($A27,'2026 Approved Budget'!$B:$B,'2026 Approved Budget'!H:H) -> #N/A
A28: 1354 | B28: Development | C28: 210 Clinical Operations | D28: Brianne Leary | E28: CW | F28: 04 - Assoc. Director | G28: Sr. Consultant, eTMF | H28: US Remote | K28: 2025 Q2 | L28: Hired - CW | N28: CW: Katie Hoover | P28: UA | Q28: eTMF, Training | S28: Inspection Readiness Kick off | W28: N/A - CW | X28: N/A - CW | Y28: N/A (CW) | AA28: =_xlfn.XLOOKUP($A28,'2026 Approved Budget'!$B:$B,'2026 Approved Budget'!C:C) -> #N/A | AB28: N/A (CW) | AC28: =_xlfn.XLOOKUP($A28,'2026 Approved Budget'!$B:$B,'2026 Approved Budget'!D:D) -> #N/A | AD28: =_xlfn.XLOOKUP($A28,'2026 Approved Budget'!$B:$B,'2026 Approved Budget'!E:E) -> #N/A | AE28: =_xlfn.XLOOKUP($A28,'2026 Approved Budget'!$B:$B,'2026 Approved Budget'!F:F) -> #N/A | AF28: =_xlfn.XLOOKUP($A28,'2026 Approved Budget'!$B:$B,'2026 Approved Budget'!H:H) -> #N/A
A29: 1324 | B29: Development | C29: 210 Clinical Operations | D29: Caroline Cooper | E29: CW | F29: 03 - Sr. Manager | G29: Senior Manager, Clinical Site Operations | H29: SSF | K29: 2025 Q2 | L29: Hired - CW | N29: CW: Ali Zetter | P29: TLA | Q29: Site selection and initiation (feasibility, qualifications) and monitoring | W29: N/A - CW | X29: N/A - CW | Y29: N/A (CW) | AA29: =_xlfn.XLOOKUP($A29,'2026 Approved Budget'!$B:$B,'2026 Approved Budget'!C:C) -> #N/A | AB29: N/A (CW) | AC29: =_xlfn.XLOOKUP($A29,'2026 Approved Budget'!$B:$B,'2026 Approved Budget'!D:D) -> #N/A | AD29: =_xlfn.XLOOKUP($A29,'2026 Approved Budget'!$B:$B,'2026 Approved Budget'!E:E) -> #N/A | AE29: =_xlfn.XLOOKUP($A29,'2026 Approved Budget'!$B:$B,'2026 Approved Budget'!F:F) -> #N/A | AF29: =_xlfn.XLOOKUP($A29,'2026 Approved Budget'!$B:$B,'2026 Approved Budget'!H:H) -> #N/A
A30: 1325 | B30: Development | C30: 210 Clinical Operations | D30: Caroline Cooper | E30: CW | F30: 03 - Sr. Manager | G30: Senior Manager, Clinical Site Operations | H30: US Remote | K30: 2025 Q2 | L30: Hired - CW | N30: CW: Chris Page | P30: TLA | Q30: Site selection and initiation (feasibility, qualifications) and monitoring | W30: N/A - CW | X30: N/A - CW | Y30: N/A (CW) | AA30: =_xlfn.XLOOKUP($A30,'2026 Approved Budget'!$B:$B,'2026 Approved Budget'!C:C) -> #N/A | AB30: N/A (CW) | AC30: =_xlfn.XLOOKUP($A30,'2026 Approved Budget'!$B:$B,'2026 Approved Budget'!D:D) -> #N/A | AD30: =_xlfn.XLOOKUP($A30,'2026 Approved Budget'!$B:$B,'2026 Approved Budget'!E:E) -> #N/A | AE30: =_xlfn.XLOOKUP($A30,'2026 Approved Budget'!$B:$B,'2026 Approved Budget'!F:F) -> #N/A | AF30: =_xlfn.XLOOKUP($A30,'2026 Approved Budget'!$B:$B,'2026 Approved Budget'!H:H) -> #N/A
A31: 5047 | B31: Development | C31: 210 Clinical Operations | D31: Brianne Leary | E31: CW | F31: 03 - Sr. Manager | G31: Clinical Trial Lead | H31: US Remote | K31: 2025 Q4 | L31: Hired - CW | N31: CW: Jade Cao | P31: Dani | Q31: Dani program | W31: N/A - CW | X31: N/A - CW | Y31: N/A (CW) | AA31: =_xlfn.XLOOKUP($A31,'2026 Approved Budget'!$B:$B,'2026 Approved Budget'!C:C) -> #N/A | AB31: N/A (CW) | AC31: =_xlfn.XLOOKUP($A31,'2026 Approved Budget'!$B:$B,'2026 Approved Budget'!D:D) -> #N/A | AD31: =_xlfn.XLOOKUP($A31,'2026 Approved Budget'!$B:$B,'2026 Approved Budget'!E:E) -> #N/A | AE31: =_xlfn.XLOOKUP($A31,'2026 Approved Budget'!$B:$B,'2026 Approved Budget'!F:F) -> #N/A | AF31: =_xlfn.XLOOKUP($A31,'2026 Approved Budget'!$B:$B,'2026 Approved Budget'!H:H) -> #N/A
A32: 5097 | B32: Development | C32: 210 Clinical Operations | D32: Brianne Leary | E32: CW | F32: 02 - Manager | G32: Clinical Trial Manager | H32: US Remote | K32: 2025 Q2 | L32: Hired - CW | N32: CW: Jutta Durstewitz | P32: Dani | W32: N/A - Not in FP&A list | X32: N/A - Not in FP&A list | Y32: Not in FP&A list | AA32: =_xlfn.XLOOKUP($A32,'2026 Approved Budget'!$B:$B,'2026 Approved Budget'!C:C) -> #N/A | AB32: N/A (CW) | AC32: =_xlfn.XLOOKUP($A32,'2026 Approved Budget'!$B:$B,'2026 Approved Budget'!D:D) -> #N/A | AD32: =_xlfn.XLOOKUP($A32,'2026 Approved Budget'!$B:$B,'2026 Approved Budget'!E:E) -> #N/A | AE32: =_xlfn.XLOOKUP($A32,'2026 Approved Budget'!$B:$B,'2026 Approved Budget'!F:F) -> #N/A | AF32: =_xlfn.XLOOKUP($A32,'2026 Approved Budget'!$B:$B,'2026 Approved Budget'!H:H) -> #N/A
A33: 1336 | B33: Development | C33: 210 Clinical Operations | D33: Mindy Worsham | E33: CW | F33: 02 - Manager | G33: Clinical Trial Manager | H33: SSF | K33: 2025 Q3 | L33: Hired - CW | N33: CW: Anila Choudhry | P33: ATA | Q33: Clinical Trial Management | W33: N/A - CW | X33: N/A - CW | Y33: N/A (CW) | AA33: =_xlfn.XLOOKUP($A33,'2026 Approved Budget'!$B:$B,'2026 Approved Budget'!C:C) -> #N/A | AB33: N/A (CW) | AC33: =_xlfn.XLOOKUP($A33,'2026 Approved Budget'!$B:$B,'2026 Approved Budget'!D:D) -> #N/A | AD33: =_xlfn.XLOOKUP($A33,'2026 Approved Budget'!$B:$B,'2026 Approved Budget'!E:E) -> #N/A | AE33: =_xlfn.XLOOKUP($A33,'2026 Approved Budget'!$B:$B,'2026 Approved Budget'!F:F) -> #N/A | AF33: =_xlfn.XLOOKUP($A33,'2026 Approved Budget'!$B:$B,'2026 Approved Budget'!H:H) -> #N/A
A34: 1353 | B34: Development | C34: 210 Clinical Operations | D34: Jody Dosanjh | E34: CW | F34: 02 - Manager | G34: Sr. Clinical Trial Manager | H34: US Remote | K34: 2025 Q3 | L34: Hired - CW | N34: CW: Suzette Warren | P34: Dani | W34: N/A - CW | X34: N/A - CW | Y34: N/A (CW) | AA34: =_xlfn.XLOOKUP($A34,'2026 Approved Budget'!$B:$B,'2026 Approved Budget'!C:C) -> #N/A | AB34: N/A (CW) | AC34: =_xlfn.XLOOKUP($A34,'2026 Approved Budget'!$B:$B,'2026 Approved Budget'!D:D) -> #N/A | AD34: =_xlfn.XLOOKUP($A34,'2026 Approved Budget'!$B:$B,'2026 Approved Budget'!E:E) -> #N/A | AE34: =_xlfn.XLOOKUP($A34,'2026 Approved Budget'!$B:$B,'2026 Approved Budget'!F:F) -> #N/A | AF34: =_xlfn.XLOOKUP($A34,'2026 Approved Budget'!$B:$B,'2026 Approved Budget'!H:H) -> #N/A
A35: 1371 | B35: Development | C35: 210 Clinical Operations | D35: Mandy Lin | E35: CW | F35: 02 - Manager | G35: Clinical Trial Manager | H35: SSF | K35: 2025 Q3 | L35: Hired - CW | N35: CW: Mandeep Grewal | P35: ATA | S35: Now | W35: N/A - CW | X35: N/A - CW | Y35: N/A (CW) | AA35: =_xlfn.XLOOKUP($A35,'2026 Approved Budget'!$B:$B,'2026 Approved Budget'!C:C) -> #N/A | AB35: N/A (CW) | AC35: =_xlfn.XLOOKUP($A35,'2026 Approved Budget'!$B:$B,'2026 Approved Budget'!D:D) -> #N/A | AD35: =_xlfn.XLOOKUP($A35,'2026 Approved Budget'!$B:$B,'2026 Approved Budget'!E:E) -> #N/A | AE35: =_xlfn.XLOOKUP($A35,'2026 Approved Budget'!$B:$B,'2026 Approved Budget'!F:F) -> #N/A | AF35: =_xlfn.XLOOKUP($A35,'2026 Approved Budget'!$B:$B,'2026 Approved Budget'!H:H) -> #N/A
A36: 1054 | B36: Development | C36: 210 Clinical Operations | D36: Jessica Kim | E36: CW | F36: 01 - Below Manager | G36: Sr. Clinical Trial Associate | H36: US Remote | K36: 2024 Q4 | L36: Hired - CW | N36: CW: Miranda Rhudy | P36: TLA | Q36: Clinical project mgmt support | W36: N/A - CW | X36: N/A - CW | Y36: N/A (CW) | AA36: =_xlfn.XLOOKUP($A36,'2026 Approved Budget'!$B:$B,'2026 Approved Budget'!C:C) -> #N/A | AB36: N/A (CW) | AC36: =_xlfn.XLOOKUP($A36,'2026 Approved Budget'!$B:$B,'2026 Approved Budget'!D:D) -> #N/A | AD36: =_xlfn.XLOOKUP($A36,'2026 Approved Budget'!$B:$B,'2026 Approved Budget'!E:E) -> #N/A | AE36: =_xlfn.XLOOKUP($A36,'2026 Approved Budget'!$B:$B,'2026 Approved Budget'!F:F) -> #N/A | AF36: =_xlfn.XLOOKUP($A36,'2026 Approved Budget'!$B:$B,'2026 Approved Budget'!H:H) -> #N/A
A37: 1053 | B37: Development | C37: 210 Clinical Operations | D37: Brianne Leary | E37: CW | F37: 01 - Below Manager | G37: Sr. Clinical Trial Associate | H37: SSF | K37: 2025 Q3 | L37: Hired - CW | N37: CW: Karrin Huang | P37: Dani | Q37: Clinical project mgmt support | W37: N/A - CW | X37: N/A - CW | Y37: N/A (CW) | AA37: =_xlfn.XLOOKUP($A37,'2026 Approved Budget'!$B:$B,'2026 Approved Budget'!C:C) -> #N/A | AB37: N/A (CW) | AC37: =_xlfn.XLOOKUP($A37,'2026 Approved Budget'!$B:$B,'2026 Approved Budget'!D:D) -> #N/A | AD37: =_xlfn.XLOOKUP($A37,'2026 Approved Budget'!$B:$B,'2026 Approved Budget'!E:E) -> #N/A | AE37: =_xlfn.XLOOKUP($A37,'2026 Approved Budget'!$B:$B,'2026 Approved Budget'!F:F) -> #N/A | AF37: =_xlfn.XLOOKUP($A37,'2026 Approved Budget'!$B:$B,'2026 Approved Budget'!H:H) -> #N/A
A38: 5360 | B38: Development | C38: 215 Clinical Development | D38: Jay Edelberg | E38: FTE | F38: 08 - VP | G38: VP, Clinical Development | H38: PNJ | I38: 3 | J38: Program | K38: 2026 Q1 | M38: Linda | P38: TLA | Q38: TBD | W38: 1. In line with Budget | X38: 3. Accelerated | Y38: Included In Budget (Open Role) | Z38: x | AA38: =_xlfn.XLOOKUP($A38,'2026 Approved Budget'!$B:$B,'2026 Approved Budget'!C:C) -> 205 Executive Development | AB38: Confirm w/ P&C | AC38: =_xlfn.XLOOKUP($A38,'2026 Approved Budget'!$B:$B,'2026 Approved Budget'!D:D) -> TBD | AD38: =_xlfn.XLOOKUP($A38,'2026 Approved Budget'!$B:$B,'2026 Approved Budget'!E:E) -> 08. VP | AE38: =_xlfn.XLOOKUP($A38,'2026 Approved Budget'!$B:$B,'2026 Approved Budget'!F:F) -> SVP, Clinical Development | AF38: =_xlfn.XLOOKUP($A38,'2026 Approved Budget'!$B:$B,'2026 Approved Budget'!H:H) -> 46371 | AG38: keep / key
A39: 5384 | B39: Development | C39: 210 Clinical Operations | D39: Jaclyn Patterson | E39: FTE | F39: 08 - VP | G39: Head of Development Services | H39: PNJ | I39: 4 | J39: Program | K39: 2026 Q1 | L39: Open | M39: Kim | P39: UA | W39: 3. Upgrade | X39: 3. Accelerated | Y39: Included In Budget (Open Role) | Z39: x | AA39: =_xlfn.XLOOKUP($A39,'2026 Approved Budget'!$B:$B,'2026 Approved Budget'!C:C) -> 901 Executive G&A | AB39: Confirm w/ P&C | AC39: =_xlfn.XLOOKUP($A39,'2026 Approved Budget'!$B:$B,'2026 Approved Budget'!D:D) -> TBD | AD39: =_xlfn.XLOOKUP($A39,'2026 Approved Budget'!$B:$B,'2026 Approved Budget'!E:E) -> 05. Director | AE39: =_xlfn.XLOOKUP($A39,'2026 Approved Budget'!$B:$B,'2026 Approved Budget'!F:F) -> Buffer Role | AF39: =_xlfn.XLOOKUP($A39,'2026 Approved Budget'!$B:$B,'2026 Approved Budget'!H:H) -> 46280 | AG39: Buffer role
A40: 1048 | B40: Development | C40: 210 Clinical Operations | D40: Jaclyn Patterson | E40: FTE | F40: 08 - VP | G40: VP, Head of Clinical Operations | H40: PNJ | I40: 5 | J40: Program | K40: 2026 Q2 | L40: Open | M40: Kim | N40: BACKFILL: Brianne L. | P40: UA | Q40: Development Operations | T40: Upgraded role to VP Clin Ops | W40: 3. Upgrade | X40: 1. In line with Budget | Y40: Included In Budget (Open Role) | Z40: x | AA40: =_xlfn.XLOOKUP($A40,'2026 Approved Budget'!$B:$B,'2026 Approved Budget'!C:C) -> 210 Clinical Operations | AB40: OK | AC40: =_xlfn.XLOOKUP($A40,'2026 Approved Budget'!$B:$B,'2026 Approved Budget'!D:D) -> Brianne Leary | AD40: =_xlfn.XLOOKUP($A40,'2026 Approved Budget'!$B:$B,'2026 Approved Budget'!E:E) -> 06. Sr. Director | AE40: =_xlfn.XLOOKUP($A40,'2026 Approved Budget'!$B:$B,'2026 Approved Budget'!F:F) -> Senior Director, Development Operations | AF40: =_xlfn.XLOOKUP($A40,'2026 Approved Budget'!$B:$B,'2026 Approved Budget'!H:H) -> 45342
A41: 1020 | B41: Development | C41: 221 Clinical Data Management | D41: Jaclyn Patterson | E41: FTE | F41: 07 - Exec. Director | G41: Executive Director, Head of CDM | H41: SSF | I41: 6 | J41: Program | K41: 2026 Q2 | M41: Kim | N41: BACKFILL: Lauren Cao | P41: TLA-Dani | Q41: Head of Clinical Data Management | W41: 3. Upgrade | X41: 1. In line with Budget | Y41: Included In Budget (Current FTE) | Z41: x | AA41: =_xlfn.XLOOKUP($A41,'2026 Approved Budget'!$B:$B,'2026 Approved Budget'!C:C) -> 221 Clinical Data Management | AB41: OK | AC41: =_xlfn.XLOOKUP($A41,'2026 Approved Budget'!$B:$B,'2026 Approved Budget'!D:D) -> Lauren Cao | AD41: =_xlfn.XLOOKUP($A41,'2026 Approved Budget'!$B:$B,'2026 Approved Budget'!E:E) -> 06. Sr. Director | AE41: =_xlfn.XLOOKUP($A41,'2026 Approved Budget'!$B:$B,'2026 Approved Budget'!F:F) -> Senior Director, Clinical Data Management | AF41: =_xlfn.XLOOKUP($A41,'2026 Approved Budget'!$B:$B,'2026 Approved Budget'!H:H) -> 45572
A42: 5026 | B42: Development | C42: 221 Clinical Data Management | D42: Lauren Cao | E42: FTE | F42: 04 - Assoc. Director | G42: Associate Director, Data Management | H42: SSF or PNJ | I42: 7 | J42: Program | K42: 2026 Q1 | L42: Open | M42: Linda | P42: Dani | Q42: Lead DM for DAN-301, CRO oversight, DM data quality and flow management | R42: lead DAN-301 DM CRO to DB Lock and filing | S42: DAN-301 baseline readout coordination start | U42: 01 - Data Readout | W42: 1. In line with Budget | X42: 1. In line with Budget | Y42: Included In Budget (Open Role) | Z42: x | AA42: =_xlfn.XLOOKUP($A42,'2026 Approved Budget'!$B:$B,'2026 Approved Budget'!C:C) -> 220 Clinical Data Science | AB42: Confirm w/ P&C | AC42: =_xlfn.XLOOKUP($A42,'2026 Approved Budget'!$B:$B,'2026 Approved Budget'!D:D) -> TBD | AD42: =_xlfn.XLOOKUP($A42,'2026 Approved Budget'!$B:$B,'2026 Approved Budget'!E:E) -> 04. AD / Staff Scientist | AE42: =_xlfn.XLOOKUP($A42,'2026 Approved Budget'!$B:$B,'2026 Approved Budget'!F:F) -> Associate Director, Data Management | AF42: =_xlfn.XLOOKUP($A42,'2026 Approved Budget'!$B:$B,'2026 Approved Budget'!H:H) -> 46096
A43: 5036 | B43: Development | C43: 215 Clinical Development | D43: Liz Moore | E43: FTE | F43: 04 - Assoc. Director | G43: Clinical Scientist | H43: PNJ | I43: 8 | J43: Program | K43: 2026 Q3 | M43: Linda | P43: TLA | R43: Immediate need given breadth of current program | T43: Experienced Leader | U43: 02 - Data Trigger | V43: Potential Tradeoff | W43: 3. Upgrade | X43: 1. In line with Budget | Y43: Included In Budget (Open Role) | Z43: x | AA43: =_xlfn.XLOOKUP($A43,'2026 Approved Budget'!$B:$B,'2026 Approved Budget'!C:C) -> 215 Clinical Development | AB43: OK | AC43: =_xlfn.XLOOKUP($A43,'2026 Approved Budget'!$B:$B,'2026 Approved Budget'!D:D) -> TBD | AD43: =_xlfn.XLOOKUP($A43,'2026 Approved Budget'!$B:$B,'2026 Approved Budget'!E:E) -> 04. AD / Staff Scientist | AE43: =_xlfn.XLOOKUP($A43,'2026 Approved Budget'!$B:$B,'2026 Approved Budget'!F:F) -> Clinical Scientist | AF43: =_xlfn.XLOOKUP($A43,'2026 Approved Budget'!$B:$B,'2026 Approved Budget'!H:H) -> 46280 | AG43: gate to data (sept)
A44: 5006 | B44: Development | C44: 220 Clinical Data Science | D44: VP Biometrics | E44: FTE | F44: 07 - Exec. Director | G44: Executive Director, Head of Data Analytics | H44: SSF | I44: 9 | J44: Program | K44: 2026 Q2 | L44: Open | M44: Kim | P44: UA | Q44: infrastructure and process build, increase efficiency | U44: 01 - Data Readout | W44: 3. Upgrade | X44: 2. Delayed | Y44: Included In Budget (Open Role) | Z44: x | AA44: =_xlfn.XLOOKUP($A44,'2026 Approved Budget'!$B:$B,'2026 Approved Budget'!C:C) -> 220 Clinical Data Science | AB44: OK | AC44: =_xlfn.XLOOKUP($A44,'2026 Approved Budget'!$B:$B,'2026 Approved Budget'!D:D) -> TBD | AD44: =_xlfn.XLOOKUP($A44,'2026 Approved Budget'!$B:$B,'2026 Approved Budget'!E:E) -> 06. Sr. Director | AE44: =_xlfn.XLOOKUP($A44,'2026 Approved Budget'!$B:$B,'2026 Approved Budget'!F:F) -> Head of Data Analytics | AF44: =_xlfn.XLOOKUP($A44,'2026 Approved Budget'!$B:$B,'2026 Approved Budget'!H:H) -> 46096
A45: 5046 | B45: Development | C45: 215 Clinical Development | D45: Jay Edelberg | E45: FTE | F45: 08 - VP | G45: VP, Clinical Development | H45: PNJ | I45: 10 | J45: Program | K45: 2026 Q2 | M45: Linda | P45: Dani | R45: Immediate need given breadth of current program | T45: Experienced Leader | U45: 02 - Data Trigger | W45: 3. Upgrade | X45: 1. In line with Budget | Y45: Included In Budget (Open Role) | Z45: x | AA45: =_xlfn.XLOOKUP($A45,'2026 Approved Budget'!$B:$B,'2026 Approved Budget'!C:C) -> 215 Clinical Development | AB45: OK | AC45: =_xlfn.XLOOKUP($A45,'2026 Approved Budget'!$B:$B,'2026 Approved Budget'!D:D) -> TBD | AD45: =_xlfn.XLOOKUP($A45,'2026 Approved Budget'!$B:$B,'2026 Approved Budget'!E:E) -> 06. Sr. Director | AE45: =_xlfn.XLOOKUP($A45,'2026 Approved Budget'!$B:$B,'2026 Approved Budget'!F:F) -> Senior Director of Clinical Development | AF45: =_xlfn.XLOOKUP($A45,'2026 Approved Budget'!$B:$B,'2026 Approved Budget'!H:H) -> 46188 | AG45: keep / key
A46: 5096 | B46: Development | C46: 210 Clinical Operations | D46: Brianne Leary | E46: FTE | F46: 02 - Manager | G46: Clinical Trial Manager | H46: PNJ | I46: 11 | K46: 2026 Q1 | M46: Kim | P46: Dani | U46: 01 - Data Readout | W46: 1. In line with Budget | X46: 3. Accelerated | Y46: Included In Budget (Open Role) | Z46: x | AA46: =_xlfn.XLOOKUP($A46,'2026 Approved Budget'!$B:$B,'2026 Approved Budget'!C:C) -> 210 Clinical Operations | AB46: OK | AC46: =_xlfn.XLOOKUP($A46,'2026 Approved Budget'!$B:$B,'2026 Approved Budget'!D:D) -> TBD | AD46: =_xlfn.XLOOKUP($A46,'2026 Approved Budget'!$B:$B,'2026 Approved Budget'!E:E) -> 02. Manager / Scientist | AE46: =_xlfn.XLOOKUP($A46,'2026 Approved Budget'!$B:$B,'2026 Approved Budget'!F:F) -> Clinical Trial Manager | AF46: =_xlfn.XLOOKUP($A46,'2026 Approved Budget'!$B:$B,'2026 Approved Budget'!H:H) -> 46188
A47: 1333 | B47: Development | C47: 220 Clinical Data Science | D47: Angela Gao | E47: FTE | F47: 04 - Assoc. Director | G47: Associate Director, Biostatistics | H47: SSF | I47: 12 | K47: 2026 Q1 | L47: Open | M47: Linda | P47: Dani | Q47: Biostat study lead | S47: Gate on receiving data - confidence in TLA, dedicated new studies, designing a registrational study | U47: 01 - Data Readout | W47: 1. In line with Budget | X47: 1. In line with Budget | Y47: Included In Budget (Open Role) | Z47: x | AA47: =_xlfn.XLOOKUP($A47,'2026 Approved Budget'!$B:$B,'2026 Approved Budget'!C:C) -> 220 Clinical Data Science | AB47: OK | AC47: =_xlfn.XLOOKUP($A47,'2026 Approved Budget'!$B:$B,'2026 Approved Budget'!D:D) -> TBD | AD47: =_xlfn.XLOOKUP($A47,'2026 Approved Budget'!$B:$B,'2026 Approved Budget'!E:E) -> 04. AD / Staff Scientist | AE47: =_xlfn.XLOOKUP($A47,'2026 Approved Budget'!$B:$B,'2026 Approved Budget'!F:F) -> Associate Director, Biostatistician Dani | AF47: =_xlfn.XLOOKUP($A47,'2026 Approved Budget'!$B:$B,'2026 Approved Budget'!H:H) -> 46096
A48: 5050 | B48: Development | C48: 220 Clinical Data Science | D48: Wanying Li | E48: FTE | F48: 03 - Sr. Manager | G48: Stats Programming Study Lead | H48: SSF or PNJ | I48: 13 | K48: 2026 Q2 | M48: Linda | P48: TLA | U48: 01 - Data Readout | W48: 1. In line with Budget | X48: 1. In line with Budget | Y48: Included In Budget (Open Role) | Z48: x | AA48: =_xlfn.XLOOKUP($A48,'2026 Approved Budget'!$B:$B,'2026 Approved Budget'!C:C) -> 220 Clinical Data Science | AB48: Confirm w/ P&C | AC48: =_xlfn.XLOOKUP($A48,'2026 Approved Budget'!$B:$B,'2026 Approved Budget'!D:D) -> TBD | AD48: =_xlfn.XLOOKUP($A48,'2026 Approved Budget'!$B:$B,'2026 Approved Budget'!E:E) -> 03. Sr. Manager / Sr. Scientist | AE48: =_xlfn.XLOOKUP($A48,'2026 Approved Budget'!$B:$B,'2026 Approved Budget'!F:F) -> Stats Programming Study Lead | AF48: =_xlfn.XLOOKUP($A48,'2026 Approved Budget'!$B:$B,'2026 Approved Budget'!H:H) -> 46188
A49: 1322 | B49: Development | C49: 210 Clinical Operations | D49: Andrea Koh | E49: CW | F49: 05 - Director | G49: Dev Business Operations | H49: US Remote | K49: 2026 Q1 | N49: CW: Pam Foster Wiley | P49: UA | Q49: Clinical Contracts specialist | U49: 01 - Data Readout | W49: N/A - CW | X49: N/A - CW | Y49: N/A (CW) | AA49: =_xlfn.XLOOKUP($A49,'2026 Approved Budget'!$B:$B,'2026 Approved Budget'!C:C) -> #N/A | AB49: N/A (CW) | AC49: =_xlfn.XLOOKUP($A49,'2026 Approved Budget'!$B:$B,'2026 Approved Budget'!D:D) -> #N/A | AD49: =_xlfn.XLOOKUP($A49,'2026 Approved Budget'!$B:$B,'2026 Approved Budget'!E:E) -> #N/A | AE49: =_xlfn.XLOOKUP($A49,'2026 Approved Budget'!$B:$B,'2026 Approved Budget'!F:F) -> #N/A | AF49: =_xlfn.XLOOKUP($A49,'2026 Approved Budget'!$B:$B,'2026 Approved Budget'!H:H) -> #N/A
A50: 5073 | B50: Development | C50: 210 Clinical Operations | D50: Andrea Koh | E50: CW | F50: 05 - Director | G50: Clinical Site Contracts | H50: PNJ | K50: 2026 Q1 | P50: UA | U50: 01 - Data Readout | W50: N/A - CW | X50: N/A - CW | Y50: N/A (CW) | AA50: =_xlfn.XLOOKUP($A50,'2026 Approved Budget'!$B:$B,'2026 Approved Budget'!C:C) -> #N/A | AB50: N/A (CW) | AC50: =_xlfn.XLOOKUP($A50,'2026 Approved Budget'!$B:$B,'2026 Approved Budget'!D:D) -> #N/A | AD50: =_xlfn.XLOOKUP($A50,'2026 Approved Budget'!$B:$B,'2026 Approved Budget'!E:E) -> #N/A | AE50: =_xlfn.XLOOKUP($A50,'2026 Approved Budget'!$B:$B,'2026 Approved Budget'!F:F) -> #N/A | AF50: =_xlfn.XLOOKUP($A50,'2026 Approved Budget'!$B:$B,'2026 Approved Budget'!H:H) -> #N/A
A51: 5392 | B51: Development | C51: 210 Clinical Operations | D51: Brianne Leary | E51: CW | F51: 05 - Director | G51: Clinical Trial Liaison (EU/UK) | H51: US Remote | K51: 2026 Q1 | P51: UA | W51: N/A - CW | X51: N/A - CW | Y51: N/A (CW) | AA51: =_xlfn.XLOOKUP($A51,'2026 Approved Budget'!$B:$B,'2026 Approved Budget'!C:C) -> #N/A | AB51: N/A (CW) | AC51: =_xlfn.XLOOKUP($A51,'2026 Approved Budget'!$B:$B,'2026 Approved Budget'!D:D) -> #N/A | AD51: =_xlfn.XLOOKUP($A51,'2026 Approved Budget'!$B:$B,'2026 Approved Budget'!E:E) -> #N/A | AE51: =_xlfn.XLOOKUP($A51,'2026 Approved Budget'!$B:$B,'2026 Approved Budget'!F:F) -> #N/A | AF51: =_xlfn.XLOOKUP($A51,'2026 Approved Budget'!$B:$B,'2026 Approved Budget'!H:H) -> #N/A
A52: 1043 | B52: Development | C52: 210 Clinical Operations | D52: Sanjay Patel | E52: FTE | F52: 04 - Assoc. Director | G52: Clinical Trial Lead | H52: SSF | I52: 14 | K52: 2026 Q2 | L52: Open | M52: Kim | N52: BACKFILL: Anyi Ihiasota | P52: ATA | Q52: Site Monitoring, Inspection Readiness | W52: 3. Upgrade | X52: 2. Delayed | Y52: Included In Budget (Open Role) | Z52: x | AA52: =_xlfn.XLOOKUP($A52,'2026 Approved Budget'!$B:$B,'2026 Approved Budget'!C:C) -> 210 Clinical Operations | AB52: OK | AC52: =_xlfn.XLOOKUP($A52,'2026 Approved Budget'!$B:$B,'2026 Approved Budget'!D:D) -> Anyi Ihiasota | AD52: =_xlfn.XLOOKUP($A52,'2026 Approved Budget'!$B:$B,'2026 Approved Budget'!E:E) -> 03. Sr. Manager / Sr. Scientist | AE52: =_xlfn.XLOOKUP($A52,'2026 Approved Budget'!$B:$B,'2026 Approved Budget'!F:F) -> Clinical Trial Lead | AF52: =_xlfn.XLOOKUP($A52,'2026 Approved Budget'!$B:$B,'2026 Approved Budget'!H:H) -> 45740
A53: 5077 | B53: Development | C53: 210 Clinical Operations | D53: Andrea Koh | E53: FTE | F53: 04 - Assoc. Director | G53: Development Business Operations | H53: SSF | I53: 15 | K53: 2026 Q1 | L53: Open | M53: Linda | P53: UA | U53: 01 - Data Readout | W53: 1. In line with Budget | X53: 1. In line with Budget | Y53: Included In Budget (Open Role) | Z53: x | AA53: =_xlfn.XLOOKUP($A53,'2026 Approved Budget'!$B:$B,'2026 Approved Budget'!C:C) -> 210 Clinical Operations | AB53: OK | AC53: =_xlfn.XLOOKUP($A53,'2026 Approved Budget'!$B:$B,'2026 Approved Budget'!D:D) -> TBD | AD53: =_xlfn.XLOOKUP($A53,'2026 Approved Budget'!$B:$B,'2026 Approved Budget'!E:E) -> 04. AD / Staff Scientist | AE53: =_xlfn.XLOOKUP($A53,'2026 Approved Budget'!$B:$B,'2026 Approved Budget'!F:F) -> Development Business Operations | AF53: =_xlfn.XLOOKUP($A53,'2026 Approved Budget'!$B:$B,'2026 Approved Budget'!H:H) -> 46096
A54: 5385 | B54: Development | C54: 210 Clinical Operations | D54: Jaclyn Patterson | E54: FTE | F54: 07 - Exec. Director | G54: Head of Global Site Management | H54: PNJ | I54: 16 | K54: 2026 Q1 | L54: Open | M54: Kim | P54: UA | W54: 3. Upgrade | X54: 3. Accelerated | Y54: Included In Budget (Open Role) | Z54: x | AA54: =_xlfn.XLOOKUP($A54,'2026 Approved Budget'!$B:$B,'2026 Approved Budget'!C:C) -> 901 Executive G&A | AB54: Confirm w/ P&C | AC54: =_xlfn.XLOOKUP($A54,'2026 Approved Budget'!$B:$B,'2026 Approved Budget'!D:D) -> TBD | AD54: =_xlfn.XLOOKUP($A54,'2026 Approved Budget'!$B:$B,'2026 Approved Budget'!E:E) -> 05. Director | AE54: =_xlfn.XLOOKUP($A54,'2026 Approved Budget'!$B:$B,'2026 Approved Budget'!F:F) -> Buffer Role | AF54: =_xlfn.XLOOKUP($A54,'2026 Approved Budget'!$B:$B,'2026 Approved Budget'!H:H) -> 46280 | AG54: Buffer role
A55: 5386 | B55: Development | C55: 210 Clinical Operations | D55: Jaclyn Patterson | E55: FTE | F55: 07 - Exec. Director | G55: Development Business Operations | H55: PNJ | I55: 17 | K55: 2026 Q1 | L55: Open | M55: Kim | P55: UA | W55: 3. Upgrade | X55: 3. Accelerated | Y55: Included In Budget (Open Role) | Z55: x | AA55: =_xlfn.XLOOKUP($A55,'2026 Approved Budget'!$B:$B,'2026 Approved Budget'!C:C) -> 901 Executive G&A | AB55: Confirm w/ P&C | AC55: =_xlfn.XLOOKUP($A55,'2026 Approved Budget'!$B:$B,'2026 Approved Budget'!D:D) -> TBD | AD55: =_xlfn.XLOOKUP($A55,'2026 Approved Budget'!$B:$B,'2026 Approved Budget'!E:E) -> 05. Director | AE55: =_xlfn.XLOOKUP($A55,'2026 Approved Budget'!$B:$B,'2026 Approved Budget'!F:F) -> Buffer Role | AF55: =_xlfn.XLOOKUP($A55,'2026 Approved Budget'!$B:$B,'2026 Approved Budget'!H:H) -> 46280 | AG55: Buffer role
A56: 5102 | B56: Development | C56: 210 Clinical Operations | D56: Caroline Cooper | E56: CW | F56: 03 - Sr. Manager | G56: Clinical Trial Lead | H56: PNJ | K56: 2026 Q1 | N56: CW: Heather Fraser | P56: TLA | U56: 01 - Data Readout | W56: N/A - CW | X56: N/A - CW | Y56: N/A (CW) | AA56: =_xlfn.XLOOKUP($A56,'2026 Approved Budget'!$B:$B,'2026 Approved Budget'!C:C) -> #N/A | AB56: N/A (CW) | AC56: =_xlfn.XLOOKUP($A56,'2026 Approved Budget'!$B:$B,'2026 Approved Budget'!D:D) -> #N/A | AD56: =_xlfn.XLOOKUP($A56,'2026 Approved Budget'!$B:$B,'2026 Approved Budget'!E:E) -> #N/A | AE56: =_xlfn.XLOOKUP($A56,'2026 Approved Budget'!$B:$B,'2026 Approved Budget'!F:F) -> #N/A | AF56: =_xlfn.XLOOKUP($A56,'2026 Approved Budget'!$B:$B,'2026 Approved Budget'!H:H) -> #N/A
A57: 5074 | B57: Development | C57: 210 Clinical Operations | D57: Brianne Leary | E57: CW | F57: 03 - Sr. Manager | G57: TMF Lead | H57: PNJ | K57: 2026 Q2 | P57: UA | W57: N/A - CW | X57: N/A - CW | Y57: N/A (CW) | AA57: =_xlfn.XLOOKUP($A57,'2026 Approved Budget'!$B:$B,'2026 Approved Budget'!C:C) -> #N/A | AB57: N/A (CW) | AC57: =_xlfn.XLOOKUP($A57,'2026 Approved Budget'!$B:$B,'2026 Approved Budget'!D:D) -> #N/A | AD57: =_xlfn.XLOOKUP($A57,'2026 Approved Budget'!$B:$B,'2026 Approved Budget'!E:E) -> #N/A | AE57: =_xlfn.XLOOKUP($A57,'2026 Approved Budget'!$B:$B,'2026 Approved Budget'!F:F) -> #N/A | AF57: =_xlfn.XLOOKUP($A57,'2026 Approved Budget'!$B:$B,'2026 Approved Budget'!H:H) -> #N/A
A58: 1369 | B58: Development | C58: 210 Clinical Operations | D58: Brianne Leary | E58: FTE | F58: 03 - Sr. Manager | G58: Clinical Trial Lead | H58: PNJ | I58: 18 | K58: 2026 Q1 | M58: Kim | P58: Dani | Q58: US regional Lead for DAN-301 and DAN-302 | S58: Now | U58: 01 - Data Readout | W58: 1. In line with Budget | X58: 1. In line with Budget | Y58: Included In Budget (Open Role) | Z58: x | AA58: =_xlfn.XLOOKUP($A58,'2026 Approved Budget'!$B:$B,'2026 Approved Budget'!C:C) -> 210 Clinical Operations | AB58: OK | AC58: =_xlfn.XLOOKUP($A58,'2026 Approved Budget'!$B:$B,'2026 Approved Budget'!D:D) -> TBD | AD58: =_xlfn.XLOOKUP($A58,'2026 Approved Budget'!$B:$B,'2026 Approved Budget'!E:E) -> 03. Sr. Manager / Sr. Scientist | AE58: =_xlfn.XLOOKUP($A58,'2026 Approved Budget'!$B:$B,'2026 Approved Budget'!F:F) -> Clinical Trial Lead (dani) | AF58: =_xlfn.XLOOKUP($A58,'2026 Approved Budget'!$B:$B,'2026 Approved Budget'!H:H) -> 46096
A59: 5150 | B59: Development | C59: 235 Regulatory | D59: Stu Heminway | E59: FTE | F59: 04 - Assoc. Director | G59: Assoc. Director, Regulatory Strategy (TLA/ATA) | H59: SSF | I59: 19 | K59: 2026 Q2 | M59: Yen | P59: UA | Q59: Regulatory Strategy | S59: Phase 3 initiations | U59: 01 - Data Readout | V59: Potential Tradeoff | W59: 1. In line with Budget | X59: 1. In line with Budget | Y59: Included In Budget (Open Role) | Z59: x | AA59: =_xlfn.XLOOKUP($A59,'2026 Approved Budget'!$B:$B,'2026 Approved Budget'!C:C) -> 235 Regulatory | AB59: OK | AC59: =_xlfn.XLOOKUP($A59,'2026 Approved Budget'!$B:$B,'2026 Approved Budget'!D:D) -> TBD | AD59: =_xlfn.XLOOKUP($A59,'2026 Approved Budget'!$B:$B,'2026 Approved Budget'!E:E) -> 04. AD / Staff Scientist | AE59: =_xlfn.XLOOKUP($A59,'2026 Approved Budget'!$B:$B,'2026 Approved Budget'!F:F) -> Associate Director, Regulatory Strategy (TLA/ATA) | AF59: =_xlfn.XLOOKUP($A59,'2026 Approved Budget'!$B:$B,'2026 Approved Budget'!H:H) -> 46188 | AG59: Potentially delay…
A60: 5153 | B60: Development | C60: 235 Regulatory | D60: Nicole Hilgraf | E60: FTE | F60: 06 - Sr. Director | G60: Sr. Director, CMC Regulatory (ATA) | H60: PNJ | I60: 20 | K60: 2026 Q3 | P60: UA | Q60: CMC Regulatory | S60: Phase 3 initiations | U60: 01 - Data Readout | W60: 1. In line with Budget | X60: 1. In line with Budget | Y60: Included In Budget (Open Role) | Z60: x | AA60: =_xlfn.XLOOKUP($A60,'2026 Approved Budget'!$B:$B,'2026 Approved Budget'!C:C) -> 235 Regulatory | AB60: OK | AC60: =_xlfn.XLOOKUP($A60,'2026 Approved Budget'!$B:$B,'2026 Approved Budget'!D:D) -> TBD | AD60: =_xlfn.XLOOKUP($A60,'2026 Approved Budget'!$B:$B,'2026 Approved Budget'!E:E) -> 06. Sr. Director | AE60: =_xlfn.XLOOKUP($A60,'2026 Approved Budget'!$B:$B,'2026 Approved Budget'!F:F) -> Sr. Director, CMC Regulatory (ATA) | AF60: =_xlfn.XLOOKUP($A60,'2026 Approved Budget'!$B:$B,'2026 Approved Budget'!H:H) -> 46280 | AG60: Delay to Q3; NDA submission
A61: 5152 | B61: Development | C61: 235 Regulatory | D61: Stu Heminway | E61: FTE | F61: 06 - Sr. Director | G61: Sr. Director, Regulatory Science Communication (X-portfolio) | H61: SSF or PNJ | I61: 21 | K61: 2026 Q2 | M61: Yen | P61: UA | Q61: Regulatory Science Communication | S61: Submission authoring and oversight including Medical Writers for Filing Teams | V61: Keep | W61: 1. In line with Budget | X61: 1. In line with Budget | Y61: Included In Budget (Open Role) | Z61: x | AA61: =_xlfn.XLOOKUP($A61,'2026 Approved Budget'!$B:$B,'2026 Approved Budget'!C:C) -> 235 Regulatory | AB61: OK | AC61: =_xlfn.XLOOKUP($A61,'2026 Approved Budget'!$B:$B,'2026 Approved Budget'!D:D) -> TBD | AD61: =_xlfn.XLOOKUP($A61,'2026 Approved Budget'!$B:$B,'2026 Approved Budget'!E:E) -> 06. Sr. Director | AE61: =_xlfn.XLOOKUP($A61,'2026 Approved Budget'!$B:$B,'2026 Approved Budget'!F:F) -> Sr. Director, Regulatory Science Communication (X-portfolio) | AF61: =_xlfn.XLOOKUP($A61,'2026 Approved Budget'!$B:$B,'2026 Approved Budget'!H:H) -> 46188 | AG61: capacity given other hires, realistically Q2
A62: 5089 | B62: Development | C62: 210 Clinical Operations | D62: Caroline Cooper | E62: CW | F62: 01 - Below Manager | G62: Associate Clinical Trial Manager | H62: US Remote | K62: 2026 Q1 | P62: TLA | W62: N/A - CW | X62: N/A - CW | Y62: N/A (CW) | AA62: =_xlfn.XLOOKUP($A62,'2026 Approved Budget'!$B:$B,'2026 Approved Budget'!C:C) -> #N/A | AB62: N/A (CW) | AC62: =_xlfn.XLOOKUP($A62,'2026 Approved Budget'!$B:$B,'2026 Approved Budget'!D:D) -> #N/A | AD62: =_xlfn.XLOOKUP($A62,'2026 Approved Budget'!$B:$B,'2026 Approved Budget'!E:E) -> #N/A | AE62: =_xlfn.XLOOKUP($A62,'2026 Approved Budget'!$B:$B,'2026 Approved Budget'!F:F) -> #N/A | AF62: =_xlfn.XLOOKUP($A62,'2026 Approved Budget'!$B:$B,'2026 Approved Budget'!H:H) -> #N/A
A63: 5075 | B63: Development | C63: 210 Clinical Operations | D63: Brianne Leary | E63: CW | F63: 01 - Below Manager | G63: Clinical Document Specialist | H63: PNJ | K63: 2026 Q3 | P63: UA | W63: N/A - CW | X63: N/A - CW | Y63: N/A (CW) | AA63: =_xlfn.XLOOKUP($A63,'2026 Approved Budget'!$B:$B,'2026 Approved Budget'!C:C) -> #N/A | AB63: N/A (CW) | AC63: =_xlfn.XLOOKUP($A63,'2026 Approved Budget'!$B:$B,'2026 Approved Budget'!D:D) -> #N/A | AD63: =_xlfn.XLOOKUP($A63,'2026 Approved Budget'!$B:$B,'2026 Approved Budget'!E:E) -> #N/A | AE63: =_xlfn.XLOOKUP($A63,'2026 Approved Budget'!$B:$B,'2026 Approved Budget'!F:F) -> #N/A | AF63: =_xlfn.XLOOKUP($A63,'2026 Approved Budget'!$B:$B,'2026 Approved Budget'!H:H) -> #N/A
A64: 5098 | B64: Development | C64: 210 Clinical Operations | D64: Brianne Leary | E64: CW | F64: 01 - Below Manager | G64: Sr. Clinical Trial Associate | H64: PNJ | K64: 2026 Q3 | P64: Dani | W64: N/A - CW | X64: N/A - CW | Y64: N/A (CW) | AA64: =_xlfn.XLOOKUP($A64,'2026 Approved Budget'!$B:$B,'2026 Approved Budget'!C:C) -> #N/A | AB64: N/A (CW) | AC64: =_xlfn.XLOOKUP($A64,'2026 Approved Budget'!$B:$B,'2026 Approved Budget'!D:D) -> #N/A | AD64: =_xlfn.XLOOKUP($A64,'2026 Approved Budget'!$B:$B,'2026 Approved Budget'!E:E) -> #N/A | AE64: =_xlfn.XLOOKUP($A64,'2026 Approved Budget'!$B:$B,'2026 Approved Budget'!F:F) -> #N/A | AF64: =_xlfn.XLOOKUP($A64,'2026 Approved Budget'!$B:$B,'2026 Approved Budget'!H:H) -> #N/A
A65: 5393 | B65: Development | C65: 210 Clinical Operations | D65: Brianne Leary | E65: CW | F65: 01 - Below Manager | G65: eTMF Document Specialist | H65: US Remote | K65: 2026 Q4 | P65: UA | Q65: eTMF filing, QC | W65: N/A - CW | X65: N/A - CW | Y65: N/A (CW) | AA65: =_xlfn.XLOOKUP($A65,'2026 Approved Budget'!$B:$B,'2026 Approved Budget'!C:C) -> #N/A | AB65: N/A (CW) | AC65: =_xlfn.XLOOKUP($A65,'2026 Approved Budget'!$B:$B,'2026 Approved Budget'!D:D) -> #N/A | AD65: =_xlfn.XLOOKUP($A65,'2026 Approved Budget'!$B:$B,'2026 Approved Budget'!E:E) -> #N/A | AE65: =_xlfn.XLOOKUP($A65,'2026 Approved Budget'!$B:$B,'2026 Approved Budget'!F:F) -> #N/A | AF65: =_xlfn.XLOOKUP($A65,'2026 Approved Budget'!$B:$B,'2026 Approved Budget'!H:H) -> #N/A
A66: 1302 | B66: Development | C66: 208 Early Development | D66: Yehuda Cohen | E66: FTE | F66: 03 - Sr. Manager | G66: Sr. Scientist, Clinical Pharmacology | H66: PNJ | I66: 22 | K66: 2026 Q3 | P66: ATA-TLA-Dani | Q66: Clinical pharmacology | U66: 01 - Data Readout | V66: Potential Tradeoff | W66: 1. In line with Budget | X66: 1. In line with Budget | Y66: Included In Budget (Open Role) | Z66: x | AA66: =_xlfn.XLOOKUP($A66,'2026 Approved Budget'!$B:$B,'2026 Approved Budget'!C:C) -> 208 Early Development | AB66: OK | AC66: =_xlfn.XLOOKUP($A66,'2026 Approved Budget'!$B:$B,'2026 Approved Budget'!D:D) -> TBD | AD66: =_xlfn.XLOOKUP($A66,'2026 Approved Budget'!$B:$B,'2026 Approved Budget'!E:E) -> 03. Sr. Manager / Sr. Scientist | AE66: =_xlfn.XLOOKUP($A66,'2026 Approved Budget'!$B:$B,'2026 Approved Budget'!F:F) -> Sr. Scientist, Clinical Pharmacology | AF66: =_xlfn.XLOOKUP($A66,'2026 Approved Budget'!$B:$B,'2026 Approved Budget'!H:H) -> 46280 | AG66: Hire in 2027
A67: 1029 | B67: Development | C67: 215 Clinical Development | D67: Jay Edelberg | E67: FTE | F67: 07 - Exec. Director | G67: Executive Director, Clinical Lead | H67: PNJ | K67: 2024 Q2 | L67: Hired | N67: HIRED: Liz Moore | O67: 10014 | P67: ATA | Q67: Clinical Development | W67: 1. In line with Budget | X67: 1. In line with Budget | Y67: Included In Budget (Current FTE) | Z67: x | AA67: =_xlfn.XLOOKUP($A67,'2026 Approved Budget'!$B:$B,'2026 Approved Budget'!C:C) -> 215 Clinical Development | AB67: OK | AC67: =_xlfn.XLOOKUP($A67,'2026 Approved Budget'!$B:$B,'2026 Approved Budget'!D:D) -> Liz Moore | AD67: =_xlfn.XLOOKUP($A67,'2026 Approved Budget'!$B:$B,'2026 Approved Budget'!E:E) -> 07. Exec. Director | AE67: =_xlfn.XLOOKUP($A67,'2026 Approved Budget'!$B:$B,'2026 Approved Budget'!F:F) -> Executive Medical Director (Clinical Research Ataciguat) | AF67: =_xlfn.XLOOKUP($A67,'2026 Approved Budget'!$B:$B,'2026 Approved Budget'!H:H) -> 45453
A68: 1234 | B68: Development | C68: 215 Clinical Development | D68: Jay Edelberg | E68: FTE | F68: 07 - Exec. Director | G68: Executive Director, Clinical Lead | H68: PNJ | K68: 2025 Q1 | L68: Hired | N68: HIRED: Juan Maya | O68: 10168 | P68: Dani | Q68: Clinical Development Dani, DCM | T68: Experienced Leader | W68: 1. In line with Budget | X68: 1. In line with Budget | Y68: Included In Budget (Current FTE) | Z68: x | AA68: =_xlfn.XLOOKUP($A68,'2026 Approved Budget'!$B:$B,'2026 Approved Budget'!C:C) -> 215 Clinical Development | AB68: OK | AC68: =_xlfn.XLOOKUP($A68,'2026 Approved Budget'!$B:$B,'2026 Approved Budget'!D:D) -> Juan Maya | AD68: =_xlfn.XLOOKUP($A68,'2026 Approved Budget'!$B:$B,'2026 Approved Budget'!E:E) -> 07. Exec. Director | AE68: =_xlfn.XLOOKUP($A68,'2026 Approved Budget'!$B:$B,'2026 Approved Budget'!F:F) -> Executive Director, Clinical Research, Dani / DCM | AF68: =_xlfn.XLOOKUP($A68,'2026 Approved Budget'!$B:$B,'2026 Approved Budget'!H:H) -> 45726
A69: 1027 | B69: Development | C69: 215 Clinical Development | D69: Jay Edelberg | E69: FTE | F69: 06 - Sr. Director | G69: Senior Director, Clinical Lead | H69: SSF | K69: 2025 Q2 | L69: Hired | N69: HIRED: Prameela Ramesan | O69: 10209 | P69: TLA | Q69: Clinical Development | T69: Experienced Leader | W69: 1. In line with Budget | X69: 1. In line with Budget | Y69: Included In Budget (Current FTE) | Z69: x | AA69: =_xlfn.XLOOKUP($A69,'2026 Approved Budget'!$B:$B,'2026 Approved Budget'!C:C) -> 215 Clinical Development | AB69: OK | AC69: =_xlfn.XLOOKUP($A69,'2026 Approved Budget'!$B:$B,'2026 Approved Budget'!D:D) -> Prameela Ramesan | AD69: =_xlfn.XLOOKUP($A69,'2026 Approved Budget'!$B:$B,'2026 Approved Budget'!E:E) -> 06. Sr. Director | AE69: =_xlfn.XLOOKUP($A69,'2026 Approved Budget'!$B:$B,'2026 Approved Budget'!F:F) -> Sr. Medical Director (Clinical Lead TLA) | AF69: =_xlfn.XLOOKUP($A69,'2026 Approved Budget'!$B:$B,'2026 Approved Budget'!H:H) -> 45775
A70: 1318 | B70: Development | C70: 215 Clinical Development | D70: Prameela Ramesan | E70: CW | F70: 04 - Assoc. Director | G70: Clinical Scientist | H70: PNJ | K70: 2025 Q4 | L70: Hired - CW | N70: CW: Yayan Z. | P70: TLA | Q70: Aid with scientific efforts (literature search, development rationale, program documentation) | R70: Clinical Data Analysis and Interpretation needs | S70: Launch of TLA-201 (already occurred) | U70: 2025 WFP/ Back-fill | W70: N/A - CW | X70: N/A - CW | Y70: N/A (CW) | AA70: =_xlfn.XLOOKUP($A70,'2026 Approved Budget'!$B:$B,'2026 Approved Budget'!C:C) -> #N/A | AB70: N/A (CW) | AC70: =_xlfn.XLOOKUP($A70,'2026 Approved Budget'!$B:$B,'2026 Approved Budget'!D:D) -> #N/A | AD70: =_xlfn.XLOOKUP($A70,'2026 Approved Budget'!$B:$B,'2026 Approved Budget'!E:E) -> #N/A | AE70: =_xlfn.XLOOKUP($A70,'2026 Approved Budget'!$B:$B,'2026 Approved Budget'!F:F) -> #N/A | AF70: =_xlfn.XLOOKUP($A70,'2026 Approved Budget'!$B:$B,'2026 Approved Budget'!H:H) -> #N/A
A71: 1319 | B71: Development | C71: 215 Clinical Development | D71: Liz Moore | E71: CW | F71: 04 - Assoc. Director | G71: Clinical Scientist | H71: PNJ | K71: 2025 Q4 | L71: Hired - CW | N71: CW: Amelia L. | P71: ATA | Q71: Lead/Aid with scientific efforts (literature search, development rationale, program documentation) | S71: NOW: Not previously included in WFP – due to current MD shortage, this may provide faster avenue to recruitment and not require >Dir hire | T71: Accomplished Professional | U71: 01 - Data Readout | W71: N/A - CW | X71: N/A - CW | Y71: N/A (CW) | AA71: =_xlfn.XLOOKUP($A71,'2026 Approved Budget'!$B:$B,'2026 Approved Budget'!C:C) -> #N/A | AB71: N/A (CW) | AC71: =_xlfn.XLOOKUP($A71,'2026 Approved Budget'!$B:$B,'2026 Approved Budget'!D:D) -> #N/A | AD71: =_xlfn.XLOOKUP($A71,'2026 Approved Budget'!$B:$B,'2026 Approved Budget'!E:E) -> #N/A | AE71: =_xlfn.XLOOKUP($A71,'2026 Approved Budget'!$B:$B,'2026 Approved Budget'!F:F) -> #N/A | AF71: =_xlfn.XLOOKUP($A71,'2026 Approved Budget'!$B:$B,'2026 Approved Budget'!H:H) -> #N/A | AG71: consider for conversion - gated to baseline data
A72: 1368 | B72: Development | C72: 215 Clinical Development | D72: Juan Maya | E72: CW to FTE | F72: 04 - Assoc. Director | G72: Clinical Scientist | H72: PNJ | K72: 2026 Q3 | L72: Hired - CW | N72: CW: Laura Liu | P72: Dani | Q72: Aid with scientific efforts (literature search, development rationale, program documentation) | R72: Convert to FTE now/next quarter: Currently developing OLE protocol, continuing to analyze 2A data, needed for KINSHIP data analysis | W72: N/A - CW | X72: N/A - CW | Y72: N/A (CW) | AA72: =_xlfn.XLOOKUP($A72,'2026 Approved Budget'!$B:$B,'2026 Approved Budget'!C:C) -> #N/A | AB72: N/A (CW) | AC72: =_xlfn.XLOOKUP($A72,'2026 Approved Budget'!$B:$B,'2026 Approved Budget'!D:D) -> #N/A | AD72: =_xlfn.XLOOKUP($A72,'2026 Approved Budget'!$B:$B,'2026 Approved Budget'!E:E) -> #N/A | AE72: =_xlfn.XLOOKUP($A72,'2026 Approved Budget'!$B:$B,'2026 Approved Budget'!F:F) -> #N/A | AF72: =_xlfn.XLOOKUP($A72,'2026 Approved Budget'!$B:$B,'2026 Approved Budget'!H:H) -> #N/A | AG72: Convert based on P2 data
A73: 5088 | B73: Development | C73: 210 Clinical Operations | D73: Caroline Cooper | E73: FTE | F73: 03 - Sr. Manager | G73: Clinical Trial Lead | H73: PNJ | I73: 23 | K73: 2026 Q2 | M73: Kim | P73: TLA | W73: 1. In line with Budget | X73: 1. In line with Budget | Y73: Included In Budget (Open Role) | Z73: x | AA73: =_xlfn.XLOOKUP($A73,'2026 Approved Budget'!$B:$B,'2026 Approved Budget'!C:C) -> 210 Clinical Operations | AB73: OK | AC73: =_xlfn.XLOOKUP($A73,'2026 Approved Budget'!$B:$B,'2026 Approved Budget'!D:D) -> TBD | AD73: =_xlfn.XLOOKUP($A73,'2026 Approved Budget'!$B:$B,'2026 Approved Budget'!E:E) -> 03. Sr. Manager / Sr. Scientist | AE73: =_xlfn.XLOOKUP($A73,'2026 Approved Budget'!$B:$B,'2026 Approved Budget'!F:F) -> Clinical Trial Lead | AF73: =_xlfn.XLOOKUP($A73,'2026 Approved Budget'!$B:$B,'2026 Approved Budget'!H:H) -> 46188
A74: 5070 | B74: Development | C74: 210 Clinical Operations | D74: Jaclyn Patterson | E74: FTE | F74: 07 - Exec. Director | G74: Exec. Director, Document Records Management & Systems | H74: PNJ | I74: 24 | K74: 2026 Q3 | M74: Kim | P74: UA | T74: Formerly Head of eTMF role; confirm timing | W74: 3. Upgrade | X74: 2. Delayed | Y74: Included In Budget (Open Role) | Z74: x | AA74: =_xlfn.XLOOKUP($A74,'2026 Approved Budget'!$B:$B,'2026 Approved Budget'!C:C) -> 210 Clinical Operations | AB74: OK | AC74: =_xlfn.XLOOKUP($A74,'2026 Approved Budget'!$B:$B,'2026 Approved Budget'!D:D) -> TBD | AD74: =_xlfn.XLOOKUP($A74,'2026 Approved Budget'!$B:$B,'2026 Approved Budget'!E:E) -> 06. Sr. Director | AE74: =_xlfn.XLOOKUP($A74,'2026 Approved Budget'!$B:$B,'2026 Approved Budget'!F:F) -> Head of TMF Operations (ClinOps Systems) | AF74: =_xlfn.XLOOKUP($A74,'2026 Approved Budget'!$B:$B,'2026 Approved Budget'!H:H) -> 46188
A75: 5095 | B75: Development | C75: 210 Clinical Operations | D75: Jody Dosanjh | E75: FTE | F75: 01 - Below Manager | G75: Associate Clinical Trial Manager | H75: SSF | I75: 25 | K75: 2026 Q1 | M75: Linda | N75: Planned conversion for Karrin | P75: Dani | U75: 01 - Data Readout | W75: 1. In line with Budget | X75: 1. In line with Budget | Y75: Included In Budget (Open Role) | Z75: x | AA75: =_xlfn.XLOOKUP($A75,'2026 Approved Budget'!$B:$B,'2026 Approved Budget'!C:C) -> 210 Clinical Operations | AB75: OK | AC75: =_xlfn.XLOOKUP($A75,'2026 Approved Budget'!$B:$B,'2026 Approved Budget'!D:D) -> Planned conversion for Karrin | AD75: =_xlfn.XLOOKUP($A75,'2026 Approved Budget'!$B:$B,'2026 Approved Budget'!E:E) -> 01. IC / Coordinator | AE75: =_xlfn.XLOOKUP($A75,'2026 Approved Budget'!$B:$B,'2026 Approved Budget'!F:F) -> Associate Clinical Trial Manager | AF75: =_xlfn.XLOOKUP($A75,'2026 Approved Budget'!$B:$B,'2026 Approved Budget'!H:H) -> 46096
A76: 5051 | B76: Development | C76: 210 Clinical Operations | D76: Sanjay Patel | E76: FTE | F76: 03 - Sr. Manager | G76: Clinical Trial Lead | H76: PNJ | I76: 26 | K76: 2026 Q3 | P76: ATA | Q76: Regional Oversight of sites and vendor management | T76: Jaclyn to check whether this role is required in 2026 | U76: 01 - Data Readout | V76: Tradeoff or push out? | W76: 1. In line with Budget | X76: 2. Delayed | Y76: Included In Budget (Open Role) | Z76: x | AA76: =_xlfn.XLOOKUP($A76,'2026 Approved Budget'!$B:$B,'2026 Approved Budget'!C:C) -> 210 Clinical Operations | AB76: OK | AC76: =_xlfn.XLOOKUP($A76,'2026 Approved Budget'!$B:$B,'2026 Approved Budget'!D:D) -> TBD | AD76: =_xlfn.XLOOKUP($A76,'2026 Approved Budget'!$B:$B,'2026 Approved Budget'!E:E) -> 03. Sr. Manager / Sr. Scientist | AE76: =_xlfn.XLOOKUP($A76,'2026 Approved Budget'!$B:$B,'2026 Approved Budget'!F:F) -> Clinical Trial Lead | AF76: =_xlfn.XLOOKUP($A76,'2026 Approved Budget'!$B:$B,'2026 Approved Budget'!H:H) -> 46188
A77: 1047 | B77: Development | C77: 220 Clinical Data Science | D77: Jaclyn Patterson | E77: FTE | F77: 06 - Sr. Director | G77: Senior Director, Biostatistics | H77: SSF | K77: 2024 Q2 | L77: Hired | N77: HIRED: Wanying Li | O77: 10010 | P77: ATA-TLA-Dani | Q77: Biostatistics | W77: 1. In line with Budget | X77: 1. In line with Budget | Y77: Included In Budget (Current FTE) | Z77: x | AA77: =_xlfn.XLOOKUP($A77,'2026 Approved Budget'!$B:$B,'2026 Approved Budget'!C:C) -> 220 Clinical Data Science | AB77: OK | AC77: =_xlfn.XLOOKUP($A77,'2026 Approved Budget'!$B:$B,'2026 Approved Budget'!D:D) -> Wanying Li | AD77: =_xlfn.XLOOKUP($A77,'2026 Approved Budget'!$B:$B,'2026 Approved Budget'!E:E) -> 06. Sr. Director | AE77: =_xlfn.XLOOKUP($A77,'2026 Approved Budget'!$B:$B,'2026 Approved Budget'!F:F) -> Senior Director, Biostatistics | AF77: =_xlfn.XLOOKUP($A77,'2026 Approved Budget'!$B:$B,'2026 Approved Budget'!H:H) -> 45425
A78: 1012 | B78: Development | C78: 220 Clinical Data Science | D78: Wanying Li | E78: FTE | F78: 06 - Sr. Director | G78: Senior Director, Biostatistics | H78: SSF | K78: 2026 Q1 | L78: Hired | M78: Yen | N78: HIRED: YJ Choi | O78: 10312 | P78: TLA | Q78: Biostat lead for TLA | T78: Experienced Leader | W78: 3. Upgrade | X78: 1. In line with Budget | Y78: Included In Budget (Current FTE) | Z78: x | AA78: =_xlfn.XLOOKUP($A78,'2026 Approved Budget'!$B:$B,'2026 Approved Budget'!C:C) -> 220 Clinical Data Science | AB78: OK | AC78: =_xlfn.XLOOKUP($A78,'2026 Approved Budget'!$B:$B,'2026 Approved Budget'!D:D) -> BACKFILL: Abbas | AD78: =_xlfn.XLOOKUP($A78,'2026 Approved Budget'!$B:$B,'2026 Approved Budget'!E:E) -> 05. Director | AE78: =_xlfn.XLOOKUP($A78,'2026 Approved Budget'!$B:$B,'2026 Approved Budget'!F:F) -> Director, Biostatistician, TLA | AF78: =_xlfn.XLOOKUP($A78,'2026 Approved Budget'!$B:$B,'2026 Approved Budget'!H:H) -> 46006
A79: 1021 | B79: Development | C79: 220 Clinical Data Science | D79: Wanying Li | E79: FTE | F79: 05 - Director | G79: Director, Head of Statistical Programming | H79: PNJ | K79: 2024 Q3 | L79: Hired | N79: HIRED: Jessie Jun Yan | O79: 10076 | P79: ATA-TLA-Dani | Q79: Head of Stat programming team | W79: 1. In line with Budget | X79: 1. In line with Budget | Y79: Included In Budget (Current FTE) | Z79: x | AA79: =_xlfn.XLOOKUP($A79,'2026 Approved Budget'!$B:$B,'2026 Approved Budget'!C:C) -> 220 Clinical Data Science | AB79: OK | AC79: =_xlfn.XLOOKUP($A79,'2026 Approved Budget'!$B:$B,'2026 Approved Budget'!D:D) -> Jessie Yan | AD79: =_xlfn.XLOOKUP($A79,'2026 Approved Budget'!$B:$B,'2026 Approved Budget'!E:E) -> 05. Director | AE79: =_xlfn.XLOOKUP($A79,'2026 Approved Budget'!$B:$B,'2026 Approved Budget'!F:F) -> Director, Statistical Programming | AF79: =_xlfn.XLOOKUP($A79,'2026 Approved Budget'!$B:$B,'2026 Approved Budget'!H:H) -> 45551
A80: 1010 | B80: Development | C80: 220 Clinical Data Science | D80: Wanying Li | E80: FTE | F80: 05 - Director | G80: Director, Data Science | H80: SSF | K80: 2024 Q4 | L80: Hired | N80: HIRED: Peiwen Wu | O80: 10116 | P80: ATA | Q80: model simulation, stat methods evaluation and research | S80: Will take on ATA and Dani initially; catalyst for splitting the role is when ATA begins enrolling | T80: Experienced Leader | W80: 1. In line with Budget | X80: 1. In line with Budget | Y80: Included In Budget (Current FTE) | Z80: x | AA80: =_xlfn.XLOOKUP($A80,'2026 Approved Budget'!$B:$B,'2026 Approved Budget'!C:C) -> 220 Clinical Data Science | AB80: OK | AC80: =_xlfn.XLOOKUP($A80,'2026 Approved Budget'!$B:$B,'2026 Approved Budget'!D:D) -> Peiwen Wu | AD80: =_xlfn.XLOOKUP($A80,'2026 Approved Budget'!$B:$B,'2026 Approved Budget'!E:E) -> 05. Director | AE80: =_xlfn.XLOOKUP($A80,'2026 Approved Budget'!$B:$B,'2026 Approved Budget'!F:F) -> Director, Biostatistician ATA | AF80: =_xlfn.XLOOKUP($A80,'2026 Approved Budget'!$B:$B,'2026 Approved Budget'!H:H) -> 45642
A81: 1011 | B81: Development | C81: 220 Clinical Data Science | D81: Wanying Li | E81: FTE | F81: 05 - Director | G81: Director, Biostatistics | H81: PNJ | K81: 2025 Q2 | L81: Hired | N81: HIRED: Angela Gao | O81: 10224 | P81: Dani | Q81: Biostat lead for Dani | T81: Experienced Leader | W81: 1. In line with Budget | X81: 1. In line with Budget | Y81: Included In Budget (Current FTE) | Z81: x | AA81: =_xlfn.XLOOKUP($A81,'2026 Approved Budget'!$B:$B,'2026 Approved Budget'!C:C) -> 220 Clinical Data Science | AB81: OK | AC81: =_xlfn.XLOOKUP($A81,'2026 Approved Budget'!$B:$B,'2026 Approved Budget'!D:D) -> Angela Gao | AD81: =_xlfn.XLOOKUP($A81,'2026 Approved Budget'!$B:$B,'2026 Approved Budget'!E:E) -> 05. Director | AE81: =_xlfn.XLOOKUP($A81,'2026 Approved Budget'!$B:$B,'2026 Approved Budget'!F:F) -> Director, Biostatistician Dani | AF81: =_xlfn.XLOOKUP($A81,'2026 Approved Budget'!$B:$B,'2026 Approved Budget'!H:H) -> 45804
A82: 1022 | B82: Development | C82: 220 Clinical Data Science | D82: Jessie Yan | E82: FTE | F82: 04 - Assoc. Director | G82: Associate Director, Statistical Programmer | H82: PNJ | K82: 2025 Q2 | L82: Hired | N82: HIRED: Sri Byrapuneni | O82: 10217 | P82: TLA | Q82: Stat Programming Lead for TLA | W82: 1. In line with Budget | X82: 1. In line with Budget | Y82: Included In Budget (Current FTE) | Z82: x | AA82: =_xlfn.XLOOKUP($A82,'2026 Approved Budget'!$B:$B,'2026 Approved Budget'!C:C) -> 220 Clinical Data Science | AB82: OK | AC82: =_xlfn.XLOOKUP($A82,'2026 Approved Budget'!$B:$B,'2026 Approved Budget'!D:D) -> Sri Byrapuneni | AD82: =_xlfn.XLOOKUP($A82,'2026 Approved Budget'!$B:$B,'2026 Approved Budget'!E:E) -> 04. AD / Staff Scientist | AE82: =_xlfn.XLOOKUP($A82,'2026 Approved Budget'!$B:$B,'2026 Approved Budget'!F:F) -> Associate Director, Statistical Programming ATA | AF82: =_xlfn.XLOOKUP($A82,'2026 Approved Budget'!$B:$B,'2026 Approved Budget'!H:H) -> 45789
A83: 1331 | B83: Development | C83: 220 Clinical Data Science | D83: Wanying Li | E83: FTE | F83: 03 - Sr. Manager | G83: Senior Manager, Data Scientist | H83: SSF | K83: 2025 Q1 | L83: Hired | N83: HIRED: Gene Chen | O83: 10156 | P83: TLA | Q83: Data Science for Advanced Analytics, Dashboard programming | W83: 1. In line with Budget | X83: 1. In line with Budget | Y83: Included In Budget (Current FTE) | Z83: x | AA83: =_xlfn.XLOOKUP($A83,'2026 Approved Budget'!$B:$B,'2026 Approved Budget'!C:C) -> 220 Clinical Data Science | AB83: OK | AC83: =_xlfn.XLOOKUP($A83,'2026 Approved Budget'!$B:$B,'2026 Approved Budget'!D:D) -> Gene Chen | AD83: =_xlfn.XLOOKUP($A83,'2026 Approved Budget'!$B:$B,'2026 Approved Budget'!E:E) -> 03. Sr. Manager / Sr. Scientist | AE83: =_xlfn.XLOOKUP($A83,'2026 Approved Budget'!$B:$B,'2026 Approved Budget'!F:F) -> Sr Manager, Data Science | AF83: =_xlfn.XLOOKUP($A83,'2026 Approved Budget'!$B:$B,'2026 Approved Budget'!H:H) -> 45719
A84: 1024 | B84: Development | C84: 220 Clinical Data Science | D84: Jessie Yan | E84: FTE | F84: 03 - Sr. Manager | G84: Senior Manager, Statistical Programming | H84: PNJ | K84: 2025 Q3 | L84: Hired | M84: Yen | N84: HIRED: George Wu | O84: 10231 | P84: ATA | Q84: Stat Programming Lead for ATA | W84: 1. In line with Budget | X84: 1. In line with Budget | Y84: Included In Budget (Current FTE) | Z84: x | AA84: =_xlfn.XLOOKUP($A84,'2026 Approved Budget'!$B:$B,'2026 Approved Budget'!C:C) -> 220 Clinical Data Science | AB84: OK | AC84: =_xlfn.XLOOKUP($A84,'2026 Approved Budget'!$B:$B,'2026 Approved Budget'!D:D) -> George Wu | AD84: =_xlfn.XLOOKUP($A84,'2026 Approved Budget'!$B:$B,'2026 Approved Budget'!E:E) -> 03. Sr. Manager / Sr. Scientist | AE84: =_xlfn.XLOOKUP($A84,'2026 Approved Budget'!$B:$B,'2026 Approved Budget'!F:F) -> Senior Manager, Statistical Programming TLA | AF84: =_xlfn.XLOOKUP($A84,'2026 Approved Budget'!$B:$B,'2026 Approved Budget'!H:H) -> 45852
A85: 1007 | B85: Development | C85: 220 Clinical Data Science | D85: Wanying Li | E85: CW | F85: Not Indicated | G85: Biostat Contractor 1 | H85: US Remote | K85: 2024 Q3 | L85: Hired - CW | N85: CW: Debi Kotlovker | P85: Dani | Q85: Biostat expert for exploratory data analysis and assisting in study management | U85: Consultant not counted (may be hidden) | W85: N/A - CW | X85: N/A - CW | Y85: N/A (CW) | AA85: =_xlfn.XLOOKUP($A85,'2026 Approved Budget'!$B:$B,'2026 Approved Budget'!C:C) -> #N/A | AB85: N/A (CW) | AC85: =_xlfn.XLOOKUP($A85,'2026 Approved Budget'!$B:$B,'2026 Approved Budget'!D:D) -> #N/A | AD85: =_xlfn.XLOOKUP($A85,'2026 Approved Budget'!$B:$B,'2026 Approved Budget'!E:E) -> #N/A | AE85: =_xlfn.XLOOKUP($A85,'2026 Approved Budget'!$B:$B,'2026 Approved Budget'!F:F) -> #N/A | AF85: =_xlfn.XLOOKUP($A85,'2026 Approved Budget'!$B:$B,'2026 Approved Budget'!H:H) -> #N/A
A86: 1017 | B86: Development | C86: 220 Clinical Data Science | D86: Jessie Yan | E86: CW | F86: Not Indicated | G86: Statistical Programming Contractor | H86: US Remote | K86: 2024 Q3 | L86: Hired - CW | N86: CW: Sandy Chang | P86: TLA | Q86: Stat programming support for study readout Dani | W86: N/A - CW | X86: N/A - CW | Y86: N/A (CW) | AA86: =_xlfn.XLOOKUP($A86,'2026 Approved Budget'!$B:$B,'2026 Approved Budget'!C:C) -> #N/A | AB86: N/A (CW) | AC86: =_xlfn.XLOOKUP($A86,'2026 Approved Budget'!$B:$B,'2026 Approved Budget'!D:D) -> #N/A | AD86: =_xlfn.XLOOKUP($A86,'2026 Approved Budget'!$B:$B,'2026 Approved Budget'!E:E) -> #N/A | AE86: =_xlfn.XLOOKUP($A86,'2026 Approved Budget'!$B:$B,'2026 Approved Budget'!F:F) -> #N/A | AF86: =_xlfn.XLOOKUP($A86,'2026 Approved Budget'!$B:$B,'2026 Approved Budget'!H:H) -> #N/A
A87: 1025 | B87: Development | C87: 220 Clinical Data Science | D87: Jessie Yan | E87: CW | F87: Not Indicated | G87: Stat programming contractor | H87: US Remote | K87: 2025 Q2 | L87: Hired - CW | N87: CW: Nishant Dholakia | P87: ATA-TLA-Dani | Q87: Stat programming support for study readout ATA | W87: N/A - CW | X87: N/A - CW | Y87: N/A (CW) | AA87: =_xlfn.XLOOKUP($A87,'2026 Approved Budget'!$B:$B,'2026 Approved Budget'!C:C) -> #N/A | AB87: N/A (CW) | AC87: =_xlfn.XLOOKUP($A87,'2026 Approved Budget'!$B:$B,'2026 Approved Budget'!D:D) -> #N/A | AD87: =_xlfn.XLOOKUP($A87,'2026 Approved Budget'!$B:$B,'2026 Approved Budget'!E:E) -> #N/A | AE87: =_xlfn.XLOOKUP($A87,'2026 Approved Budget'!$B:$B,'2026 Approved Budget'!F:F) -> #N/A | AF87: =_xlfn.XLOOKUP($A87,'2026 Approved Budget'!$B:$B,'2026 Approved Budget'!H:H) -> #N/A
A88: 1009 | B88: Development | C88: 220 Clinical Data Science | D88: Wanying Li | E88: CW | F88: Not Indicated | G88: Biostat Contractor | H88: US Remote | K88: 2025 Q4 | L88: Hired - CW | M88: Yen | N88: CW: Linda Tang | P88: TLA | Q88: Biostat Study Lead - TLA program and support for submission | S88: Gate on receiving data - confidence in TLA, dedicated new studies, designing a registrational study | U88: Consultant not counted (may be hidden) | W88: N/A - CW | X88: N/A - CW | Y88: N/A (CW) | AA88: =_xlfn.XLOOKUP($A88,'2026 Approved Budget'!$B:$B,'2026 Approved Budget'!C:C) -> #N/A | AB88: N/A (CW) | AC88: =_xlfn.XLOOKUP($A88,'2026 Approved Budget'!$B:$B,'2026 Approved Budget'!D:D) -> #N/A | AD88: =_xlfn.XLOOKUP($A88,'2026 Approved Budget'!$B:$B,'2026 Approved Budget'!E:E) -> #N/A | AE88: =_xlfn.XLOOKUP($A88,'2026 Approved Budget'!$B:$B,'2026 Approved Budget'!F:F) -> #N/A | AF88: =_xlfn.XLOOKUP($A88,'2026 Approved Budget'!$B:$B,'2026 Approved Budget'!H:H) -> #N/A
A89: 5004 | B89: Development | C89: 220 Clinical Data Science | D89: Wanying Li | E89: CW | F89: Not Indicated | G89: Contractor, Clinical Data Scientist | H89: US Remote | K89: 2025 Q4 | L89: Hired - CW | M89: Yen | N89: CW: Meng Xie | P89: UA | Q89: Data visualization and dashboard build | U89: 01 - Data Readout | W89: N/A - CW | X89: N/A - CW | Y89: N/A (CW) | AA89: =_xlfn.XLOOKUP($A89,'2026 Approved Budget'!$B:$B,'2026 Approved Budget'!C:C) -> #N/A | AB89: N/A (CW) | AC89: =_xlfn.XLOOKUP($A89,'2026 Approved Budget'!$B:$B,'2026 Approved Budget'!D:D) -> #N/A | AD89: =_xlfn.XLOOKUP($A89,'2026 Approved Budget'!$B:$B,'2026 Approved Budget'!E:E) -> #N/A | AE89: =_xlfn.XLOOKUP($A89,'2026 Approved Budget'!$B:$B,'2026 Approved Budget'!F:F) -> #N/A | AF89: =_xlfn.XLOOKUP($A89,'2026 Approved Budget'!$B:$B,'2026 Approved Budget'!H:H) -> #N/A
A90: 1330 | B90: Development | C90: 220 Clinical Data Science | D90: Wanying Li | E90: CW | F90: 04 - Assoc. Director | G90: Contractor, Biostatistics | H90: US Remote | K90: 2025 Q3 | L90: Hired - CW | M90: Yen | N90: CW: Christina Nurse | P90: TLA | Q90: Biostat study support for ATA | W90: N/A - CW | X90: N/A - CW | Y90: N/A (CW) | AA90: =_xlfn.XLOOKUP($A90,'2026 Approved Budget'!$B:$B,'2026 Approved Budget'!C:C) -> #N/A | AB90: N/A (CW) | AC90: =_xlfn.XLOOKUP($A90,'2026 Approved Budget'!$B:$B,'2026 Approved Budget'!D:D) -> #N/A | AD90: =_xlfn.XLOOKUP($A90,'2026 Approved Budget'!$B:$B,'2026 Approved Budget'!E:E) -> #N/A | AE90: =_xlfn.XLOOKUP($A90,'2026 Approved Budget'!$B:$B,'2026 Approved Budget'!F:F) -> #N/A | AF90: =_xlfn.XLOOKUP($A90,'2026 Approved Budget'!$B:$B,'2026 Approved Budget'!H:H) -> #N/A
A91: 5052 | B91: Development | C91: 210 Clinical Operations | D91: Sanjay Patel | E91: FTE | F91: 04 - Assoc. Director | G91: Clinical Operations | H91: SSF | I91: 27 | K91: 2026 Q4 | P91: ATA | T91: Jaclyn to check whether this role is required in 2026 | U91: 01 - Data Readout | V91: Potential Tradeoff | W91: 3. Upgrade | X91: 2. Delayed | Y91: Included In Budget (Open Role) | Z91: x | AA91: =_xlfn.XLOOKUP($A91,'2026 Approved Budget'!$B:$B,'2026 Approved Budget'!C:C) -> 210 Clinical Operations | AB91: Confirm w/ P&C | AC91: =_xlfn.XLOOKUP($A91,'2026 Approved Budget'!$B:$B,'2026 Approved Budget'!D:D) -> TBD | AD91: =_xlfn.XLOOKUP($A91,'2026 Approved Budget'!$B:$B,'2026 Approved Budget'!E:E) -> 02. Manager / Scientist | AE91: =_xlfn.XLOOKUP($A91,'2026 Approved Budget'!$B:$B,'2026 Approved Budget'!F:F) -> Clinical Operations | AF91: =_xlfn.XLOOKUP($A91,'2026 Approved Budget'!$B:$B,'2026 Approved Budget'!H:H) -> 46188
A92: 5123 | B92: Development | C92: 230 Pharmacovigilance | D92: Krisztina Debreczeni | E92: FTE | F92: 05 - Director | G92: Director, PV Scientist (non-MD) | H92: PNJ | I92: 28 | K92: 2026 Q4 | P92: Dani | Q92: Medical oversight across all assets and all trials. Experienced in safety risk management, safety benefit-risk analysis, signal management and safety data assessment. Leader of function | R92: Safety Surveillance program, company core risk management plan, DSUR, PSUR, PADER/PAER, company core safety information | S92: Safety data collection in one or more assets and the creation of the support timely and accurate safety data assessment and surveillance, signal detection, benefit-risk evaluation and safety risk management | T92: medical background with strong pharmacovigilance experience | U92: 01 - Data Readout | V92: Potential Tradeoff | W92: 1. In line with Budget | X92: 1. In line with Budget | Y92: Included In Budget (Open Role) | Z92: x | AA92: =_xlfn.XLOOKUP($A92,'2026 Approved Budget'!$B:$B,'2026 Approved Budget'!C:C) -> 230 Pharmacovigilance | AB92: OK | AC92: =_xlfn.XLOOKUP($A92,'2026 Approved Budget'!$B:$B,'2026 Approved Budget'!D:D) -> TBD | AD92: =_xlfn.XLOOKUP($A92,'2026 Approved Budget'!$B:$B,'2026 Approved Budget'!E:E) -> 05. Director | AE92: =_xlfn.XLOOKUP($A92,'2026 Approved Budget'!$B:$B,'2026 Approved Budget'!F:F) -> Director, PV Scientist | AF92: =_xlfn.XLOOKUP($A92,'2026 Approved Budget'!$B:$B,'2026 Approved Budget'!H:H) -> 46371
A93: 5388 | B93: Development | C93: 205 Executive Development | D93: Jay Edelberg | E93: FTE | F93: 05 - Director | G93: Director, Chief of Staff | H93: PNJ | I93: 29 | K93: 2026 Q3 | P93: UA | Q93: TBD | V93: Potential Tradeoff | W93: 1. In line with Budget | X93: 3. Accelerated | Y93: Included In Budget (Open Role) | Z93: x | AA93: =_xlfn.XLOOKUP($A93,'2026 Approved Budget'!$B:$B,'2026 Approved Budget'!C:C) -> 901 Executive G&A | AB93: Confirm w/ P&C | AC93: =_xlfn.XLOOKUP($A93,'2026 Approved Budget'!$B:$B,'2026 Approved Budget'!D:D) -> TBD | AD93: =_xlfn.XLOOKUP($A93,'2026 Approved Budget'!$B:$B,'2026 Approved Budget'!E:E) -> 05. Director | AE93: =_xlfn.XLOOKUP($A93,'2026 Approved Budget'!$B:$B,'2026 Approved Budget'!F:F) -> Buffer Role | AF93: =_xlfn.XLOOKUP($A93,'2026 Approved Budget'!$B:$B,'2026 Approved Budget'!H:H) -> 46280
A94: 5387 | B94: Development | C94: 210 Clinical Operations | D94: Jaclyn Patterson | E94: FTE | F94: 07 - Exec. Director | G94: Head of Clinical Trial Management | H94: PNJ | I94: 30 | K94: 2026 Q3 | M94: Kim | P94: UA | W94: 3. Upgrade | X94: 1. In line with Budget | Y94: Included In Budget (Open Role) | Z94: x | AA94: =_xlfn.XLOOKUP($A94,'2026 Approved Budget'!$B:$B,'2026 Approved Budget'!C:C) -> 901 Executive G&A | AB94: Confirm w/ P&C | AC94: =_xlfn.XLOOKUP($A94,'2026 Approved Budget'!$B:$B,'2026 Approved Budget'!D:D) -> TBD | AD94: =_xlfn.XLOOKUP($A94,'2026 Approved Budget'!$B:$B,'2026 Approved Budget'!E:E) -> 05. Director | AE94: =_xlfn.XLOOKUP($A94,'2026 Approved Budget'!$B:$B,'2026 Approved Budget'!F:F) -> Buffer Role | AF94: =_xlfn.XLOOKUP($A94,'2026 Approved Budget'!$B:$B,'2026 Approved Budget'!H:H) -> 46280 | AG94: Buffer role
A95: 5390 | B95: Development | C95: 220 Clinical Data Science | D95: Wanying Li | E95: CW to FTE | F95: 04 - Assoc. Director | G95: Associate Director, Statistical Programming | H95: TBD | K95: 2026 Q3 | P95: TLA/ATA/Dani | Q95: Support early development and legacy study | W95: N/A - CW | X95: N/A - CW | Y95: N/A (CW) | AA95: =_xlfn.XLOOKUP($A95,'2026 Approved Budget'!$B:$B,'2026 Approved Budget'!C:C) -> #N/A | AB95: N/A (CW) | AC95: =_xlfn.XLOOKUP($A95,'2026 Approved Budget'!$B:$B,'2026 Approved Budget'!D:D) -> #N/A | AD95: =_xlfn.XLOOKUP($A95,'2026 Approved Budget'!$B:$B,'2026 Approved Budget'!E:E) -> #N/A | AE95: =_xlfn.XLOOKUP($A95,'2026 Approved Budget'!$B:$B,'2026 Approved Budget'!F:F) -> #N/A | AF95: =_xlfn.XLOOKUP($A95,'2026 Approved Budget'!$B:$B,'2026 Approved Budget'!H:H) -> #N/A
A96: 5391 | B96: Development | C96: 220 Clinical Data Science | D96: Wanying Li | E96: CW to FTE | F96: 04 - Assoc. Director | G96: Associate Director, Biostatistics | H96: TBD | K96: 2026 Q3 | P96: TLA/ATA/Dani | Q96: Support early development and legacy study | W96: N/A - CW | X96: N/A - CW | Y96: N/A (CW) | AA96: =_xlfn.XLOOKUP($A96,'2026 Approved Budget'!$B:$B,'2026 Approved Budget'!C:C) -> #N/A | AB96: N/A (CW) | AC96: =_xlfn.XLOOKUP($A96,'2026 Approved Budget'!$B:$B,'2026 Approved Budget'!D:D) -> #N/A | AD96: =_xlfn.XLOOKUP($A96,'2026 Approved Budget'!$B:$B,'2026 Approved Budget'!E:E) -> #N/A | AE96: =_xlfn.XLOOKUP($A96,'2026 Approved Budget'!$B:$B,'2026 Approved Budget'!F:F) -> #N/A | AF96: =_xlfn.XLOOKUP($A96,'2026 Approved Budget'!$B:$B,'2026 Approved Budget'!H:H) -> #N/A
A97: 5410 | B97: Development | C97: 210 Clinical Operations | D97: Jaclyn Patterson | E97: FTE | F97: 06 - Sr. Director | G97: Sr. Director, Vendor Relationship & Management | H97: PNJ | K97: 2026 Q1 | M97: Kim | P97: UA | V97: Formerly Director, Clinical Operations Program Lead, Early Dev | W97: 3. Upgrade | X97: 1. In line with Budget | Y97: Incremental Request | AA97: =_xlfn.XLOOKUP($A97,'2026 Approved Budget'!$B:$B,'2026 Approved Budget'!C:C) -> #N/A | AB97: Confirm w/ P&C | AC97: =_xlfn.XLOOKUP($A97,'2026 Approved Budget'!$B:$B,'2026 Approved Budget'!D:D) -> #N/A | AD97: =_xlfn.XLOOKUP($A97,'2026 Approved Budget'!$B:$B,'2026 Approved Budget'!E:E) -> #N/A | AE97: =_xlfn.XLOOKUP($A97,'2026 Approved Budget'!$B:$B,'2026 Approved Budget'!F:F) -> #N/A | AF97: =_xlfn.XLOOKUP($A97,'2026 Approved Budget'!$B:$B,'2026 Approved Budget'!H:H) -> #N/A | AG97: OOBR - tradeoff with #5104
A98: 5009 | B98: Development | C98: 220 Clinical Data Science | D98: Wanying Li | E98: CW | F98: 03 - Sr. Manager | G98: Biostat Contractor | H98: SSF or PNJ | K98: 2026 Q2 | P98: TLA/ATA/Dani | Q98: Biostat support for data readout and publicatoin | S98: Gate on TLA-301 positive Part 1 data readout | U98: 01 - Data Readout | W98: N/A - CW | X98: N/A - CW | Y98: N/A (CW) | AA98: =_xlfn.XLOOKUP($A98,'2026 Approved Budget'!$B:$B,'2026 Approved Budget'!C:C) -> #N/A | AB98: N/A (CW) | AC98: =_xlfn.XLOOKUP($A98,'2026 Approved Budget'!$B:$B,'2026 Approved Budget'!D:D) -> #N/A | AD98: =_xlfn.XLOOKUP($A98,'2026 Approved Budget'!$B:$B,'2026 Approved Budget'!E:E) -> #N/A | AE98: =_xlfn.XLOOKUP($A98,'2026 Approved Budget'!$B:$B,'2026 Approved Budget'!F:F) -> #N/A | AF98: =_xlfn.XLOOKUP($A98,'2026 Approved Budget'!$B:$B,'2026 Approved Budget'!H:H) -> #N/A
A99: 5372 | B99: Development | C99: 220 Clinical Data Science | D99: Wanying Li | E99: CW | F99: 03 - Sr. Manager | G99: Contractor, Clinical Data Scientist | H99: US Remote | K99: 2026 Q2 | P99: Dani | Q99: Data visualization and dashboard build | U99: 01 - Data Readout | W99: N/A - CW | X99: N/A - CW | Y99: N/A (CW) | AA99: =_xlfn.XLOOKUP($A99,'2026 Approved Budget'!$B:$B,'2026 Approved Budget'!C:C) -> #N/A | AB99: N/A (CW) | AC99: =_xlfn.XLOOKUP($A99,'2026 Approved Budget'!$B:$B,'2026 Approved Budget'!D:D) -> #N/A | AD99: =_xlfn.XLOOKUP($A99,'2026 Approved Budget'!$B:$B,'2026 Approved Budget'!E:E) -> #N/A | AE99: =_xlfn.XLOOKUP($A99,'2026 Approved Budget'!$B:$B,'2026 Approved Budget'!F:F) -> #N/A | AF99: =_xlfn.XLOOKUP($A99,'2026 Approved Budget'!$B:$B,'2026 Approved Budget'!H:H) -> #N/A
A100: 1014 | B100: Development | C100: 221 Clinical Data Management | D100: Lauren Cao | E100: FTE | F100: 05 - Director | G100: Director, Clinical Data Management | H100: SSF | K100: 2025 Q3 | L100: Hired | M100: Yen | N100: HIRED: Frances Dingle | O100: 10233 | P100: TLA | Q100: CDM lead for TLA201 | S100: When Dani is licensed in; once TLA lead is filled, will move CDM contractor into this role | W100: 1. In line with Budget | X100: 1. In line with Budget | Y100: Included In Budget (Current FTE) | Z100: x | AA100: =_xlfn.XLOOKUP($A100,'2026 Approved Budget'!$B:$B,'2026 Approved Budget'!C:C) -> 221 Clinical Data Management | AB100: OK | AC100: =_xlfn.XLOOKUP($A100,'2026 Approved Budget'!$B:$B,'2026 Approved Budget'!D:D) -> Frances Seput Dingle | AD100: =_xlfn.XLOOKUP($A100,'2026 Approved Budget'!$B:$B,'2026 Approved Budget'!E:E) -> 05. Director | AE100: =_xlfn.XLOOKUP($A100,'2026 Approved Budget'!$B:$B,'2026 Approved Budget'!F:F) -> Associate Director, Clinical Data Management TLA | AF100: =_xlfn.XLOOKUP($A100,'2026 Approved Budget'!$B:$B,'2026 Approved Budget'!H:H) -> 45929
...

Sheet WFP Details - Beyond 2026
A1: Temp Job ID | B1: Function | C1: Department | D1: Requestor / Manager | E1: Employee Type | F1: Level | G1: Title | H1: Location | I1: Functional Priority | J1: Corp. Priority | K1: Target Start Dt | L1: Recruiting Status | M1: Recruiter | N1: Hired Name | O1: HiBob ID | P1: Asset | Q1: Key Capability | R1: Catalyst for Growth (business rationale, key deliverables, etc.) | S1: Milestone / Trigger for Hire | T1: Talent Assessment | U1: Horizon 1 | V1: Tradeoff?
A2: 5346 | B2: G&A | C2: 925 Business Development | D2: Brianne Jahn | E2: FTE | F2: 03 - Sr. Manager | G2: Senior Manager, Business Development | H2: PNJ | I2: Capacity building | K2: 2027 Q1 | P2: N/A | Q2: Financial, market, and scientific literacy—with the balance of scientific vs. financial expertise tailored to the role and shaped by the backgrounds of candidates hired into other open positions. | R2: Support the implementation of a proactive BD strategy by expanding our capacity for opportunity sourcing, strengthening CI, accelerating deal readiness, and enhancing cross-functional execution | S2: Proactive BD strategy rollout | T2: Emerging talent
A3: 5347 | B3: G&A | C3: 925 Business Development | D3: Brianne Jahn | E3: FTE | F3: 02 - Manager | G3: Manager, Business Development | H3: SSF | I3: Capacity building | K3: 2027 Q2 | P3: N/A | Q3: Scientific Literacy - ability to assess mechanisms of action, target biology, and indication relevance to support BD evaluations and cross-functional alignment | R3: Support the implementation of a proactive BD strategy by expanding our capacity for opportunity sourcing, strengthening CI, accelerating deal readiness, and enhancing cross-functional execution | S3: Proactive BD strategy rollout | T3: Emerging talent
A4: 5345 | B4: G&A | C4: 925 Business Development | D4: Brianne Jahn | E4: FTE | F4: 04 - Associate | G4: Associate or Director, Business Development | H4: SSF | I4: Capacity building | K4: 2027 Q3 | N4: Associate or director level | P4: N/A | Q4: Financial and market literacy - skilled in basic valuation, deal analysis, market research, and competitive intelligence to support strategic assessments and BD decisions | R4: Support the implementation of a proactive BD strategy by expanding our capacity for opportunity sourcing, strengthening CI, accelerating deal readiness, and enhancing cross-functional execution | S4: Proactive BD strategy rollout | T4: Extensive background in finance
A5: 5348 | B5: G&A | C5: 925 Business Development | D5: Brianne Jahn | E5: FTE | F5: 01 - Below Manager | G5: Analyst, Business Development | H5: PNJ | I5: Capacity building | K5: 2027 Q3 | P5: N/A | Q5: Financial, market, and scientific literacy—with the balance of scientific vs. financial expertise tailored to the role and shaped by the backgrounds of candidates hired into other open positions. | R5: Support the implementation of a proactive BD strategy by expanding our capacity for opportunity sourcing, strengthening CI, accelerating deal readiness, and enhancing cross-functional execution | S5: Proactive BD strategy rollout | T5: Emerging talent
A6: 1006 | B6: G&A | C6: 930 Communications | D6: Emily Faucette | E6: Agency | F6: Not Indicated | G6: IR Agency TBD | H6: SSF | K6: 2026 Q2 | L6: 2026 H1 pending insight from VP hire | N6: CW: TBD | P6: N/A | S6: Once time of IPO becomes certain
A7: 1314 | B7: G&A | C7: 930 Communications | D7: Emily Faucette | E7: Agency | F7: Not Indicated | G7: Health + Commerce | H7: SSF | K7: 2024 Q3 | L7: Onboard as of November 2024 | N7: CW: TBD | P7: N/A | Q7: Agency support and industry expertise/insights to serve as additional thought partners with capabilities to help Kardigan communications leadership execute plans - key areas of support include media relations and digital marketing | S7: Exiting stealth mode
A8: 5002 | B8: G&A | C8: 930 Communications | D8: Emily Faucette | E8: FTE | F8: (Senior) Manager | G8: Communications Manager | H8: SSF or PNJ | K8: 2027 Q1 | L8: 2026 H1 | N8: Agency support | Q8: Executional support across all communications workstreams with an emphasis on internal where more junior support is required and in-house perspective critical. Digital and social media skills a plus. | R8: As we begin to build out inmtegrated function this level hire will help us rely less on external agency support | S8: Once time of IPO becomes certain | T8: Ideally someone coming out of an agency environment who can wear many hats and is adept/thrives working in a fast-paced environment on multiple projects at once.
A9: 5220 | B9: PPM | C9: 240 PPM | D9: Amy Westfall | E9: FTE | F9: 06- Sr. Director | G9: Alliance Management | H9: SSF or PNJ | K9: 2027 Q2 | P9: N/A | Q9: Partner with GPMs to manage partnership commitmenets & milestones; build and drive capability for In-licensing/Out-licensing - develop playbooks for this | R9: Dependent on partnership activity and/or in/out-licensing activity | S9: Dependent on partnership activity and/or in/out-licensing activity
A10: 5221 | B10: PPM | C10: 240 PPM | D10: Amy Westfall/Sr Dir Alliance Management | E10: FTE | F10: 05 - Director | G10: Alliance Management | H10: SSF or PNJ | K10: 2027 Q2 | P10: N/A | Q10: Project Manage/own specific in-licensing/out-licensing activities; # of roles dependent on partnership activity | R10: Dependent on partnership activity and/or in/out-licensing activity | S10: Dependent on partnership activity and/or in/out-licensing activity
A11: 5222 | B11: PPM | C11: 240 PPM | D11: Amy Westfall/VP GPM | E11: FTE | F11: 05 - Director | G11: Global Program Manager, New Asset | H11: SSF or PNJ | K11: 2027 Q2 | P11: N/A | Q11: Program Management to drive cross-functional strategic planning, execution, risk management, resource management, and decision-making for key programs; # of roles dependent on new Asset activity | R11: Dependent on new Asset(s) within portfolio | S11: Dependent on new Asset(s) within portfolio
A12: 5223 | B12: PPM | C12: 240 PPM | D12: Amy Westfall/VP GPM | E12: FTE | F12: 04 - Assoc. Director | G12: Project Manager | H12: SSF or PNJ | K12: 2027 Q2 | P12: N/A | Q12: Addiitonal Project Management capability to support filing activities/NDA readiness | R12: Addiitonal Project Management capability to support filing activities/NDA readiness | S12: Go decisions on NDA readiness
A13: 5294 | B13: Tech Ops | C13: 410 Manufacturing | D13: Gus Kodersha | E13: FTE | F13: 05 - Director | G13: Assoc Director /Sr. Manager | H13: PNJ | I13: Business Critical | K13: 2027 Q1 | P13: Dani | Q13: DANI Program Development | S13: DANI Proc Char and Pre PPQ and NDA Authoring | T13: Technical Expert
A14: 5295 | B14: Tech Ops | C14: 410 Manufacturing | D14: Gus Kodersha | E14: FTE | F14: 04 - Assoc. Director | G14: Assoc Director /Sr. Manager | H14: PNJ | I14: Business Critical | K14: 2027 Q1 | P14: Future Asset | Q14: IND Support DS Pre-IND | S14: Pre IND DS to support IND filing | T14: Technical Expert
A15: 5296 | B15: Tech Ops | C15: 410 Manufacturing | D15: Gus Kodersha | E15: FTE | F15: 04 - Assoc. Director | G15: Assoc Director /Sr. Manager | H15: SSF | I15: Business Critical | K15: 2027 Q1 | P15: Future Asset | Q15: IND Support DS Pre-IND | S15: Pre IND DS to support IND filing | T15: Technical Expert
A16: 5300 | B16: Tech Ops | C16: 410 Manufacturing | D16: Rennan Pan | E16: FTE | F16: 05 - Director | G16: Dir/Associate Director - DP | H16: SSF | I16: Business Critical | K16: 2027 Q1 | P16: Dani | Q16: Product Development | R16: To support NDA prep for Dani; CR formulation development; New Projects | S16: FPI for Dani clinical study | T16: Technical Expert
A17: 5302 | B17: Tech Ops | C17: 410 Manufacturing | D17: Rennan Pan | E17: FTE | F17: 05 - Director | G17: Dir - DP | H17: PNJ | I17: Business Critical | K17: 2027 Q1 | P17: Future Asset | Q17: Product Development | R17: To lead drug product development for new assets | S17: Candidate selection | T17: Emerging Leader
A18: 5303 | B18: Tech Ops | C18: 410 Manufacturing | D18: Rennan Pan | E18: FTE | F18: 05 - Director | G18: Dir - DP | H18: PNJ | I18: Business Critical | K18: 2027 Q1 | P18: Future Asset | Q18: Product Development | R18: To lead drug product development for new assets | S18: In-licensing agreement signed | T18: Technical Expert
A19: 5307 | B19: Tech Ops | C19: 410 Manufacturing | D19: Leon Zhou | E19: FTE | F19: 05 - Director | G19: Director, Analytical Development | H19: PNJ | I19: Business Critical | K19: 2027 Q1 | P19: Future Asset | Q19: Analytical and Material Sciences | R19: 2G ATA and new INDs | S19: 2G ATA and new INDs | T19: Technical Expert
A20: 5310 | B20: Tech Ops | C20: 410 Manufacturing | D20: Leon Zhou | E20: FTE | F20: 04 - Assoc. Director | G20: Associate Director, Analytical Development | H20: PNJ | I20: Business Critical | K20: 2027 Q1 | P20: KAR-141 | Q20: Analytical Science | T20: Technical Expert
A21: 5314 | B21: Tech Ops | C21: 405 Supply Chain | D21: Aaron Misrack | E21: FTE | F21: 04 - Assoc. Director | G21: Associate Director, Clinical Supply Chain Planning | H21: SSF | I21: Business Critical | K21: 2027 Q1 | P21: ATA-TLA-Dani | Q21: Focused clinical planning resource to support forecasting system implementation, additional trials, new molecules and potential indications | R21: Multiple assets | S21: Organic & inorganic asset growth | T21: Technical Expert
A22: 1351 | B22: Tech Ops | C22: 405 Supply Chain | D22: Aaron Misrack | E22: FTE | F22: 04 - Assoc. Director | G22: Associate Director, Clinical Supply Chain Planning | H22: PNJ | I22: Business Critical | K22: 2027 Q1 | P22: ATA-TLA-Dani | Q22: Planning / increased modeling, ERP system implementation and ongoing oversight / use | R22: Commercial launches of multiple assets | S22: 12-18 mo ahead of first commercial launch | T22: Technical Expert
A23: 1208 | B23: Tech Ops | C23: 410 Manufacturing | D23: Erika Riffel | E23: FTE | F23: 03 - Sr. Manager | G23: Senior Manager, External Mfg. | H23: SSF | I23: Infrastructure / Support | K23: 2027 Q1 | P23: ATA-TLA-Dani | Q23: Coordinate, manage and execute the procure to pay processes & systems for Tech Ops. Replaces a consultant | R23: Multiple assets and CDMOs | S23: Volume increase and commercial launches a year out | T23: Technical Expert
A24: 5319 | B24: Tech Ops | C24: 405 Supply Chain | D24: Taylor Elkington | E24: FTE | F24: 01 - Below Manager | G24: Clinical Supply Chain Associate | H24: SSF | I24: Business Critical | K24: 2027 Q1 | P24: ATA-TLA | Q24: Clinical Supply Chain | R24: Additional indications / studies / programs | S24: Additional indications / studies / programs | T24: Technical Expert
A25: 5323 | B25: Tech Ops | C25: 405 Supply Chain | D25: Taylor Elkington | E25: FTE | F25: 03 - Sr. Manager | G25: Senior Manager, Clinical Device Supply Chain | H25: SSF | I25: Infrastructure / Support | K25: 2027 Q1 | P25: ATA-TLA-Dani | Q25: Clinical Supply Chain | R25: Prolaio kits planning, inventory management and coordination | S25: Prolaio kits planning, inventory management and coordination | T25: Technical Expert
A26: 5324 | B26: Tech Ops | C26: 405 Supply Chain | D26: Amelia Milani | E26: FTE | F26: 06 - Sr. Director | G26: Senior Director, Commercial Supply Chain | H26: SSF | I26: Business Critical | K26: 2027 Q1 | P26: ATA-TLA-Dani | Q26: Oversight of commercial SC and launch capabilities needed: 3PL, Serialization, State Licenses, Shipping Val, etc. | R26: Launches for ATA, TLA and DANI | S26: 1 year prior to NDA filing
A27: 5330 | B27: Tech Ops | C27: 410 Manufacturing | D27: William Walker | E27: FTE | F27: 03 - Sr. Manager | G27: Tech Ops Program Manager | H27: SSF | I27: Business Critical | K27: 2027 Q1 | P27: TLA | Q27: Project management within CMC / Tech Ops, owning timelines, RAID, meetings, and cross-fcungional coordination across Tech Ops | R27: Enable execution of Tech Ops operating model (meetings, timeline, actions, RAID, etc.) driven by increasing complexity of deliverables | S27: TLA Program in late-stage development | T27: Emerging Leader
A28: 5331 | B28: Tech Ops | C28: 410 Manufacturing | D28: William Walker | E28: FTE | F28: 06 - Sr. Director | G28: Tech Ops Program Lead (TOPL) | H28: PNJ | I28: Business Critical | K28: 2027 Q1 | P28: ATA-Dani | Q28: Strategic, cross-functional leadership of Tech Ops program, accountable for development, NDA readiness, risks mgmt, and EC / GPT interface | R28: Multiple and concurrent early to late stage programs requiring dedicated strategic leadership to manage cross-functional Tech Ops activities | S28: Dani Program in late-stage development | T28: Experienced Leader
A29: 5332 | B29: Tech Ops | C29: 410 Manufacturing | D29: William Walker | E29: FTE | F29: 03 - Sr. Manager | G29: Tech Ops Program Manager | H29: PNJ | I29: Business Critical | K29: 2027 Q1 | P29: Dani | Q29: Project management within CMC / Tech Ops, owning timelines, RAID, meetings, and cross-fcungional coordination across Tech Ops | R29: Enable execution of Tech Ops operating model (meetings, timeline, actions, RAID, etc.) driven by increasing complexity of deliverables | S29: Dani Program in late-stage development | T29: Emerging Leader
A30: 5335 | B30: Tech Ops | C30: 410 Manufacturing | D30: William Walker | E30: FTE | F30: 06 - Sr. Director | G30: Tech Ops Program Lead (TOPL) | H30: SSF | I30: Business Critical | K30: 2027 Q1 | P30: Future Asset | Q30: Strategic, cross-functional leadership of Tech Ops program, accountable for development, NDA readiness, risks mgmt, and EC / GPT interface | R30: Multiple and concurrent early to late stage programs requiring dedicated strategic leadership to manage cross-functional Tech Ops activities | S30: 3x early stage programs approaching IND within two to three quarters | T30: Emerging Leader
A31: 5336 | B31: Tech Ops | C31: 410 Manufacturing | D31: William Walker | E31: FTE | F31: 03 - Sr. Manager | G31: Tech Ops Program Manager | H31: SSF | I31: Infrastructure / Support | K31: 2027 Q1 | P31: Future Asset | Q31: Project management within CMC / Tech Ops, owning timelines, RAID, meetings, and cross-fcungional coordination across Tech Ops | R31: Enable execution of Tech Ops operating model (meetings, timeline, actions, RAID, etc.) driven by increasing complexity of deliverables | S31: 3x early stage programs approaching IND within two to three quarters | T31: Emerging Leader
A32: 5293 | B32: Tech Ops | C32: 410 Manufacturing | D32: Gus Kodersha | E32: FTE | F32: 04 - Assoc. Director | G32: Assoc Director /Sr. Manager | H32: SSF | I32: Business Critical | K32: 2027 Q2 | P32: TLA | Q32: TLA and ATA Program Development | S32: TLA Proc Char and Pre PPQ and NDA Authoring | T32: Technical Expert
A33: 5301 | B33: Tech Ops | C33: 410 Manufacturing | D33: Rennan Pan | E33: FTE | F33: 05 - Director | G33: Dir - DP | H33: PNJ | I33: Business Critical | K33: 2027 Q2 | P33: KAR-141 | Q33: Product Development | R33: To lead drug product development for KAR-141, process dev, CTM, TT, etc. | S33: Completion of KAR-141 POM study | T33: Emerging Leader
A34: 5309 | B34: Tech Ops | C34: 410 Manufacturing | D34: Leon Zhou | E34: FTE | F34: 04 - Assoc. Director | G34: Associate Director, Analytical Development | H34: PNJ | I34: Business Critical | K34: 2027 Q2 | P34: KAR-141 | Q34: Analytical Science/Technical Writer | R34: TLA/ATA NDAs | S34: TLA/ATA NDAs | T34: Technical Expert
A35: 5311 | B35: Tech Ops | C35: 410 Manufacturing | D35: Leon Zhou | E35: FTE | F35: 05 - Director | G35: Director, Analytical Lifecycle Management | H35: PNJ | I35: Business Critical | K35: 2027 Q2 | P35: ATA-TLA | Q35: Analytical Life Cycle | T35: Technical Expert
A36: 5312 | B36: Tech Ops | C36: 410 Manufacturing | D36: Leon Zhou | E36: FTE | F36: 03 - Sr. Manager | G36: Sr. Manager, Analytical Development | H36: SSF | I36: Business Critical | K36: 2027 Q2 | P36: Future Asset | Q36: Analytical Science | T36: Technical Expert
A37: 5313 | B37: Tech Ops | C37: 410 Manufacturing | D37: Leon Zhou | E37: FTE | F37: 03 - Sr. Manager | G37: Sr. Manager, Analytical Development | H37: SSF | I37: Business Critical | K37: 2027 Q2 | P37: Future Asset | Q37: Analytical Science | T37: Technical Expert
A38: 1198 | B38: Tech Ops | C38: 405 Supply Chain | D38: Aaron Misrack | E38: FTE | F38: 05 - Director | G38: Director, Supply Chain Planning | H38: PNJ | I38: Business Critical | K38: 2027 Q2 | P38: ATA-TLA-Dani | Q38: Planning, analytics, resilience strategy enablement | R38: Multiple assets | S38: Increasing CMO Network; SC complexity | T38: Technical Expert
A39: 5316 | B39: Tech Ops | C39: 410 Manufacturing | D39: Erika Riffel | E39: FTE | F39: 05 - Director | G39: Director, External Mfg. | H39: PNJ | I39: Business Critical | K39: 2027 Q2 | P39: ATA-TLA | Q39: Commercial CMO mgmt | R39: NDA submissions | S39: 9-12 mo ahead of NDA submission | T39: Emerging Leader
A40: 5320 | B40: Tech Ops | C40: 405 Supply Chain | D40: Taylor Elkington | E40: FTE | F40: 05 - Director | G40: Director, Clinical Supply Chain | H40: PNJ | I40: Business Critical | K40: 2027 Q2 | P40: ATA-TLA-Dani | Q40: Clinical Supply Chain | R40: OLE studies / additional indications / studies / programs | S40: OLE studies / additional indications / studies / programs | T40: Technical Expert
A41: 5322 | B41: Tech Ops | C41: 405 Supply Chain | D41: Taylor Elkington | E41: FTE | F41: 01 - Below Manager | G41: Clinical Supply Chain Associate | H41: SSF | I41: Business Critical | K41: 2027 Q2 | P41: TLA-Dani | Q41: Clinical Supply Chain | R41: Additional indications / studies / programs | S41: Additional indications / studies / programs | T41: Technical Expert
A42: 5325 | B42: Tech Ops | C42: 405 Supply Chain | D42: Senior Director, Commercial Supply Chain | E42: FTE | F42: 05 - Director | G42: Director, Commercial Supply Chain | H42: PNJ | I42: Business Critical | K42: 2027 Q2 | P42: ATA-TLA-Dani | Q42: Oversight of commercial SC and launch capabilities needed: 3PL, Serialization, State Licenses, Shipping Val, etc. | R42: Launches for ATA, TLA and DANI | S42: 9 mo prior to NDA filing
A43: 5297 | B43: Tech Ops | C43: 410 Manufacturing | D43: Gus Kodersha | E43: FTE | F43: 05 - Director | G43: Director | H43: PNJ | I43: Business Critical | K43: 2028 Q1 | P43: KAR-141 | Q43: KAR 141 tech transfer to support Reg stability studies | S43: KAR POM and POC results. KAR-141 Tech transfer to CDMO for Reg Stab production campaign | T43: Technical Expert
A44: 5317 | B44: Tech Ops | C44: 410 Manufacturing | D44: Erika Riffel | E44: FTE | F44: 05 - Director | G44: Director, External Mfg. | H44: PNJ | I44: Business Critical | K44: 2028 Q1 | P44: Dani-KAR-141 | Q44: Commercial CMO mgmt | R44: NDA submissions, KAR-141 advancement (POC start) | S44: 9-12 mo ahead of NDA submission | T44: Emerging Leader
A45: 5321 | B45: Tech Ops | C45: 405 Supply Chain | D45: Taylor Elkington | E45: FTE | F45: 03 - Sr. Manager | G45: Senior Manager, Clinical Supply Chain | H45: SSF | I45: Business Critical | K45: 2028 Q1 | P45: KAR-141 | Q45: Clinical Supply Chain | R45: Additional indications / studies / programs | S45: Additional indications / studies / programs | T45: Technical Expert
A46: 5326 | B46: Tech Ops | C46: 405 Supply Chain | D46: Senior Director, Commercial Supply Chain | E46: FTE | F46: 04 - Assoc. Director | G46: Associate Director, Commercial Supply Chain | H46: PNJ | I46: Business Critical | K46: 2028 Q1 | P46: ATA-TLA-Dani | Q46: Commercial Supply Chain; Artwork Mgmt, Pkg Eng for Expanded WW Markts; Support for WW Expansion | R46: Further building of internal capabilities | S46: ~6 mo prior to launch
A47: 5333 | B47: Tech Ops | C47: 410 Manufacturing | D47: William Walker | E47: FTE | F47: 06 - Sr. Director | G47: Tech Ops Program Lead (TOPL) | H47: PNJ | I47: Business Critical | K47: TBD | P47: Future Asset | Q47: Strategic, cross-functional leadership of Tech Ops program, accountable for development, NDA readiness, risks mgmt, and EC / GPT interface | R47: Multiple and concurrent early to late stage programs requiring dedicated strategic leadership to manage cross-functional Tech Ops activities | S47: 2x Emerging programs (including KAR-141) in portfolio and a 3rd within one quarter | T47: Emerging Leader
A48: 5334 | B48: Tech Ops | C48: 410 Manufacturing | D48: William Walker | E48: FTE | F48: 03 - Sr. Manager | G48: Tech Ops Program Manager | H48: PNJ | I48: Infrastructure / Support | K48: TBD | P48: Future Asset | Q48: Project management within CMC / Tech Ops, owning timelines, RAID, meetings, and cross-fcungional coordination across Tech Ops | R48: Enable execution of Tech Ops operating model (meetings, timeline, actions, RAID, etc.) driven by increasing complexity of deliverables | S48: 2x Emerging programs (including KAR-141) in portfolio and a 3rd within one quarter | T48: Emerging Leader
A49: 5342 | B49: G&A | C49: 915 Finance & Accounting | D49: Darrin Chang | E49: FTE | F49: 01 - Below Manager | G49: Accounting Analyst / Senior Accountant | H49: PNJ | K49: 2027 Q1 | P49: N/A | Q49: As Kardigan's headcount growth continues, we need a dedicated individual to support expense and corporate credit card reporting. This person would also help with the general increase in accounting activity | T49: New
A50: 5341 | B50: G&A | C50: 915 Finance & Accounting | D50: Darrin Chang | E50: FTE | F50: 02 - Manager | G50: Payroll | H50: PNJ | K50: 2027 Q1 | P50: N/A | Q50: Provide payroll support for large, scaling organization
A51: 5181 | B51: G&A | C51: 915 Finance & Accounting | D51: Darrin Chang | E51: FTE | F51: 05 - Director | G51: Cost Accounting | H51: SSF | K51: 2027 Q2 | P51: N/A | Q51: Provide Cost Accounting and inventory management capabilities to the organization as the company moves to commercialization | R51: Hired needed only if we have an assets that will be commercialized | S51: Hired needed only if we have an assets that will be commercialized
A52: 5343 | B52: G&A | C52: 915 Finance & Accounting | D52: Darrin Chang | E52: FTE | F52: 01 - Below Manager | G52: Accounting Analyst / Senior Accountant | H52: PNJ | K52: 2027 Q2 | P52: N/A | Q52: As Kardigan makes clincial progress and moves towards commericalization, we need a dedicated individual to support Sunshine Act reporting requirements. | T52: New
A53: 5182 | B53: G&A | C53: 915 Finance & Accounting | D53: Darrin Chang | E53: FTE | F53: 05 - Director | G53: SOX / Internal Audit | H53: SSF | K53: 2027 Q3 | P53: N/A | Q53: Leadership over necessary compliance and governence responsibilities for a publicy traded organization
A54: 5183 | B54: G&A | C54: 915 Finance & Accounting | D54: Darrin Chang | E54: FTE | F54: 05 - Director | G54: Revenue Accounting | H54: SSF | K54: 2028 Q2 | P54: N/A | Q54: Provide Revenue Accounting capabilities to the organization as the company moves to commercialization | R54: Hired needed only if we have an assets that will be commercialized | S54: Hired needed only if we have an assets that will be commercialized
A55: 1078 | B55: G&A | C55: 960 Facilities | D55: Oliver Sjahsam | E55: CW | F55: 01 - Below Manager | G55: Day Porter | H55: PNJ | K55: 2027 Q2 | L55: 2025 WFP Wave 3 | P55: N/A | Q55: Soft Services | S55: > 75 employees at the site
A56: 1350 | B56: G&A | C56: 960 Facilities | D56: Oliver Sjahsam | E56: FTE | F56: 2 - Below Manager | G56: Lab Ops Specialist | H56: SSF | K56: 2027 Q3 | L56: 2025 WFP Wave 3 | P56: N/A | Q56: Support Day to Day Lab Op/Stocking
A57: 5174 | B57: G&A | C57: 960 Facilities | D57: Oliver Sjahsam | E57: CW | F57: 01 - Below Manager | G57: Lab Ops Specialist | H57: SSF | I57: Capacity Building | K57: 2027 Q1 | P57: N/A | Q57: Lab Operations Support | R57: Additional SSF lab users >50, vivarium workload | S57: Post Phase II fit-out
A58: 5175 | B58: G&A | C58: 960 Facilities | D58: Oliver Sjahsam | E58: FTE | F58: 01 - Below Manager | G58: Facilities Technician | H58: SSF | I58: Infrastructure / Support | K58: 2027 Q2 | P58: N/A | Q58: Facilities Engineering | R58: Support lab metrology, utilities and specialized equipment | S58: Occupancy >85% SSF labs
A59: 5176 | B59: G&A | C59: 960 Facilities | D59: Oliver Sjahsam | E59: CW | F59: 01 - Below Manager | G59: Facilities Coordinator | H59: PNJ | I59: Capacity Building | K59: 2028 Q1 | P59: N/A | Q59: Facilities / Soft Services | R59: Princeton site >100 employees | S59: Headcount milestone reached
A60: 5177 | B60: G&A | C60: 960 Facilities | D60: Oliver Sjahsam | E60: CW | F60: 01 - Below Manager | G60: EHS Specialist | H60: SSF | I60: Business Critical | K60: 2027 Q2 | P60: N/A | Q60: EHS Compliance | R60: Support EHS Manager for vivarium & chemistry operations | S60: Chemistrystart up /Vivarium full operations
A61: 5212 | B61: G&A | C61: 910 People and Culture | D61: Liz Nguyen | E61: FTE | F61: 03 - Sr. Manager | G61: Sr. Talent Acquisition Partner | H61: PNJ | K61: 2027 Q1 | P61: N/A | Q61: People & Culture Leader
A62: 5213 | B62: G&A | C62: 910 People and Culture | D62: Liz Nguyen | E62: FTE | F62: 04 - Assoc. Director | G62: Total Rewards Analyst | H62: SSF | K62: 2027 Q1 | P62: N/A | Q62: Additional capacity to support comp and benefits for field and global staff
A63: 5366 | B63: Development | C63: 220 Clinical Data Science | D63: Wanying Li | E63: FTE | F63: 03 - Sr. Manager | G63: Senior Manager, Statistical Programming | H63: SSF or PNJ | K63: 2027 Q1 | P63: TLA | Q63: TLA-202 study lead | S63: Critical Role - Not Accounted for in top down guidance; shifted to 2027. | U63: 01 - Data Readout
A64: 5373 | B64: Development | C64: 220 Clinical Data Science | D64: Wanying Li | E64: FTE | F64: 03 - Sr. Manager | G64: Senior Manager, Statistical Programming | H64: SSF or PNJ | K64: 2027 Q1 | P64: ATA | Q64: ATA-301 study lead | S64: Critical Role - Not Accounted for in top down guidance; shifted to 2027. | U64: 01 - Data Readout
A65: 5049 | B65: Development | C65: 210 Clinical Operations | D65: Brianne Leary | E65: FTE | F65: 01 - Below Manager | G65: Associate Clinical Trial Manager | H65: SSF | K65: 2027 Q1 | P65: ATA | Q65: Post TAVR Study aCTM | U65: 01 - Data Readout
A66: 5053 | B66: Development | C66: 210 Clinical Operations | D66: Lisa Morello | E66: FTE | F66: 05 - Director | G66: Director, Clinical Operations Program lead | H66: PNJ | K66: 2027 Q1 | P66: ATA | Q66: ATA COPL New Indications | U66: 02 - Data Trigger
A67: 5054 | B67: Development | C67: 210 Clinical Operations | D67: Brianne Leary | E67: FTE | F67: 04 - Assoc. Director | G67: Clinical Trial Lead | H67: PNJ | K67: 2027 Q1 | P67: ATA | Q67: Mild AS Global CTL | U67: 02 - Data Trigger
A68: 5055 | B68: Development | C68: 210 Clinical Operations | D68: Brianne Leary | E68: FTE | F68: 04 - Assoc. Director | G68: Clinical Trial Lead | H68: PNJ | K68: 2027 Q1 | P68: ATA | Q68: Post TAVR Global CTL | U68: 02 - Data Trigger
A69: 5058 | B69: Development | C69: 210 Clinical Operations | D69: Brianne Leary | E69: FTE | F69: 02 - Manager | G69: Clinical Trial Manager | H69: PNJ | K69: 2027 Q1 | P69: ATA | Q69: Mild AS CTM | U69: 02 - Data Trigger
A70: 5059 | B70: Development | C70: 210 Clinical Operations | D70: Brianne Leary | E70: FTE | F70: 01 - Below Manager | G70: Associate Clinical Trial Manager | H70: PNJ | K70: 2027 Q1 | P70: ATA | Q70: Mild AS aCTM | U70: 02 - Data Trigger
A71: 5060 | B71: Development | C71: 210 Clinical Operations | D71: Brianne Leary | E71: FTE | F71: 04 - Assoc. Director | G71: Clinical Trial Lead | H71: PNJ | K71: 2027 Q1 | P71: ATA | Q71: Bi-Cuspid CTL | U71: 02 - Data Trigger
A72: 5061 | B72: Development | C72: 210 Clinical Operations | D72: Brianne Leary | E72: FTE | F72: 02 - Manager | G72: Clinical Trial Manager | H72: PNJ | K72: 2027 Q1 | P72: ATA | Q72: Post TAVR CTM | U72: 02 - Data Trigger
A73: 5065 | B73: Development | C73: 210 Clinical Operations | D73: Brianne Leary | E73: FTE | F73: 06 - Sr. Director | G73: Clinical Operations Program Lead | H73: PNJ | K73: 2027 Q1 | P73: ATA-KAR-141 | Q73: ClinOps Program Management: Combo ATA+KAR-141 | U73: 02 - Data Trigger
A74: 5072 | B74: Development | C74: 210 Clinical Operations | D74: Brianne Leary | E74: FTE | F74: 05 - Director | G74: Sample and Data Governance | H74: PNJ | K74: 2027 Q1 | P74: N/A
A75: 5076 | B75: Development | C75: 210 Clinical Operations | D75: Brianne Leary | E75: FTE | F75: 02 - Manager | G75: Clinical Trial Manager | H75: PNJ | K75: 2027 Q1 | P75: N/A | Q75: Early Development - New Programs
A76: 5081 | B76: Development | C76: 210 Clinical Operations | D76: Brianne Leary | E76: FTE | F76: 03 - Sr. Manager | G76: TMF Lead | H76: PNJ | K76: 2027 Q1 | P76: N/A
A77: 5082 | B77: Development | C77: 210 Clinical Operations | D77: Brianne Leary | E77: FTE | F77: 01 - Below Manager | G77: Clinical Document Specialist | H77: PNJ | K77: 2027 Q1 | P77: N/A
A78: 5084 | B78: Development | C78: 210 Clinical Operations | D78: Brianne Leary | E78: FTE | F78: 06 - Sr. Director | G78: Clinical Operations Excellence | H78: PNJ | K78: 2027 Q1 | P78: N/A
A79: 5099 | B79: Development | C79: 210 Clinical Operations | D79: Brianne Leary | E79: FTE | F79: 04 - Assoc. Director | G79: Clinical Trial Lead | H79: PNJ | I79: LVAD | K79: 2027 Q1 | P79: Dani | Q79: LVAD CTL
A80: 5100 | B80: Development | C80: 210 Clinical Operations | D80: Brianne Leary | E80: FTE | F80: 02 - Manager | G80: Clinical Trial Manager | H80: PNJ | K80: 2027 Q1 | P80: Dani | Q80: LVAD CTM
A81: 5101 | B81: Development | C81: 210 Clinical Operations | D81: Brianne Leary | E81: FTE | F81: 01 - Below Manager | G81: Associate Clinical Trial Manager | H81: PNJ | K81: 2027 Q1 | P81: Dani | Q81: LVAD CTA
A82: 5106 | B82: Development | C82: 210 Clinical Operations | D82: Brianne Leary | E82: FTE | F82: 04 - Assoc. Director | G82: Clinical Trial Lead | H82: PNJ | K82: 2027 Q1 | P82: N/A | Q82: Early Development - New Programs
A83: 5056 | B83: Development | C83: 210 Clinical Operations | D83: Brianne Leary | E83: CW | F83: 01 - Below Manager | G83: Sr. Clinical Trial Associate | H83: PNJ | K83: 2027 Q1 | P83: ATA | Q83: Post TAVR Study CTA | U83: 02 - Data Trigger
A84: 5078 | B84: Development | C84: 210 Clinical Operations | D84: Andrea Koh | E84: CW | F84: 02 - Manager | G84: Clinical Outsourcing | H84: PNJ | K84: 2027 Q1 | P84: N/A | U84: 01 - Data Readout
A85: 5044 | B85: Development | C85: 215 Clinical Development | D85: Cheryl Abbas | E85: FTE | F85: 07 - Exec. Director | G85: Executive Director, Clinical Development Lead | H85: PNJ | I85: Business Critical/ Infrasructure & Support | K85: 2027 Q1 | P85: ATA (Post-TAVR) | Q85: Doctorate degree; Clinical oversight of post-TAVR strategy & trial execution, post-TAVR CDP development | R85: Development of post-TAVR strategy clinical trial program | S85: Preparation for post-TAVR CDP | T85: Experienced Leader | U85: 02 - Data Trigger
A86: 5003 | B86: Development | C86: 220 Clinical Data Science | D86: Frances Dingle | E86: FTE | F86: 04 - Assoc. Director | G86: Associate Director, Clinical Programming | H86: SSF or PNJ | K86: 2027 Q1 | L86: Moved to 2027 | P86: N/A | Q86: Lead DM for TLA 2nd Indication | R86: support growing TLA pipeline activities | S86: TLA 2nd indication protocol synopsis | U86: moved to 2027
A87: 5027 | B87: Development | C87: 220 Clinical Data Science | D87: Lauren Cao | E87: FTE | F87: 03 - Sr. Manager | G87: Senior Manager, Data Management | H87: SSF | K87: 2027 Q1 | L87: moved to 2027 | P87: ATA | Q87: CRO oversight, ATA Mild AS study DB build and cross functional study launch activities | R87: Lead DM for ATA Mild AS | S87: ATA Mild AS study launch (Synopsis) | U87: 02 - Data Trigger
A88: 5030 | B88: Development | C88: 220 Clinical Data Science | D88: Lauren Cao | E88: FTE | F88: 03 - Sr. Manager | G88: Senior Manager, Data Management | H88: SSF or PNJ | K88: 2027 Q1 | L88: Moved to 2027 | P88: ATA | Q88: lead DM for ATA Post TAVR study DB build and cross functional study launch activities | R88: initiation of ATA Post TAVR study: synopsis | S88: initiation of ATA Post TAVR study: synopsis | U88: 02 - Data Trigger
A89: 5034 | B89: Development | C89: 220 Clinical Data Science | D89: Lauren Cao | E89: FTE | F89: 04 - Assoc. Director | G89: Associate Director, Clinical Programming | H89: SSF or PNJ | K89: 2027 Q1 | L89: Moved to 2027 | P89: N/A | Q89: EDC URL Management and Configuration oversight
A90: 1018 | B90: Development | C90: 220 Clinical Data Science | D90: Wanying Li | E90: FTE | F90: 05 - Director | G90: Director, Data Science | H90: SSF | K90: 2027 Q1 | P90: N/A | Q90: Data Science for Advanced Analytics, lead for Data Excellence Center | T90: Experienced Leader
A91: 5005 | B91: Development | C91: 220 Clinical Data Science | D91: Wanying Li | E91: FTE | F91: 06 - Sr. Director | G91: Sr Director, Statistical Strategy and Standards | H91: SSF | K91: 2027 Q1 | P91: N/A | Q91: Regulatory senior stat review and strategy planning, innovative study design research | U91: 03 - NDA Submission
A92: 5007 | B92: Development | C92: 220 Clinical Data Science | D92: Wanying Li | E92: FTE | F92: 04 - Assoc. Director | G92: Associate Director, Biostatistician ATA | H92: SSF or PNJ | K92: 2027 Q1 | P92: ATA | Q92: Biostat support for ATA | S92: Gate on ATA-301 positive wk 24 data readout | U92: 02 - Data Trigger
A93: 5008 | B93: Development | C93: 220 Clinical Data Science | D93: Wanying Li | E93: FTE | F93: 03 - Sr. Manager | G93: Senior Manager, Statistical Programming | H93: SSF or PNJ | K93: 2027 Q1 | P93: ATA | Q93: Stat programming support for ATA submission | S93: Gate on ATA-301 positive wk 24 data readout | U93: 02 - Data Trigger
A94: 5010 | B94: Development | C94: 220 Clinical Data Science | D94: Wanying Li | E94: FTE | F94: 03 - Sr. Manager | G94: Senior Manager, Statistical Programming | H94: SSF or PNJ | K94: 2027 Q1 | P94: TLA | Q94: Stat programming support for TLA submission | S94: Gate on TLA-301 positive Part 1 data readout | U94: 02 - Data Trigger
A95: 5012 | B95: Development | C95: 220 Clinical Data Science | D95: Wanying Li | E95: FTE | F95: 04 - Assoc. Director | G95: Associate Director, Statistical Programming | H95: SSF or PNJ | K95: 2027 Q1 | P95: N/A | Q95: Biostat programming for legacy studies readiness for submission | U95: 03 - NDA Submission
A96: 5014 | B96: Development | C96: 220 Clinical Data Science | D96: Wanying Li | E96: FTE | F96: 04 - Assoc. Director | G96: Clinical Data Scientist | H96: SSF or PNJ | K96: 2027 Q1 | P96: N/A | Q96: Data visualization and dashboard build
A97: 5017 | B97: Development | C97: 220 Clinical Data Science | D97: Wanying Li | E97: FTE | F97: 05 - Director | G97: Director, Biostatistics | H97: SSF or PNJ | K97: 2027 Q1 | P97: Early development | Q97: Early development programs, including KAR141 and clin pharm studies and other IND activities, and RWD or registrational study | U97: 01 - Data Readout
A98: 5018 | B98: Development | C98: 220 Clinical Data Science | D98: Wanying Li | E98: FTE | F98: 03 - Sr. Manager | G98: Sr Manager, Biostatistics | H98: SSF or PNJ | K98: 2027 Q1 | P98: Early development | Q98: Supporting early development biostat activities | U98: 01 - Data Readout
A99: 5019 | B99: Development | C99: 220 Clinical Data Science | D99: Wanying Li | E99: FTE | F99: 04 - Assoc. Director | G99: Associate Director, Statistical Programming | H99: SSF or PNJ | K99: 2027 Q1 | P99: Early development | Q99: Supporting early development programming activities | U99: 01 - Data Readout
A100: 5020 | B100: Development | C100: 220 Clinical Data Science | D100: Wanying Li | E100: FTE | F100: 03 - Sr. Manager | G100: Sr Manager, Statistical Programming | H100: SSF or PNJ | K100: 2027 Q1 | P100: Early development | Q100: Supporting early development programming activities | U100: 01 - Data Readout
...

Sheet 2026 Approved Budget
H2: Subtotal | K2: =SUBTOTAL(9,K8:K1048576) -> 160 | L2: =SUBTOTAL(9,L8:L1048576) -> 160 | M2: =SUBTOTAL(9,M8:M1048576) -> 204 | N2: =SUBTOTAL(9,N8:N1048576) -> 204 | O2: =SUBTOTAL(9,O8:O1048576) -> 204 | P2: =SUBTOTAL(9,P8:P1048576) -> 224 | Q2: =SUBTOTAL(9,Q8:Q1048576) -> 224 | R2: =SUBTOTAL(9,R8:R1048576) -> 224 | ... AT2: =SUBTOTAL(9,AT8:AT1048576) -> 255
C3: Duplicate Temp Job IDs | H3: Total | K3: =SUM(K8:K1048576) -> 160 | L3: =SUM(L8:L1048576) -> 160 | M3: =SUM(M8:M1048576) -> 204 | N3: =SUM(N8:N1048576) -> 204 | O3: =SUM(O8:O1048576) -> 204 | P3: =SUM(P8:P1048576) -> 224 | Q3: =SUM(Q8:Q1048576) -> 224 | R3: =SUM(R8:R1048576) -> 224 | ... AT3: =SUM(AT8:AT1048576) -> 521
C4: 5273 / 5029 / 5357 / 5358
K5: 2026 | L5: 2026 | M5: 2026 | N5: 2026 | O5: 2026 | P5: 2026 | Q5: 2026 | R5: 2026 | S5: 2026 | T5: 2026 | U5: 2026 | V5: 2026 | W5: 2027 | X5: 2027 | Y5: 2027 | Z5: 2027 | AA5: 2027 | AB5: 2027 | AC5: 2027 | AD5: 2027 | AE5: 2027 | AF5: 2027 | AG5: 2027 | AH5: 2027 | AI5: 2028 | AJ5: 2028 | AK5: 2028 | AL5: 2028 | AM5: 2028 | AN5: 2028 | AO5: 2028 | AP5: 2028 | AQ5: 2028 | AR5: 2028 | AS5: 2028 | AT5: 2028
K6: Q1 | L6: Q1 | M6: Q1 | N6: Q2 | O6: Q2 | P6: Q2 | Q6: Q3 | R6: Q3 | S6: Q3 | T6: Q4 | U6: Q4 | V6: Q4 | W6: Q1 | X6: Q1 | Y6: Q1 | Z6: Q2 | AA6: Q2 | AB6: Q2 | AC6: Q3 | AD6: Q3 | AE6: Q3 | AF6: Q4 | AG6: Q4 | AH6: Q4 | AI6: Q1 | AJ6: Q1 | AK6: Q1 | AL6: Q2 | AM6: Q2 | AN6: Q2 | AO6: Q3 | AP6: Q3 | AQ6: Q3 | AR6: Q4 | AS6: Q4 | AT6: Q4
B7: Temp Job ID | C7: Department | D7: Employee Name | E7: Level | F7: Job title | G7: check | H7: Start Date | I7: Start Date (Month) | J7: Start Date (Year) | K7: Jan | L7: Feb | M7: Mar | N7: Apr | O7: May | P7: Jun | Q7: Jul | R7: Aug | S7: Sep | T7: Oct | U7: Nov | V7: Dec | W7: Jan | X7: Feb | Y7: Mar | Z7: Apr | AA7: May | AB7: Jun | AC7: Jul | AD7: Aug | AE7: Sep | AF7: Oct | AG7: Nov | AH7: Dec | AI7: Jan | AJ7: Feb | AK7: Mar | AL7: Apr | AM7: May | AN7: Jun | AO7: Jul | AP7: Aug | AQ7: Sep | AR7: Oct | AS7: Nov | AT7: Dec
B8: 1195 | C8: 105 Research and Translational Science | D8: Carlos del Rio | E8: 08. VP | F8: Vice President, Research and Translational Sciences | G8: =_xlfn.XLOOKUP(B8,'WFP Details - 2026'!A:A,'WFP Details - 2026'!Z:Z) -> x | H8: 45292 | I8: 1 | J8: 2024 | K8: 1 | L8: 1 | M8: 1 | N8: 1 | O8: 1 | P8: 1 | Q8: 1 | R8: 1 | S8: 1 | T8: 1 | U8: 1 | V8: 1 | W8: 1 | X8: 1 | Y8: 1 | Z8: 1 | AA8: 1 | AB8: 1 | AC8: 1 | AD8: 1 | AE8: 1 | AF8: 1 | AG8: 1 | AH8: 1 | AI8: 1 | AJ8: 1 | AK8: 1 | AL8: 1 | AM8: 1 | AN8: 1 | AO8: 1 | AP8: 1 | AQ8: 1 | AR8: 1 | AS8: 1 | AT8: 1
B9: 1192 | C9: 105 Research and Translational Science | D9: Rafael Shimkunas | E9: 03. Sr. Manager / Sr. Scientist | F9: Principal Scientist, Biology | G9: =_xlfn.XLOOKUP(B9,'WFP Details - 2026'!A:A,'WFP Details - 2026'!Z:Z) -> x | H9: 45488 | I9: 7 | J9: 2024 | K9: 1 | L9: 1 | M9: 1 | N9: 1 | O9: 1 | P9: 1 | Q9: 1 | R9: 1 | S9: 1 | T9: 1 | U9: 1 | V9: 1 | W9: 1 | X9: 1 | Y9: 1 | Z9: 1 | AA9: 1 | AB9: 1 | AC9: 1 | AD9: 1 | AE9: 1 | AF9: 1 | AG9: 1 | AH9: 1 | AI9: 1 | AJ9: 1 | AK9: 1 | AL9: 1 | AM9: 1 | AN9: 1 | AO9: 1 | AP9: 1 | AQ9: 1 | AR9: 1 | AS9: 1 | AT9: 1
B10: 1176 | C10: 105 Research and Translational Science | D10: Dilara Batan | E10: 02. Manager / Scientist | F10: Scientist, Biology | G10: =_xlfn.XLOOKUP(B10,'WFP Details - 2026'!A:A,'WFP Details - 2026'!Z:Z) -> x | H10: 45509 | I10: 8 | J10: 2024 | K10: 1 | L10: 1 | M10: 1 | N10: 1 | O10: 1 | P10: 1 | Q10: 1 | R10: 1 | S10: 1 | T10: 1 | U10: 1 | V10: 1 | W10: 1 | X10: 1 | Y10: 1 | Z10: 1 | AA10: 1 | AB10: 1 | AC10: 1 | AD10: 1 | AE10: 1 | AF10: 1 | AG10: 1 | AH10: 1 | AI10: 1 | AJ10: 1 | AK10: 1 | AL10: 1 | AM10: 1 | AN10: 1 | AO10: 1 | AP10: 1 | AQ10: 1 | AR10: 1 | AS10: 1 | AT10: 1
B11: 1174 | C11: 105 Research and Translational Science | D11: Anu Anto | E11: 02. Manager / Scientist | F11: Scientist, Biology | G11: =_xlfn.XLOOKUP(B11,'WFP Details - 2026'!A:A,'WFP Details - 2026'!Z:Z) -> x | H11: 45523 | I11: 8 | J11: 2024 | K11: 1 | L11: 1 | M11: 1 | N11: 1 | O11: 1 | P11: 1 | Q11: 1 | R11: 1 | S11: 1 | T11: 1 | U11: 1 | V11: 1 | W11: 1 | X11: 1 | Y11: 1 | Z11: 1 | AA11: 1 | AB11: 1 | AC11: 1 | AD11: 1 | AE11: 1 | AF11: 1 | AG11: 1 | AH11: 1 | AI11: 1 | AJ11: 1 | AK11: 1 | AL11: 1 | AM11: 1 | AN11: 1 | AO11: 1 | AP11: 1 | AQ11: 1 | AR11: 1 | AS11: 1 | AT11: 1
B12: 1169 | C12: 105 Research and Translational Science | D12: Na Sa | E12: 04. AD / Staff Scientist | F12: Staff Scientist, Director, Sarcomere Biology | G12: =_xlfn.XLOOKUP(B12,'WFP Details - 2026'!A:A,'WFP Details - 2026'!Z:Z) -> x | H12: 45523 | I12: 8 | J12: 2024 | K12: 1 | L12: 1 | M12: 1 | N12: 1 | O12: 1 | P12: 1 | Q12: 1 | R12: 1 | S12: 1 | T12: 1 | U12: 1 | V12: 1 | W12: 1 | X12: 1 | Y12: 1 | Z12: 1 | AA12: 1 | AB12: 1 | AC12: 1 | AD12: 1 | AE12: 1 | AF12: 1 | AG12: 1 | AH12: 1 | AI12: 1 | AJ12: 1 | AK12: 1 | AL12: 1 | AM12: 1 | AN12: 1 | AO12: 1 | AP12: 1 | AQ12: 1 | AR12: 1 | AS12: 1 | AT12: 1
B13: 1172 | C13: 105 Research and Translational Science | D13: Jani Saksi | E13: 03. Sr. Manager / Sr. Scientist | F13: Senior Scientist, Biology | G13: =_xlfn.XLOOKUP(B13,'WFP Details - 2026'!A:A,'WFP Details - 2026'!Z:Z) -> x | H13: 45551 | I13: 9 | J13: 2024 | K13: 1 | L13: 1 | M13: 1 | N13: 1 | O13: 1 | P13: 1 | Q13: 1 | R13: 1 | S13: 1 | T13: 1 | U13: 1 | V13: 1 | W13: 1 | X13: 1 | Y13: 1 | Z13: 1 | AA13: 1 | AB13: 1 | AC13: 1 | AD13: 1 | AE13: 1 | AF13: 1 | AG13: 1 | AH13: 1 | AI13: 1 | AJ13: 1 | AK13: 1 | AL13: 1 | AM13: 1 | AN13: 1 | AO13: 1 | AP13: 1 | AQ13: 1 | AR13: 1 | AS13: 1 | AT13: 1
B14: 1182 | C14: 105 Research and Translational Science | D14: Mary Papadaki | E14: 03. Sr. Manager / Sr. Scientist | F14: Principal Scientist, In Vitro Pharmacology | G14: =_xlfn.XLOOKUP(B14,'WFP Details - 2026'!A:A,'WFP Details - 2026'!Z:Z) -> x | H14: 45551 | I14: 9 | J14: 2024 | K14: 1 | L14: 1 | M14: 1 | N14: 1 | O14: 1 | P14: 1 | Q14: 1 | R14: 1 | S14: 1 | T14: 1 | U14: 1 | V14: 1 | W14: 1 | X14: 1 | Y14: 1 | Z14: 1 | AA14: 1 | AB14: 1 | AC14: 1 | AD14: 1 | AE14: 1 | AF14: 1 | AG14: 1 | AH14: 1 | AI14: 1 | AJ14: 1 | AK14: 1 | AL14: 1 | AM14: 1 | AN14: 1 | AO14: 1 | AP14: 1 | AQ14: 1 | AR14: 1 | AS14: 1 | AT14: 1
B15: 1187 | C15: 105 Research and Translational Science | D15: Saffie Mohran | E15: 02. Manager / Scientist | F15: Scientist, In Vitro Pharmacology | G15: =_xlfn.XLOOKUP(B15,'WFP Details - 2026'!A:A,'WFP Details - 2026'!Z:Z) -> x | H15: 45551 | I15: 9 | J15: 2024 | K15: 1 | L15: 1 | M15: 1 | N15: 1 | O15: 1 | P15: 1 | Q15: 1 | R15: 1 | S15: 1 | T15: 1 | U15: 1 | V15: 1 | W15: 1 | X15: 1 | Y15: 1 | Z15: 1 | AA15: 1 | AB15: 1 | AC15: 1 | AD15: 1 | AE15: 1 | AF15: 1 | AG15: 1 | AH15: 1 | AI15: 1 | AJ15: 1 | AK15: 1 | AL15: 1 | AM15: 1 | AN15: 1 | AO15: 1 | AP15: 1 | AQ15: 1 | AR15: 1 | AS15: 1 | AT15: 1
B16: 1154 | C16: 105 Research and Translational Science | D16: Hector Manuel Rodriguez | E16: 08. VP | F16: Vice President, New Targets | G16: =_xlfn.XLOOKUP(B16,'WFP Details - 2026'!A:A,'WFP Details - 2026'!Z:Z) -> x | H16: 45706 | I16: 2 | J16: 2025 | K16: 1 | L16: 1 | M16: 1 | N16: 1 | O16: 1 | P16: 1 | Q16: 1 | R16: 1 | S16: 1 | T16: 1 | U16: 1 | V16: 1 | W16: 1 | X16: 1 | Y16: 1 | Z16: 1 | AA16: 1 | AB16: 1 | AC16: 1 | AD16: 1 | AE16: 1 | AF16: 1 | AG16: 1 | AH16: 1 | AI16: 1 | AJ16: 1 | AK16: 1 | AL16: 1 | AM16: 1 | AN16: 1 | AO16: 1 | AP16: 1 | AQ16: 1 | AR16: 1 | AS16: 1 | AT16: 1
B17: 1173 | C17: 105 Research and Translational Science | D17: Christine Rivera | E17: 02. Manager / Scientist | F17: Associate Scientist, Biochemistry | G17: =_xlfn.XLOOKUP(B17,'WFP Details - 2026'!A:A,'WFP Details - 2026'!Z:Z) -> x | H17: 45880 | I17: 8 | J17: 2025 | K17: 1 | L17: 1 | M17: 1 | N17: 1 | O17: 1 | P17: 1 | Q17: 1 | R17: 1 | S17: 1 | T17: 1 | U17: 1 | V17: 1 | W17: 1 | X17: 1 | Y17: 1 | Z17: 1 | AA17: 1 | AB17: 1 | AC17: 1 | AD17: 1 | AE17: 1 | AF17: 1 | AG17: 1 | AH17: 1 | AI17: 1 | AJ17: 1 | AK17: 1 | AL17: 1 | AM17: 1 | AN17: 1 | AO17: 1 | AP17: 1 | AQ17: 1 | AR17: 1 | AS17: 1 | AT17: 1
B18: 1170 | C18: 105 Research and Translational Science | D18: CW: Hannah Kleppe | E18: 01. IC / Coordinator | F18: SRA, Biology | G18: =_xlfn.XLOOKUP(B18,'WFP Details - 2026'!A:A,'WFP Details - 2026'!Z:Z) -> x | H18: 46096 | I18: 3 | J18: 2026 | K18: 0 | L18: 0 | M18: 1 | N18: 1 | O18: 1 | P18: 1 | Q18: 1 | R18: 1 | S18: 1 | T18: 1 | U18: 1 | V18: 1 | W18: 1 | X18: 1 | Y18: 1 | Z18: 1 | AA18: 1 | AB18: 1 | AC18: 1 | AD18: 1 | AE18: 1 | AF18: 1 | AG18: 1 | AH18: 1 | AI18: 1 | AJ18: 1 | AK18: 1 | AL18: 1 | AM18: 1 | AN18: 1 | AO18: 1 | AP18: 1 | AQ18: 1 | AR18: 1 | AS18: 1 | AT18: 1
B19: 1177 | C19: 105 Research and Translational Science | D19: TBD | E19: 02. Manager / Scientist | F19: Scientist, TM (Computational Biologist) - Omics (transcriptomics) | G19: =_xlfn.XLOOKUP(B19,'WFP Details - 2026'!A:A,'WFP Details - 2026'!Z:Z) -> x | H19: 46096 | I19: 3 | J19: 2026 | K19: 0 | L19: 0 | M19: 1 | N19: 1 | O19: 1 | P19: 1 | Q19: 1 | R19: 1 | S19: 1 | T19: 1 | U19: 1 | V19: 1 | W19: 1 | X19: 1 | Y19: 1 | Z19: 1 | AA19: 1 | AB19: 1 | AC19: 1 | AD19: 1 | AE19: 1 | AF19: 1 | AG19: 1 | AH19: 1 | AI19: 1 | AJ19: 1 | AK19: 1 | AL19: 1 | AM19: 1 | AN19: 1 | AO19: 1 | AP19: 1 | AQ19: 1 | AR19: 1 | AS19: 1 | AT19: 1
... B193: 5020 | C193: 220 Clinical Data Science | D193: TBD | E193: 03. Sr. Manager / Sr. Scientist | F193: Sr Manager, Statistical Programming | G193: =_xlfn.XLOOKUP(B193,'WFP Details - 2026'!A:A,'WFP Details - 2026'!Z:Z) -> #N/A | H193: 46461 | I193: 3 | J193: 2027 | K193: 0 | L193: 0 | M193: 0 | N193: 0 | O193: 0 | P193: 0 | Q193: 0 | R193: 0 | S193: 0 | T193: 0 | U193: 0 | V193: 0 | W193: 0 | X193: 0 | Y193: 1 | Z193: 1 | AA193: 1 | AB193: 1 | AC193: 1 | AD193: 1 | AE193: 1 | AF193: 1 | AG193: 1 | AH193: 1 | AI193: 1 | AJ193: 1 | AK193: 1 | AL193: 1 | AM193: 1 | AN193: 1 | AO193: 1 | AP193: 1 | AQ193: 1 | AR193: 1 | AS193: 1 | AT193: 1
B194: 6000 (5357 Previously) | C194: 220 Clinical Data Science | D194: TBD | E194: 04. AD / Staff Scientist | F194: Associate Director, Statistical Strategy and Standards | G194: =_xlfn.XLOOKUP(B194,'WFP Details - 2026'!A:A,'WFP Details - 2026'!Z:Z) -> #N/A | H194: 46461 | I194: 3 | J194: 2027 | K194: 0 | L194: 0 | M194: 0 | N194: 0 | O194: 0 | P194: 0 | Q194: 0 | R194: 0 | S194: 0 | T194: 0 | U194: 0 | V194: 0 | W194: 0 | X194: 0 | Y194: 1 | Z194: 1 | AA194: 1 | AB194: 1 | AC194: 1 | AD194: 1 | AE194: 1 | AF194: 1 | AG194: 1 | AH194: 1 | AI194: 1 | AJ194: 1 | AK194: 1 | AL194: 1 | AM194: 1 | AN194: 1 | AO194: 1 | AP194: 1 | AQ194: 1 | AR194: 1 | AS194: 1 | AT194: 1
B195: 6001 (5358 Previously) | C195: 220 Clinical Data Science | D195: TBD | E195: 03. Sr. Manager / Sr. Scientist | F195: Senior Manager, Biostatistician | G195: =_xlfn.XLOOKUP(B195,'WFP Details - 2026'!A:A,'WFP Details - 2026'!Z:Z) -> #N/A | H195: 46461 | I195: 3 | J195: 2027 | K195: 0 | L195: 0 | M195: 0 | N195: 0 | O195: 0 | P195: 0 | Q195: 0 | R195: 0 | S195: 0 | T195: 0 | U195: 0 | V195: 0 | W195: 0 | X195: 0 | Y195: 1 | Z195: 1 | AA195: 1 | AB195: 1 | AC195: 1 | AD195: 1 | AE195: 1 | AF195: 1 | AG195: 1 | AH195: 1 | AI195: 1 | AJ195: 1 | AK195: 1 | AL195: 1 | AM195: 1 | AN195: 1 | AO195: 1 | AP195: 1 | AQ195: 1 | AR195: 1 | AS195: 1 | AT195: 1
B196: 5364 | C196: 220 Clinical Data Science | D196: TBD | E196: 03. Sr. Manager / Sr. Scientist | F196: Senior Manager, Statistical Programming | G196: =_xlfn.XLOOKUP(B196,'WFP Details - 2026'!A:A,'WFP Details - 2026'!Z:Z) -> #N/A | H196: 46461 | I196: 3 | J196: 2027 | K196: 0 | L196: 0 | M196: 0 | N196: 0 | O196: 0 | P196: 0 | Q196: 0 | R196: 0 | S196: 0 | T196: 0 | U196: 0 | V196: 0 | W196: 0 | X196: 0 | Y196: 1 | Z196: 1 | AA196: 1 | AB196: 1 | AC196: 1 | AD196: 1 | AE196: 1 | AF196: 1 | AG196: 1 | AH196: 1 | AI196: 1 | AJ196: 1 | AK196: 1 | AL196: 1 | AM196: 1 | AN196: 1 | AO196: 1 | AP196: 1 | AQ196: 1 | AR196: 1 | AS196: 1 | AT196: 1
B197: 5370 | C197: 220 Clinical Data Science | D197: TBD | E197: 04. AD / Staff Scientist | F197: Associate Director, Statistical Strategy and Standards | G197: =_xlfn.XLOOKUP(B197,'WFP Details - 2026'!A:A,'WFP Details - 2026'!Z:Z) -> #N/A | H197: 46461 | I197: 3 | J197: 2027 | K197: 0 | L197: 0 | M197: 0 | N197: 0 | O197: 0 | P197: 0 | Q197: 0 | R197: 0 | S197: 0 | T197: 0 | U197: 0 | V197: 0 | W197: 0 | X197: 0 | Y197: 1 | Z197: 1 | AA197: 1 | AB197: 1 | AC197: 1 | AD197: 1 | AE197: 1 | AF197: 1 | AG197: 1 | AH197: 1 | AI197: 1 | AJ197: 1 | AK197: 1 | AL197: 1 | AM197: 1 | AN197: 1 | AO197: 1 | AP197: 1 | AQ197: 1 | AR197: 1 | AS197: 1 | AT197: 1
B198: 1020 | C198: 221 Clinical Data Management | D198: Lauren Cao | E198: 06. Sr. Director | F198: Senior Director, Clinical Data Management | G198: =_xlfn.XLOOKUP(B198,'WFP Details - 2026'!A:A,'WFP Details - 2026'!Z:Z) -> x | H198: 45572 | I198: 10 | J198: 2024 | K198: 1 | L198: 1 | M198: 1 | N198: 1 | O198: 1 | P198: 1 | Q198: 1 | R198: 1 | S198: 1 | T198: 1 | U198: 1 | V198: 1 | W198: 1 | X198: 1 | Y198: 1 | Z198: 1 | AA198: 1 | AB198: 1 | AC198: 1 | AD198: 1 | AE198: 1 | AF198: 1 | AG198: 1 | AH198: 1 | AI198: 1 | AJ198: 1 | AK198: 1 | AL198: 1 | AM198: 1 | AN198: 1 | AO198: 1 | AP198: 1 | AQ198: 1 | AR198: 1 | AS198: 1 | AT198: 1
B199: 1013 | C199: 221 Clinical Data Management | D199: David Lim | E199: 03. Sr. Manager / Sr. Scientist | F199: Associate Director, Clinical Data Management ATA | G199: =_xlfn.XLOOKUP(B199,'WFP Details - 2026'!A:A,'WFP Details - 2026'!Z:Z) -> x | H199: 45642 | I199: 12 | J199: 2024 | K199: 1 | L199: 1 | M199: 1 | N199: 1 | O199: 1 | P199: 1 | Q199: 1 | R199: 1 | S199: 1 | T199: 1 | U199: 1 | V199: 1 | W199: 1 | X199: 1 | Y199: 1 | Z199: 1 | AA199: 1 | AB199: 1 | AC199: 1 | AD199: 1 | AE199: 1 | AF199: 1 | AG199: 1 | AH199: 1 | AI199: 1 | AJ199: 1 | AK199: 1 | AL199: 1 | AM199: 1 | AN199: 1 | AO199: 1 | AP199: 1 | AQ199: 1 | AR199: 1 | AS199: 1 | AT199: 1
B200: 1015 | C200: 221 Clinical Data Management | D200: Sheri Van Zandt | E200: 04. AD / Staff Scientist | F200: Associate Director, Clinical Data Management Dani | G200: =_xlfn.XLOOKUP(B200,'WFP Details - 2026'!A:A,'WFP Details - 2026'!Z:Z) -> x | H200: 45824 | I200: 6 | J200: 2025 | K200: 1 | L200: 1 | M200: 1 | N200: 1 | O200: 1 | P200: 1 | Q200: 1 | R200: 1 | S200: 1 | T200: 1 | U200: 1 | V200: 1 | W200: 1 | X200: 1 | Y200: 1 | Z200: 1 | AA200: 1 | AB200: 1 | AC200: 1 | AD200: 1 | AE200: 1 | AF200: 1 | AG200: 1 | AH200: 1 | AI200: 1 | AJ200: 1 | AK200: 1 | AL200: 1 | AM200: 1 | AN200: 1 | AO200: 1 | AP200: 1 | AQ200: 1 | AR200: 1 | AS200: 1 | AT200: 1
B201: 1014 | C201: 221 Clinical Data Management | D201: Frances Seput Dingle | E201: 05. Director | F201: Associate Director, Clinical Data Management TLA | G201: =_xlfn.XLOOKUP(B201,'WFP Details - 2026'!A:A,'WFP Details - 2026'!Z:Z) -> x | H201: 45929 | I201: 9 | J201: 2025 | K201: 1 | L201: 1 | M201: 1 | N201: 1 | O201: 1 | P201: 1 | Q201: 1 | R201: 1 | S201: 1 | T201: 1 | U201: 1 | V201: 1 | W201: 1 | X201: 1 | Y201: 1 | Z201: 1 | AA201: 1 | AB201: 1 | AC201: 1 | AD201: 1 | AE201: 1 | AF201: 1 | AG201: 1 | AH201: 1 | AI201: 1 | AJ201: 1 | AK201: 1 | AL201: 1 | AM201: 1 | AN201: 1 | AO201: 1 | AP201: 1 | AQ201: 1 | AR201: 1 | AS201: 1 | AT201: 1
B202: 5003 | C202: 221 Clinical Data Management | D202: TBD | E202: 04. AD / Staff Scientist | F202: Associate Director, Clinical Programming | G202: =_xlfn.XLOOKUP(B202,'WFP Details - 2026'!A:A,'WFP Details - 2026'!Z:Z) -> #N/A | H202: 46461 | I202: 3 | J202: 2027 | K202: 0 | L202: 0 | M202: 0 | N202: 0 | O202: 0 | P202: 0 | Q202: 0 | R202: 0 | S202: 0 | T202: 0 | U202: 0 | V202: 0 | W202: 0 | X202: 0 | Y202: 1 | Z202: 1 | AA202: 1 | AB202: 1 | AC202: 1 | AD202: 1 | AE202: 1 | AF202: 1 | AG202: 1 | AH202: 1 | AI202: 1 | AJ202: 1 | AK202: 1 | AL202: 1 | AM202: 1 | AN202: 1 | AO202: 1 | AP202: 1 | AQ202: 1 | AR202: 1 | AS202: 1 | AT202: 1
B203: 5027 | C203: 221 Clinical Data Management | D203: TBD | E203: 03. Sr. Manager / Sr. Scientist | F203: Senior Manager, Data Management | G203: =_xlfn.XLOOKUP(B203,'WFP Details - 2026'!A:A,'WFP Details - 2026'!Z:Z) -> #N/A | H203: 46461 | I203: 3 | J203: 2027 | K203: 0 | L203: 0 | M203: 0 | N203: 0 | O203: 0 | P203: 0 | Q203: 0 | R203: 0 | S203: 0 | T203: 0 | U203: 0 | V203: 0 | W203: 0 | X203: 0 | Y203: 1 | Z203: 1 | AA203: 1 | AB203: 1 | AC203: 1 | AD203: 1 | AE203: 1 | AF203: 1 | AG203: 1 | AH203: 1 | AI203: 1 | AJ203: 1 | AK203: 1 | AL203: 1 | AM203: 1 | AN203: 1 | AO203: 1 | AP203: 1 | AQ203: 1 | AR203: 1 | AS203: 1 | AT203: 1
B204: 5030 | C204: 221 Clinical Data Management | D204: TBD | E204: 03. Sr. Manager / Sr. Scientist | F204: Senior Manager, Data Management | G204: =_xlfn.XLOOKUP(B204,'WFP Details - 2026'!A:A,'WFP Details - 2026'!Z:Z) -> #N/A | H204: 46461 | I204: 3 | J204: 2027 | K204: 0 | L204: 0 | M204: 0 | N204: 0 | O204: 0 | P204: 0 | Q204: 0 | R204: 0 | S204: 0 | T204: 0 | U204: 0 | V204: 0 | W204: 0 | X204: 0 | Y204: 1 | Z204: 1 | AA204: 1 | AB204: 1 | AC204: 1 | AD204: 1 | AE204: 1 | AF204: 1 | AG204: 1 | AH204: 1 | AI204: 1 | AJ204: 1 | AK204: 1 | AL204: 1 | AM204: 1 | AN204: 1 | AO204: 1 | AP204: 1 | AQ204: 1 | AR204: 1 | AS204: 1 | AT204: 1
B205: 5034 | C205: 221 Clinical Data Management | D205: TBD | E205: 04. AD / Staff Scientist | F205: Associate Director, Clinical Programming | G205: =_xlfn.XLOOKUP(B205,'WFP Details - 2026'!A:A,'WFP Details - 2026'!Z:Z) -> #N/A | H205: 46461 | I205: 3 | J205: 2027 | K205: 0 | L205: 0 | M205: 0 | N205: 0 | O205: 0 | P205: 0 | Q205: 0 | R205: 0 | S205: 0 | T205: 0 | U205: 0 | V205: 0 | W205: 0 | X205: 0 | Y205: 1 | Z205: 1 | AA205: 1 | AB205: 1 | AC205: 1 | AD205: 1 | AE205: 1 | AF205: 1 | AG205: 1 | AH205: 1 | AI205: 1 | AJ205: 1 | AK205: 1 | AL205: 1 | AM205: 1 | AN205: 1 | AO205: 1 | AP205: 1 | AQ205: 1 | AR205: 1 | AS205: 1 | AT205: 1
B206: 1311 | C206: 230 Pharmacovigilance | D206: Krisztina Debreczeni | E206: 08. VP | F206: Head PV | G206: =_xlfn.XLOOKUP(B206,'WFP Details - 2026'!A:A,'WFP Details - 2026'!Z:Z) -> x | H206: 45684 | I206: 1 | J206: 2025 | K206: 1 | L206: 1 | M206: 1 | N206: 1 | O206: 1 | P206: 1 | Q206: 1 | R206: 1 | S206: 1 | T206: 1 | U206: 1 | V206: 1 | W206: 1 | X206: 1 | Y206: 1 | Z206: 1 | AA206: 1 | AB206: 1 | AC206: 1 | AD206: 1 | AE206: 1 | AF206: 1 | AG206: 1 | AH206: 1 | AI206: 1 | AJ206: 1 | AK206: 1 | AL206: 1 | AM206: 1 | AN206: 1 | AO206: 1 | AP206: 1 | AQ206: 1 | AR206: 1 | AS206: 1 | AT206: 1
B207: 1235 | C207: 230 Pharmacovigilance | D207: Brian Burns | E207: 06. Sr. Director | F207: Senior Director, Pharmacovigilance Functional Excellence and Inspection Readiness | G207: =_xlfn.XLOOKUP(B207,'WFP Details - 2026'!A:A,'WFP Details - 2026'!Z:Z) -> x | H207: 45810 | I207: 6 | J207: 2025 | K207: 1 | L207: 1 | M207: 1 | N207: 1 | O207: 1 | P207: 1 | Q207: 1 | R207: 1 | S207: 1 | T207: 1 | U207: 1 | V207: 1 | W207: 1 | X207: 1 | Y207: 1 | Z207: 1 | AA207: 1 | AB207: 1 | AC207: 1 | AD207: 1 | AE207: 1 | AF207: 1 | AG207: 1 | AH207: 1 | AI207: 1 | AJ207: 1 | AK207: 1 | AL207: 1 | AM207: 1 | AN207: 1 | AO207: 1 | AP207: 1 | AQ207: 1 | AR207: 1 | AS207: 1 | AT207: 1
... B518: 5195 | C518: 970 IT | D518: TBD | E518: 02. Manager / Scientist | F518: IT Business Analyst, Commercial | G518: =_xlfn.XLOOKUP(B518,'WFP Details - 2026'!A:A,'WFP Details - 2026'!Z:Z) -> #N/A | H518: 46736 | I518: 12 | J518: 2027 | K518: 0 | L518: 0 | M518: 0 | N518: 0 | O518: 0 | P518: 0 | Q518: 0 | R518: 0 | S518: 0 | T518: 0 | U518: 0 | V518: 0 | W518: 0 | X518: 0 | Y518: 0 | Z518: 0 | AA518: 0 | AB518: 0 | AC518: 0 | AD518: 0 | AE518: 0 | AF518: 0 | AG518: 0 | AH518: 1 | AI518: 1 | AJ518: 1 | AK518: 1 | AL518: 1 | AM518: 1 | AN518: 1 | AO518: 1 | AP518: 1 | AQ518: 1 | AR518: 1 | AS518: 1 | AT518: 1

Sheet Tradeoffs
A1: Temp Job ID | B1: Department | C1: Level | D1: Title | E1: Dif | F1: Temp Job ID | G1: Department | H1: Level | I1: Title | J1: Trade-off Status
A2: 5395 | B2: 205 Executive Development | C2: 01 - Below Manager | D2: Senior Executive Assistant | E2: 0 | F2: 1175 | G2: 105 Biochemistry | H2: 01 - Below Manager | I2: RA, Biology
A3: 5407 | B3: 210 Clinical Operations | C3: 06 - Sr. Director | D3: Sr. Director, Clinical Trial Optimization & Strategic Partnerships | E3: 0 | F3: 1394 | G3: 605 Marketing | H3: 06 - Sr. Director | I3: Sr Dir, Commercial Ops (all programs)
A4: 5408 | B4: 210 Clinical Operations | C4: 06 - Sr. Director | D4: Sr. Director, Site Management & Monitoring | E4: 0
A5: 5403 | B5: 210 Clinical Operations | C5: 04 - Assoc. Director | D5: Medical Trial Liaison (CTL) | E5: 0 | F5: 5052 | G5: 210 Clinical Operations | H5: 04 - Assoc. Director | I5: Clinical Operations
A6: 5405 | B6: 210 Clinical Operations | C6: 04 - Assoc. Director | D6: Medical Trial Liaison (CTL) | E6: 0 | F6: 5150 | G6: 235 Regulatory | H6: 04 - Assoc. Director | I6: Assoc. Director, Regulatory Strategy (TLA/ATA)
A7: 5404 | B7: 210 Clinical Operations | C7: 04 - Assoc. Director | D7: Medical Trial Liaison (CTL) | E7: 0
A8: 5411 | B8: 505 Medical Affairs | C8: 07 - Exec. Director | D8: ED, National Director of Field Medical | E8: 0
A9: 5396 | B9: 505 Medical Affairs | C9: 06 - Sr. Director | D9: Medical Science Liaison (MSL) | E9: 0
A10: 5397 | B10: 505 Medical Affairs | C10: 06 - Sr. Director | D10: Medical Science Liaison (MSL) | E10: -1 | F10: 5123 | G10: 230 Pharmacovigilance | H10: 05 - Director | I10: Director, PV Scientist (non-MD)
A11: 5398 | B11: 505 Medical Affairs | C11: 05 - Director | D11: Director, Medical Affairs – Digital Innovation & AI (Prolaio) | E11: -1 | F11: 5036 | G11: 215 Clinical Development | H11: 04 - Assoc. Director | I11: Clinical Scientist
A12: 5399 | B12: 505 Medical Affairs | C12: 05 - Director | D12: Medical Science Liaison (MSL) | E12: 0 | F12: 5388 | G12: 205 Executive Development | H12: 05 - Director | I12: Director, Chief of Staff
A13: 5400 | B13: 505 Medical Affairs | C13: 05 - Director | D13: Medical Science Liaison (MSL) | E13: -2 | F13: 1302 | G13: 208 Early Development | H13: 03 - Sr. Manager | I13: Sr. Scientist, Clinical Pharmacology
A14: 5401 | B14: 505 Medical Affairs | C14: 04 - Assoc. Director | D14: Medical Science Liaison (MSL) | E14: -1 | F14: 5051 | G14: 210 Clinical Operations | H14: 03 - Sr. Manager | I14: Clinical Trial Lead
A15: 5402 | B15: 505 Medical Affairs | C15: 04 - Assoc. Director | D15: Medical Science Liaison (MSL) | E15: -2 | F15: 1071 | G15: 960 Facilities | H15: 02 - Manager | I15: EHS Manager
A16: 5215 | B16: 910 People and Culture | C16: 06 - Sr. Director | D16: Senior Director, People & Culture Business Partner | E16: 0
E17: =SUM(E2:E16) -> -7
A20: 5410 | B20: 210 Clinical Operations | C20: 06 - Sr. Director | D20: Sr. Director, Vendor Relationship & Management | E20: -1 | G20: 210 Clinical Operations | H20: 05 - Director | I20: Director, Clinical Operations Program Lead, Early Dev | J20: Confirmed push to 2027
G21: 105 Translational Sciences | H21: 05 - Director | I21: Staff Scientist, Director Non-Clinical | J21: Confirmed push to 2027

Sheet By Function
A3: Count of Temp Job ID | B3: Column Labels
A4: Function / Dept | B4: CW | C4: CW PT | D4: CW to FTE | E4: FTE | F4: Postdoc | G4: Grand Total
A5: Communications | E5: 4 | G5: 4
A6: 930 Communications | E6: 4 | G6: 4
A7: Development | B7: 38 | C7: 6 | D7: 3 | E7: 85 | G7: 132
A8: 210 Clinical Operations | B8: 20 | E8: 29 | G8: 49
A9: 215 Clinical Development | B9: 2 | D9: 1 | E9: 7 | G9: 10
A10: 220 Clinical Data Science | B10: 8 | D10: 2 | E10: 13 | G10: 23
A11: 235 Regulatory | C11: 6 | E11: 11 | G11: 17
A12: 230 Pharmacovigilance | E12: 5 | G12: 5
A13: 505 Medical Affairs | B13: 2 | E13: 8 | G13: 10
A14: 208 Early Development | E14: 3 | G14: 3
A15: 205 Executive Development | E15: 3 | G15: 3
A16: 221 Clinical Data Management | B16: 6 | E16: 6 | G16: 12
A17: Executive | E17: 8 | G17: 8
A18: 216 Program Management | E18: 3 | G18: 3
A19: 901 Executive G&A | E19: 2 | G19: 2
A20: 240 Portfolio Management | E20: 3 | G20: 3
A21: Legal | E21: 12 | G21: 12
A22: 920 Legal | E22: 12 | G22: 12
A23: Office of CFO | B23: 4 | E23: 34 | G23: 38
A24: 960 Facilities | B24: 2 | E24: 6 | G24: 8
A25: 970 IT | B25: 2 | E25: 10 | G25: 12
A26: 915 Accounting | E26: 11 | G26: 11
A27: 916 Finance | E27: 7 | G27: 7
A28: Office of CSO | E28: 20 | G28: 20
A29: 925 Business Development | E29: 5 | G29: 5
A30: 605 Marketing | E30: 5 | G30: 5
A31: 615 Commercial Analytics | E31: 2 | G31: 2
A32: 917 Corporate Strategy | E32: 5 | G32: 5
A33: 240 Portfolio Management | E33: 3 | G33: 3
A34: P&C | B34: 5 | E34: 14 | G34: 19
A35: 910 People and Culture | B35: 5 | E35: 14 | G35: 19
A36: Quality | B36: 8 | C36: 1 | E36: 16 | G36: 25
A37: 305 Quality | B37: 8 | C37: 1 | E37: 16 | G37: 25
A38: Research - Discovery | E38: 9 | G38: 9
A39: 110 Discovery | E39: 9 | G39: 9
A40: Research - Translational | B40: 3 | E40: 21 | F40: 3 | G40: 27
A41: 105 Translational Sciences | B41: 3 | E41: 16 | F41: 3 | G41: 22
A42: 115 In Vivo Pharmacology | E42: 5 | G42: 5
A43: Tech Ops | B43: 2 | E43: 31 | G43: 33
A44: 405 Supply Chain | B44: 2 | E44: 1 | G44: 3
A45: 410 Manufacturing | E45: 30 | G45: 30
A46: Grand Total | B46: 60 | C46: 7 | D46: 3 | E46: 254 | F46: 3 | G46: 327
A58: Employee Type | B58: FTE
A60: Count of Temp Job ID | B60: Column Labels
A61: Function / Dept | B61: Chicago | C61: PNJ | D61: SSF | E61: SSF or PNJ | F61: US Remote | G61: Grand Total
A62: Communications | B62: 1 | C62: 1 | D62: 2 | G62: 4
A63: Development | C63: 42 | D63: 33 | E63: 4 | F63: 6 | G63: 85
A64: Executive | B64: 1 | C64: 4 | D64: 3 | G64: 8
A65: Legal | B65: 1 | C65: 3 | D65: 8 | G65: 12
A66: Office of CFO | B66: 2 | C66: 13 | D66: 19 | G66: 34
A67: Office of CSO | B67: 10 | D67: 10 | G67: 20
A68: P&C | B68: 3 | C68: 1 | D68: 10 | G68: 14
A69: Quality | C69: 2 | D69: 14 | G69: 16
A70: Research - Discovery | D70: 9 | G70: 9
A71: Research - Translational | C71: 1 | D71: 20 | G71: 21
A72: Tech Ops | C72: 16 | D72: 15 | G72: 31
A73: Grand Total | B73: 18 | C73: 83 | D73: 143 | E73: 4 | F73: 6 | G73: 254
A78: Employee Type | B78: FTE
A79: Recruiting Status | B79: (All)
A81: Count of Temp Job ID | B81: Column Labels
A82: Level | B82: 09 - C-Suite | C82: 08 - VP | D82: 07 - Exec. Director | E82: 06 - Sr. Director | F82: 05 - Director | G82: 04 - Assoc. Director | H82: 03 - Sr. Manager | I82: 02 - Manager | J82: 01 - Below Manager | K82: Grand Total
A83: Communications | B83: 1 | D83: 2 | E83: 1 | K83: 4
A84: Development | B84: 1 | C84: 11 | D84: 12 | E84: 16 | F84: 14 | G84: 15 | H84: 11 | I84: 1 | J84: 4 | K84: 85
A85: Executive | B85: 1 | C85: 3 | E85: 1 | F85: 2 | J85: 1 | K85: 8
A86: Legal | B86: 1 | C86: 3 | E86: 3 | F86: 3 | H86: 2 | K86: 12
A87: Office of CFO | B87: 1 | C87: 4 | D87: 1 | E87: 4 | F87: 5 | G87: 1 | H87: 10 | I87: 6 | J87: 2 | K87: 34
A88: Office of CSO | B88: 1 | C88: 4 | D88: 4 | E88: 5 | F88: 3 | G88: 1 | H88: 1 | I88: 1 | K88: 20
A89: P&C | B89: 1 | C89: 1 | D89: 3 | E89: 2 | F89: 1 | H89: 4 | J89: 2 | K89: 14
A90: Quality | B90: 1 | C90: 1 | E90: 5 | F90: 5 | G90: 1 | H90: 3 | K90: 16
A91: Research - Discovery | C91: 1 | F91: 2 | G91: 2 | H91: 1 | I91: 2 | J91: 1 | K91: 9
A92: Research - Translational | C92: 2 | G92: 4 | H92: 5 | I92: 6 | J92: 4 | K92: 21
A93: Tech Ops | B93: 1 | C93: 4 | E93: 9 | F93: 7 | G93: 5 | H93: 5 | K93: 31
A94: Grand Total | B94: 9 | C94: 34 | D94: 22 | E94: 46 | F94: 42 | G94: 29 | H94: 42 | I94: 16 | J94: 14 | K94: 254
A98: Employee Type | B98: FTE
A100: Count of Temp Job ID | B100: Column Labels
B101: 2026 Q1 | G101: 2026 Q1 Total | H101: Grand Total
A102: Function / Dept | B102: Hired | C102: Open | D102: (blank) | E102: Offer | F102: Agency | L102: Function / Dept | M102: Hired | N102: Open | O102: Offer | P102: To be opened | Q102: Active Q1 Roles | R102: Not Yet Started | S102: Remaining Q1 Unfilled | T102: Total Q1 Target | U102: Hired % of Target
A103: Communications | C103: 1 | G103: 1 | H103: 1 | L103: Quality | M103: 1 | Q103: =SUM(N103:P103) -> 0 | S103: =Q103+R103 -> 0 | T103: =M103+S103 -> 1 | U103: =M103/T103 -> 1
A104: Development | B104: 9 | C104: 8 | D104: 6 | E104: 1 | G104: 24 | H104: 24 | L104: Tech Ops | M104: 2 | N104: 5 | Q104: =SUM(N104:P104) -> 5 | S104: =Q104+R104 -> 5 | T104: =M104+S104 -> 7 | U104: =M104/T104 -> 0.28571429
A105: Executive | B105: 1 | G105: 1 | H105: 1 | L105: Development | M105: 5 | N105: 11 | O105: 4 | Q105: =SUM(N105:P105) -> 15 | R105: 7 | S105: =Q105+R105 -> 22 | T105: =M105+S105 -> 27 | U105: =M105/T105 -> 0.18518519
A106: Legal | B106: 2 | C106: 1 | F106: 1 | G106: 4 | H106: 4 | L106: Research - Discovery | Q106: =SUM(N106:P106) -> 0 | R106: 2 | S106: =Q106+R106 -> 2 | T106: =M106+S106 -> 2 | U106: =M106/T106 -> 0
A107: Office of CFO | B107: 4 | D107: 4 | F107: 1 | G107: 9 | H107: 9 | L107: Research - Translational | M107: 3 | N107: 2 | Q107: =SUM(N107:P107) -> 2 | S107: =Q107+R107 -> 2 | T107: =M107+S107 -> 5 | U107: =M107/T107 -> 0.6
A108: Office of CSO | B108: 3 | G108: 3 | H108: 3 | L108: Office of CSO | M108: 5 | N108: 1 | Q108: =SUM(N108:P108) -> 1 | R108: 1 | S108: =Q108+R108 -> 2 | T108: =M108+S108 -> 7 | U108: =M108/T108 -> 0.71428571
A109: P&C | B109: 2 | D109: 1 | G109: 3 | H109: 3 | L109: P&C | M109: 1 | N109: 1 | O109: 1 | Q109: =SUM(N109:P109) -> 2 | S109: =Q109+R109 -> 2 | T109: =M109+S109 -> 3 | U109: =M109/T109 -> 0.33333333
A110: Quality | B110: 1 | G110: 1 | H110: 1 | L110: Office of CFO | M110: 4 | N110: 1 | Q110: =SUM(N110:P110) -> 1 | R110: 4 | S110: =Q110+R110 -> 5 | T110: =M110+S110 -> 9 | U110: =M110/T110 -> 0.44444444
A111: Research - Translational | B111: 4 | G111: 4 | H111: 4 | L111: Legal | M111: 2 | N111: 2 | Q111: =SUM(N111:P111) -> 2 | R111: 1 | S111: =Q111+R111 -> 3 | T111: =M111+S111 -> 5 | U111: =M111/T111 -> 0.4
A112: Tech Ops | B112: 3 | C112: 4 | G112: 7 | H112: 7 | L112: Communications | P112: 1 | Q112: =SUM(N112:P112) -> 1 | S112: =Q112+R112 -> 1 | T112: =M112+S112 -> 1 | U112: =M112/T112 -> 0
A113: Grand Total | B113: 29 | C113: 14 | D113: 11 | E113: 1 | F113: 2 | G113: 57 | H113: 57 | L113: Grand Total | M113: =SUM(M103:M112) -> 23 | N113: =SUM(N103:N112) -> 23 | O113: =SUM(O103:O112) -> 5 | P113: =SUM(P103:P112) -> 1 | Q113: =SUM(Q103:Q112) -> 29 | R113: =SUM(R103:R112) -> 15 | S113: =SUM(S103:S112) -> 44 | T113: =SUM(T103:T112) -> 67 | U113: =M113/T113 -> 0.34328358
A118: Employee Type | B118: FTE
A119: Recruiting Status | B119: (Multiple Items)
A121: Count of Temp Job ID | B121: Column Labels
A122: Function / Dept | B122: 2026 Q1 | C122: 2026 Q2 | D122: 2026 Q3 | E122: 2026 Q4 | F122: Grand Total | L122: Function / Dept | M122: 2026 Starts | N122: 2026 Q1 | O122: 2026 Q2 | P122: 2026 Q3 | Q122: 2026 Q4 | R122: Remaining 2026 Unfilled | S122: Total 2026 Target | T122: Hired % of Target
A123: Communications | B123: 1 | C123: 1 | F123: 2 | L123: Communications | N123: 1 | O123: 1 | R123: =SUM(N123:Q123) -> 2 | S123: =SUM(M123:Q123) -> 2 | T123: =M123/S123 -> 0
A124: Development | B124: 15 | C124: 10 | D124: 9 | E124: 2 | F124: 36 | L124: Development | M124: 11 | N124: 17 | O124: 7 | P124: 8 | Q124: 3 | R124: =SUM(N124:Q124) -> 35 | S124: =SUM(M124:Q124) -> 46 | T124: =M124/S124 -> 0.23913043
A125: Legal | B125: 2 | C125: 1 | D125: 3 | F125: 6 | L125: Legal | M125: 2 | N125: 2 | O125: 1 | P125: 3 | R125: 6 | S125: =SUM(M125:Q125) -> 8 | T125: =M125/S125 -> 0.25
A126: Office of CFO | B126: 5 | C126: 2 | D126: 1 | E126: 1 | F126: 9 | L126: Office of CFO | M126: 4 | N126: 5 | O126: 2 | P126: 1 | Q126: 1 | R126: =SUM(N126:Q126) -> 9 | S126: =SUM(M126:Q126) -> 13 | T126: =M126/S126 -> 0.30769231
A127: Office of CSO | C127: 9 | D127: 1 | F127: 10 | L127: Office of CSO | M127: 4 | N127: 3 | O127: 4 | P127: 3 | Q127: 1 | R127: =SUM(N127:Q127) -> 11 | S127: =SUM(M127:Q127) -> 15 | T127: =M127/S127 -> 0.26666667
A128: P&C | B128: 1 | F128: 1 | L128: P&C | M128: 2 | N128: 1 | R128: =SUM(N128:Q128) -> 1 | S128: =SUM(M128:Q128) -> 3 | T128: =M128/S128 -> 0.66666667
...

Sheet By Grade
A2: Projected Year-end by Grade and Function
A5: Employee Type | B5: FTE
A6: Recruiting Status | B6: (All)
A8: Count of Temp Job ID | B8: Column Labels
A9: Level | B9: CFO | C9: Comms | D9: CSO | E9: Dev | F9: Exec | G9: Legal | H9: P&C | I9: Quality | J9: Research - Discovery | K9: Research - Translational | L9: Tech Ops | M9: Grand Total | O9: Level | P9: Exec | Q9: CFO | R9: CSO | S9: Legal | T9: Comms | U9: P&C | V9: Dev | W9: Quality | X9: Res | Y9: Tech Ops | Z9: Total | AA9: %
A10: 09 - C-Suite | B10: 1 | C10: 1 | D10: 1 | E10: 1 | F10: 1 | G10: 1 | H10: 1 | I10: 1 | L10: 1 | M10: 9 | O10: 09 - C-Suite | P10: 1 | Q10: 1 | R10: 1 | S10: 1 | T10: 1 | U10: 1 | V10: 1 | W10: 1 | Y10: 1 | Z10: =SUM(P10:Y10) -> 9 | AA10: =Z10/Z19 -> 0.035294118
A11: 08 - VP | B11: 4 | D11: 4 | E11: 11 | F11: 3 | G11: 3 | H11: 1 | I11: 1 | J11: 1 | K11: 2 | L11: 4 | M11: 34 | O11: 08 - VP | P11: 3 | Q11: 4 | R11: 4 | S11: 3 | U11: 1 | V11: 11 | W11: 1 | X11: 3 | Y11: 4 | Z11: =SUM(P11:Y11) -> 34 | AA11: =Z11/Z19 -> 0.13333333
A12: 07 - Exec. Director | B12: 1 | C12: 2 | D12: 4 | E12: 12 | H12: 3 | M12: 22 | O12: 07 - Exec. Director | Q12: 1 | R12: 4 | T12: 2 | U12: 3 | V12: 12 | Z12: =SUM(P12:Y12) -> 22 | AA12: =Z12/Z19 -> 0.08627451
A13: 06 - Sr. Director | B13: 4 | C13: 1 | D13: 5 | E13: 16 | F13: 1 | G13: 3 | H13: 2 | I13: 5 | L13: 9 | M13: 46 | O13: 06 - Sr. Director | P13: 1 | Q13: 4 | R13: 5 | S13: 3 | T13: 1 | U13: 2 | V13: 15 | W13: 5 | Y13: 9 | Z13: =SUM(P13:Y13) -> 45 | AA13: =Z13/Z19 -> 0.17647059
A14: 05 - Director | B14: 5 | D14: 3 | E14: 14 | F14: 2 | G14: 3 | H14: 1 | I14: 5 | J14: 2 | L14: 7 | M14: 42 | O14: 05 - Director | P14: 2 | Q14: 5 | R14: 3 | S14: 3 | U14: 1 | V14: 15 | W14: 5 | X14: 3 | Y14: 7 | Z14: =SUM(P14:Y14) -> 44 | AA14: =Z14/Z19 -> 0.17254902
A15: 04 - Assoc. Director | B15: 1 | D15: 1 | E15: 15 | I15: 1 | J15: 2 | K15: 4 | L15: 5 | M15: 29 | O15: 04 - Assoc. Director | Q15: 1 | R15: 1 | V15: 14 | W15: 1 | X15: 6 | Y15: 5 | Z15: =SUM(P15:Y15) -> 28 | AA15: =Z15/Z19 -> 0.10980392
A16: 03 - Sr. Manager | B16: 10 | D16: 1 | E16: 11 | G16: 2 | H16: 4 | I16: 3 | J16: 1 | K16: 5 | L16: 5 | M16: 42 | O16: 03 - Sr. Manager | Q16: 10 | R16: 1 | S16: 2 | U16: 4 | V16: 12 | W16: 3 | X16: 6 | Y16: 5 | Z16: =SUM(P16:Y16) -> 43 | AA16: =Z16/Z19 -> 0.16862745
A17: 02 - Manager | B17: 6 | D17: 1 | E17: 1 | J17: 2 | K17: 6 | M17: 16 | O17: 02 - Manager | Q17: 6 | R17: 1 | V17: 1 | X17: 8 | Z17: =SUM(P17:Y17) -> 16 | AA17: =Z17/Z19 -> 0.062745098
A18: 01 - Below Manager | B18: 2 | E18: 4 | F18: 1 | H18: 2 | J18: 1 | K18: 4 | M18: 14 | O18: 01 - Below Manager | P18: 1 | Q18: 2 | U18: 2 | V18: 4 | X18: 5 | Z18: =SUM(P18:Y18) -> 14 | AA18: =Z18/Z19 -> 0.054901961
A19: Grand Total | B19: 34 | C19: 4 | D19: 20 | E19: 85 | F19: 8 | G19: 12 | H19: 14 | I19: 16 | J19: 9 | K19: 21 | L19: 31 | M19: 254 | O19: Total | P19: =SUM(P10:P18) -> 8 | Q19: =SUM(Q10:Q18) -> 34 | R19: =SUM(R10:R18) -> 20 | S19: =SUM(S10:S18) -> 12 | T19: =SUM(T10:T18) -> 4 | U19: =SUM(U10:U18) -> 14 | V19: =SUM(V10:V18) -> 85 | W19: =SUM(W10:W18) -> 16 | ... AA19: =SUM(AA10:AA18) -> 1
A23: New Requests for 2026 WFP
A26: Employee Type | B26: FTE
A27: Recruiting Status | B27: (Multiple Items)
A29: Count of Temp Job ID | B29: Column Labels
A30: Level | B30: CFO | C30: Comms | D30: CSO | E30: Dev | F30: Legal | G30: P&C | H30: Quality | I30: Research - Discovery | J30: Research - Translational | K30: Tech Ops | L30: Grand Total | O30: Level | P30: Exec | Q30: CFO | R30: CSO | S30: Legal | T30: Comms | U30: P&C | V30: Dev | W30: Quality | X30: Res | Y30: Tech Ops | Z30: Total | AA30: %
A31: 09 - C-Suite | F31: 1 | L31: 1 | O31: 09 - C-Suite | S31: 1 | Z31: =SUM(P31:Y31) -> 1 | AA31: =Z31/Z40 -> 0.011494253
A32: 08 - VP | B32: 1 | E32: 7 | K32: 1 | L32: 9 | O32: 08 - VP | Q32: 1 | V32: 7 | Y32: 1 | Z32: =SUM(P32:Y32) -> 9 | AA32: =Z32/Z40 -> 0.10344828
A33: 07 - Exec. Director | C33: 1 | D33: 4 | E33: 6 | L33: 11 | O33: 07 - Exec. Director | R33: 4 | T33: 1 | V33: 6 | Z33: =SUM(P33:Y33) -> 11 | AA33: =Z33/Z40 -> 0.12643678
A34: 06 - Sr. Director | B34: 1 | C34: 1 | D34: 1 | E34: 4 | F34: 2 | G34: 1 | H34: 1 | K34: 2 | L34: 13 | O34: 06 - Sr. Director | Q34: 1 | R34: 1 | S34: 2 | T34: 1 | U34: 1 | V34: 3 | W34: 1 | Y34: 2 | Z34: =SUM(P34:Y34) -> 12 | AA34: =Z34/Z40 -> 0.13793103
A35: 05 - Director | D35: 3 | E35: 4 | F35: 2 | H35: 2 | K35: 6 | L35: 17 | O35: 05 - Director | R35: 3 | S35: 2 | V35: 5 | W35: 2 | X35: 1 | Y35: 6 | Z35: =SUM(P35:Y35) -> 19 | AA35: =Z35/Z40 -> 0.2183908
A36: 04 - Assoc. Director | D36: 1 | E36: 8 | I36: 1 | J36: 1 | K36: 3 | L36: 14 | O36: 04 - Assoc. Director | R36: 1 | V36: 7 | X36: 2 | Y36: 3 | Z36: =SUM(P36:Y36) -> 13 | AA36: =Z36/Z40 -> 0.14942529
A37: 03 - Sr. Manager | B37: 3 | E37: 5 | F37: 1 | H37: 1 | K37: 2 | L37: 12 | O37: 03 - Sr. Manager | Q37: 3 | S37: 1 | V37: 6 | W37: 1 | Y37: 2 | Z37: =SUM(P37:Y37) -> 13 | AA37: =Z37/Z40 -> 0.14942529
A38: 02 - Manager | B38: 3 | D38: 1 | E38: 1 | L38: 5 | O38: 02 - Manager | Q38: 3 | R38: 1 | V38: 1 | Z38: =SUM(P38:Y38) -> 5 | AA38: =Z38/Z40 -> 0.057471264
A39: 01 - Below Manager | B39: 1 | E39: 1 | I39: 1 | J39: 1 | L39: 4 | O39: 01 - Below Manager | Q39: 1 | V39: 1 | X39: 2 | Z39: =SUM(P39:Y39) -> 4 | AA39: =Z39/Z40 -> 0.045977011
A40: Grand Total | B40: 9 | C40: 2 | D40: 10 | E40: 36 | F40: 6 | G40: 1 | H40: 4 | I40: 2 | J40: 2 | K40: 14 | L40: 86 | O40: Total | P40: =SUM(P31:P39) -> 0 | Q40: =SUM(Q31:Q39) -> 9 | R40: =SUM(R31:R39) -> 10 | S40: =SUM(S31:S39) -> 6 | T40: =SUM(T31:T39) -> 2 | U40: =SUM(U31:U39) -> 1 | V40: =SUM(V31:V39) -> 36 | W40: =SUM(W31:W39) -> 4 | ... AA40: =SUM(AA31:AA39) -> 1

Sheet By Location
A1: Hiring by Quarter
A3: Employee Type | B3: FTE
A4: Recruiting Status | B4: (Multiple Items)
A6: Count of Temp Job ID | B6: Column Labels | J6: Location | K6: Q1 Breakdown | M6: Remaining Unfilled | Q6: Remaining 2026 Unfilled | R6: Total 2026 Target | S6: Hired % of Target
A7: Location | B7: 2026 Q1 | C7: 2026 Q2 | D7: 2026 Q3 | E7: 2026 Q4 | F7: Grand Total | K7: Hired | L7: Unfilled | M7: 2026 Q1 | N7: 2026 Q2 | O7: 2026 Q3 | P7: 2026 Q4
A8: Chicago | B8: 1 | C8: 8 | F8: 9 | J8: Chicago | K8: 5 | L8: 1 | M8: 1 | N8: 4 | Q8: =SUM(M8:P8) -> 5 | R8: =Q8+K8 -> 10 | S8: =L8/R8 -> 0.1
A9: PNJ | B9: 15 | C9: 6 | D9: 13 | E9: 2 | F9: 36 | J9: PNJ | K9: 4 | L9: 20 | M9: 20 | N9: 4 | O9: 13 | P9: 3 | Q9: =SUM(M9:P9) -> 40 | R9: =Q9+K9 -> 44 | S9: =L9/R9 -> 0.45454545
A10: SSF | B10: 11 | C10: 16 | D10: 7 | E10: 3 | F10: 37 | J10: SSF | K10: 13 | L10: 21 | M10: 21 | N10: 7 | O10: 9 | P10: 4 | Q10: =SUM(M10:P10) -> 41 | R10: =Q10+K10 -> 54 | S10: =L10/R10 -> 0.38888889
A11: SSF or PNJ | B11: 1 | C11: 2 | F11: 3 | J11: SSF or PNJ | K11: 0 | L11: 2 | M11: 2 | N11: 3 | P11: 1 | Q11: =SUM(M11:P11) -> 6 | R11: =Q11+K11 -> 6 | S11: =L11/R11 -> 0.33333333
A12: US Remote | D12: 1 | F12: 1 | J12: US Remote | K12: 1 | O12: 1 | Q12: =SUM(M12:P12) -> 1 | R12: =Q12+K12 -> 2 | S12: =L12/R12 -> 0
A13: Grand Total | B13: 28 | C13: 32 | D13: 21 | E13: 5 | F13: 86 | J13: Grand Total | K13: =SUM(K8:K12) -> 23 | L13: =SUM(L8:L12) -> 44 | M13: =SUM(M8:M12) -> 44 | N13: =SUM(N8:N12) -> 18 | O13: =SUM(O8:O12) -> 23 | P13: =SUM(P8:P12) -> 8 | Q13: =SUM(Q8:Q12) -> 93 | R13: =SUM(R8:R12) -> 116 | S13: =L13/R13 -> 0.37931034
A16: Hiring by Recruiting Status
A18: Employee Type | B18: FTE
A20: Count of Temp Job ID | B20: Column Labels
B21: 2026 Q1 | G21: 2026 Q1 Total | H21: Grand Total | K21: Location | L21: 2026 Q1 Hired | M21: Open | N21: Offer | O21: To be opened | P21: Active Q1 Roles | Q21: Not Yet Started | R21: Remaining Q1 Unfilled | S21: Total Q1 Target | T21: Hired % of Target
A22: Location | B22: Hired | C22: Open | D22: (blank) | E22: Offer | F22: Agency
A23: Chicago | B23: 5 | C23: 1 | G23: 6 | H23: 6 | K23: Chicago | L23: 5 | O23: 1 | P23: =SUM(M23:O23) -> 1 | R23: =P23+Q23 -> 1 | S23: =L23+R23 -> 6 | T23: =L23/S23 -> 0.83333333
A24: PNJ | B24: 9 | C24: 7 | D24: 6 | E24: 1 | F24: 1 | G24: 24 | H24: 24 | K24: PNJ | L24: 4 | M24: 14 | N24: 3 | P24: =SUM(M24:O24) -> 17 | Q24: 3 | R24: =P24+Q24 -> 20 | S24: =L24+R24 -> 24 | T24: =L24/S24 -> 0.16666667
A25: SSF | B25: 13 | C25: 5 | D25: 5 | F25: 1 | G25: 24 | H25: 24 | K25: SSF | L25: 13 | M25: 9 | N25: 1 | P25: =SUM(M25:O25) -> 10 | Q25: 11 | R25: =P25+Q25 -> 21 | S25: =L25+R25 -> 34 | T25: =L25/S25 -> 0.38235294
A26: SSF or PNJ | B26: 1 | C26: 1 | G26: 2 | H26: 2 | K26: SSF or PNJ | N26: 1 | P26: =SUM(M26:O26) -> 1 | Q26: 1 | R26: =P26+Q26 -> 2 | S26: =L26+R26 -> 2 | T26: =L26/S26 -> 0
A27: US Remote | B27: 1 | G27: 1 | H27: 1 | K27: US Remote | L27: 1 | P27: =SUM(M27:O27) -> 0 | R27: =P27+Q27 -> 0 | S27: =L27+R27 -> 1 | T27: =L27/S27 -> 1
A28: Grand Total | B28: 29 | C28: 14 | D28: 11 | E28: 1 | F28: 2 | G28: 57 | H28: 57 | K28: Grand Total | L28: =SUM(L23:L27) -> 23 | M28: =SUM(M23:M27) -> 23 | N28: =SUM(N23:N27) -> 5 | O28: =SUM(O23:O27) -> 1 | P28: =SUM(P23:P27) -> 29 | Q28: =SUM(Q23:Q27) -> 15 | R28: =SUM(R23:R27) -> 44 | S28: =SUM(S23:S27) -> 67 | T28: =L28/S28 -> 0.34328358
A31: Hiring by Location and Grade - Current | K31: Hiring by Location and Grade - Future
A33: Employee Type | B33: FTE | K33: Employee Type | L33: FTE
A34: Recruiting Status | B34: (Multiple Items) | K34: Recruiting Status | L34: (Multiple Items)
A36: Count of Temp Job ID | B36: Column Labels | K36: Count of Temp Job ID | L36: Column Labels
A37: Location | B37: Chicago | C37: PNJ | D37: SSF | E37: SSF or PNJ | F37: US Remote | G37: Grand Total | K37: Location | L37: Chicago | M37: PNJ | N37: SSF | O37: SSF or PNJ | P37: US Remote | Q37: Grand Total
A38: 01 - Below Manager | B38: 1 | C38: 1 | D38: 8 | G38: 10 | K38: 01 - Below Manager | N38: 4 | Q38: 4
A39: 02 - Manager | C39: 3 | D39: 8 | G39: 11 | K39: 02 - Manager | L39: 1 | M39: 2 | N39: 2 | Q39: 5
A40: 03 - Sr. Manager | B40: 2 | C40: 6 | D40: 22 | G40: 30 | K40: 03 - Sr. Manager | M40: 6 | N40: 5 | O40: 1 | Q40: 12
A41: 04 - Assoc. Director | C41: 4 | D41: 11 | G41: 15 | K41: 04 - Assoc. Director | M41: 3 | N41: 10 | O41: 1 | Q41: 14
A42: 05 - Director | B42: 2 | C42: 6 | D42: 15 | E42: 1 | F42: 1 | G42: 25 | K42: 05 - Director | L42: 3 | M42: 7 | N42: 6 | P42: 1 | Q42: 17
A43: 06 - Sr. Director | C43: 11 | D43: 20 | F43: 2 | G43: 33 | K43: 06 - Sr. Director | L43: 1 | M43: 5 | N43: 6 | O43: 1 | Q43: 13
A44: 07 - Exec. Director | C44: 4 | D44: 5 | F44: 2 | G44: 11 | K44: 07 - Exec. Director | L44: 4 | M44: 4 | N44: 3 | Q44: 11
A45: 08 - VP | B45: 3 | C45: 10 | D45: 13 | G45: 26 | K45: 08 - VP | M45: 8 | Q45: 8
A46: 09 - C-Suite | B46: 1 | C46: 3 | D46: 5 | G46: 9 | K46: Grand Total | L46: 9 | M46: 35 | N46: 36 | O46: 3 | P46: 1 | Q46: 84
A47: Grand Total | B47: 9 | C47: 48 | D47: 107 | E47: 1 | F47: 5 | G47: 170

Sheet Other Metrics
A3: Change Management
A6: Employee Type | B6: FTE
A7: Target Start Dt | B7: (Multiple Items)
A9: Count of Temp Job ID | B9: Column Labels | M9: Function / Dept | N9: Impact to Level | P9: Impact to Timing | R9: Incremental Requests | S9: Grand Total
A10: Function / Dept | B10: 1. In line with Budget | C10: 2. Downgrade | D10: 3. Upgrade | E10: Grand Total | N10: Downgrade | O10: Upgrade | P10: Delayed | Q10: Accelerated
A11: Communications | B11: 1 | D11: 1 | E11: 2 | M11: Communications | O11: 1 | P11: 1 | S11: 2
A12: Development | B12: 27 | C12: 3 | D12: 16 | E12: 46 | M12: Development | N12: 3 | O12: 12 | P12: 4 | Q12: 9 | R12: 15 | S12: 61
A13: Executive | B13: 1 | E13: 1 | M13: Legal | O13: 1 | P13: 2 | Q13: 2 | S13: 8
A14: Legal | B14: 7 | D14: 1 | E14: 8 | M14: Office of CFO | S14: 13
A15: Office of CFO | B15: 13 | E15: 13 | M15: Office of CSO | N15: 1 | O15: 1 | P15: 5 | Q15: 2 | S15: 15
A16: Office of CSO | B16: 9 | C16: 3 | D16: 3 | E16: 15 | M16: P&C | N16: 1 | Q16: 1 | S16: 3
A17: P&C | B17: 2 | C17: 1 | E17: 3 | M17: Quality | S17: 4
A18: Quality | B18: 5 | E18: 5 | M18: Research - Discovery | S18: 2
A19: Research - Discovery | B19: 2 | E19: 2 | M19: Research - Translational | O19: 1 | S19: 7
A20: Research - Translational | B20: 5 | D20: 1 | E20: 6 | M20: Tech Ops | N20: 1 | O20: 1 | P20: 1 | S20: 17
A21: Tech Ops | B21: 15 | C21: 1 | D21: 1 | E21: 17 | M21: Grand Total | N21: =SUM(N11:N20) -> 6 | O21: =SUM(O11:O20) -> 17 | P21: =SUM(P11:P20) -> 13 | Q21: =SUM(Q11:Q20) -> 14 | R21: =SUM(R11:R20) -> 15 | S21: =SUM(S11:S20) -> 132
A22: Grand Total | B22: 87 | C22: 8 | D22: 23 | E22: 118
A25: Employee Type | B25: FTE
A26: Target Start Dt | B26: (Multiple Items)
A28: Count of Temp Job ID | B28: Column Labels
A29: Function / Dept | B29: 1. In line with Budget | C29: 2. Delayed | D29: 3. Accelerated | E29: Grand Total
A30: Communications | B30: 1 | C30: 1 | E30: 2
A31: Development | B31: 32 | C31: 5 | D31: 9 | E31: 46
A32: Executive | B32: 1 | E32: 1
A33: Legal | B33: 4 | C33: 2 | D33: 2 | E33: 8
A34: Office of CFO | B34: 13 | E34: 13
A35: Office of CSO | B35: 3 | C35: 7 | D35: 5 | E35: 15
A36: P&C | B36: 2 | D36: 1 | E36: 3
A37: Quality | B37: 5 | E37: 5
A38: Research - Discovery | C38: 2 | E38: 2
A39: Research - Translational | B39: 5 | D39: 1 | E39: 6
A40: Tech Ops | B40: 16 | C40: 1 | E40: 17
A41: Grand Total | B41: 82 | C41: 18 | D41: 18 | E41: 118
A45: Hiring by Grade
A46: Employee Type | B46: FTE
A47: Recruiting Status | B47: Hired
A48: Target Start Dt | B48: (Multiple Items)
A50: Location | B50: Count of Temp Job ID | M50: Location | N50: 2025 # | O50: 2026 # | Q50: Location | R50: 2025 # | S50: 2026 # | T50: % Y-over-Y Growth
A51: 09 - C-Suite | B51: 7 | M51: 09 - C-Suite | N51: 8 | O51: 9 | Q51: C-Suite | R51: 8 | S51: 9 | T51: =(S51-R51)/R51 -> 0.125
A52: 08 - VP | B52: 18 | M52: 08 - VP | N52: 18 | O52: 35 | Q52: SVP / VP | R52: 18 | S52: 35 | T52: =(S52-R52)/R52 -> 0.94444444
A53: 07 - Exec. Director | B53: 7 | M53: 07 - Exec. Director | N53: 7 | O53: 17 | Q53: ED-AD | R53: =SUM(N53:N56) -> 69 | S53: =SUM(O53:O56) -> 137 | T53: =(S53-R53)/R53 -> 0.98550725
A54: 06 - Sr. Director | B54: 27 | M54: 06 - Sr. Director | N54: 28 | O54: 48 | Q54: Sr. Mgr / Mgr / IC | R54: =SUM(N57:N59) -> 44 | S54: =SUM(O57:O59) -> 74 | T54: =(S54-R54)/R54 -> 0.68181818
A55: 05 - Director | B55: 22 | M55: 05 - Director | N55: 23 | O55: 44 | Q55: Grand Total | R55: =SUM(R51:R54) -> 139 | S55: =SUM(S51:S54) -> 255 | T55: =(S55-R55)/R55 -> 0.83453237
A56: 04 - Assoc. Director | B56: 11 | M56: 04 - Assoc. Director | N56: 11 | O56: 28
A57: 03 - Sr. Manager | B57: 26 | M57: 03 - Sr. Manager | N57: 26 | O57: 44
A58: 02 - Manager | B58: 9 | M58: 02 - Manager | N58: 9 | O58: 16
A59: 01 - Below Manager | B59: 9 | M59: 01 - Below Manager | N59: 9 | O59: 14
A60: Grand Total | B60: 136 | M60: Grand Total | N60: =SUM(N51:N59) -> 139 | O60: =SUM(O51:O59) -> 255
A65: TA Support
A68: Employee Type | B68: FTE
A69: Recruiting Status | B69: (Multiple Items)
A70: Target Start Dt | B70: (Multiple Items)
A72: Count of Temp Job ID | B72: Column Labels
A73: Function / Dept | B73: Kim | C73: Linda | D73: Steven | E73: Yen | F73: (blank) | G73: Grand Total | M73: Function / Mgr | N73: Bob | P73: Function / Mgr | Q73: Kim | S73: Function / Mgr | T73: Linda | V73: Function / Mgr | W73: Yen | Y73: Function / Mgr | Z73: Steven
A74: Communications | D74: 1 | E74: 1 | G74: 2 | M74: Development | N74: 6 | P74: Development | Q74: 13 | S74: Development | T74: 8 | V74: Communications | W74: 1 | Y74: Communications | Z74: 1
A75: 930 Communications | D75: 1 | E75: 1 | G75: 2 | M75: Cheryl Abbas | N75: 4 | P75: Brianne Leary | Q75: 2 | S75: Andrea Koh | T75: 1 | V75: Emily Faucette | W75: 1 | Y75: Emily Faucette | Z75: 1
A76: Emily Faucette | D76: 1 | E76: 1 | G76: 2 | M76: Global Site Lead | N76: 2 | P76: Caroline Cooper | Q76: 1 | S76: Jay Edelberg | T76: 3 | V76: Development | W76: 5 | Y76: Development | Z76: 1
A77: Development | B77: 12 | C77: 8 | E77: 5 | G77: 25 | M77: Grand Total | N77: 6 | P77: Jaclyn Patterson | Q77: 8 | S77: Jessie Yan | T77: 1 | V77: Angela Gao | W77: 1 | Y77: Cheryl Abbas | Z77: 1
A78: 210 Clinical Operations | B78: 9 | C78: 2 | G78: 11 | P78: VP Biometrics | Q78: 1 | S78: Jody Dosanjh | T78: 1 | V78: Cheryl Abbas | W78: 1 | Y78: Grand Total | Z78: 2
A79: Andrea Koh | C79: 1 | G79: 1 | P79: Sanjay Patel | Q79: 1 | S79: Lauren Cao | T79: 1 | V79: Stu Heminway | W79: 3
A80: Brianne Leary | B80: 2 | G80: 2 | P80: P&C | Q80: 1 | S80: Wanying Li | T80: 1 | V80: Legal | W80: 2
A81: Caroline Cooper | B81: 1 | G81: 1 | P81: Liz Nguyen | Q81: 1 | S81: Office of CFO | T81: 4 | V81: Brianne Jahn | W81: 1
A82: Jaclyn Patterson | B82: 5 | G82: 5 | P82: Quality | Q82: 3 | S82: Daren Wilkinson | T82: 1 | V82: Mike Rhee | W82: 1
A83: Jody Dosanjh | C83: 1 | G83: 1 | P83: Donna Walters | Q83: 1 | S83: Oliver Sjahsam | T83: 2 | V83: Office of CFO | W83: 2
A84: Sanjay Patel | B84: 1 | G84: 1 | P84: Justin Thompson | Q84: 1 | S84: Steve Servantez | T84: 1 | V84: Darrin Chang | W84: 1
A85: 215 Clinical Development | C85: 3 | G85: 3 | P85: Theresa Friend | Q85: 1 | S85: Research - Discovery | T85: 2 | V85: Suresh Sasidaran | W85: 1
A86: Jay Edelberg | C86: 3 | G86: 3 | P86: Tech Ops | Q86: 7 | S86: Jim Driscoll | T86: 1 | V86: Office of CSO | W86: 8
A87: 220 Clinical Data Science | B87: 2 | C87: 2 | E87: 1 | G87: 5 | P87: Donald Mackenzie | Q87: 1 | S87: Steve McKerrall | T87: 1 | V87: Andy Pasternak | W87: 1
A88: Angela Gao | E88: 1 | G88: 1 | P88: Leon Zhou | Q88: 1 | S88: Research - Translational | T88: 1 | V88: Betsy O'Neill | W88: 3
A89: Jaclyn Patterson | B89: 1 | G89: 1 | P89: VP DS | Q89: 3 | S89: Carlos del Rio | T89: 1 | V89: Head of Portfolio Strategy | W89: 2
A90: Jessie Yan | C90: 1 | G90: 1 | P90: William Walker | Q90: 2 | S90: Grand Total | T90: 15 | V90: Brett Koch | W90: 2
A91: VP Biometrics | B91: 1 | G91: 1 | P91: Grand Total | Q91: 24 | V91: Grand Total | W91: 18
A92: Wanying Li | C92: 1 | G92: 1
A93: 221 Clinical Data Management | B93: 1 | C93: 1 | G93: 2
A94: Jaclyn Patterson | B94: 1 | G94: 1
A95: Lauren Cao | C95: 1 | G95: 1
A96: 235 Regulatory | E96: 3 | G96: 3
A97: Stu Heminway | E97: 3 | G97: 3
A98: 505 Medical Affairs | E98: 1 | G98: 1
A99: Cheryl Abbas | E99: 1 | G99: 1
A100: Legal | E100: 2 | G100: 2
A101: 920 Legal | E101: 2 | G101: 2
A102: Brianne Jahn | E102: 1 | G102: 1
A103: Mike Rhee | E103: 1 | G103: 1
A104: Office of CFO | C104: 4 | E104: 2 | G104: 6
A105: 915 Accounting | E105: 2 | G105: 2
A106: Darrin Chang | E106: 1 | G106: 1
A107: Suresh Sasidaran | E107: 1 | G107: 1
A108: 960 Facilities | C108: 2 | G108: 2
A109: Oliver Sjahsam | C109: 2 | G109: 2
A110: 970 IT | C110: 2 | G110: 2
A111: Daren Wilkinson | C111: 1 | G111: 1
A112: Steve Servantez | C112: 1 | G112: 1
A113: Office of CSO | D113: 2 | E113: 6 | F113: 1 | G113: 9
A114: 240 Portfolio Management | E114: 3 | G114: 3
A115: Andy Pasternak | E115: 1 | G115: 1
A116: Head of Portfolio Strategy | E116: 2 | G116: 2
A117: 917 Corporate Strategy | D117: 2 | F117: 1 | G117: 3
A118: Brett Koch | D118: 2 | F118: 1 | G118: 3
A119: 925 Business Development | E119: 3 | G119: 3
...

Sheet Copy to Pres
A1: Function / Dept | B1: CW / PD | C1: CW Part time | D1: FTE | E1: 2026 Guidance | F1: Dif | G1: Total FTE + CW | I1: Current FTE | J1: 2026 Guidance | K1: Potential Hires | M1: Starts in 2025 | O1: % FTE 2026 | P1: % Total WF | R1: % FTE 2025 | S1: Dif
A2: Commercial | D2: 9 | E2: 9 | F2: =D2-E2 -> 0 | G2: =SUM(B2:D2) -> 9 | I2: 4 | J2: 9 | K2: =J2-I2 -> 5 | M2: 2 | O2: =D2/257 -> 0.035019455 | P2: =G2/329 -> 0.027355623 | R2: =I2/146 -> 0.02739726 | S2: =O2-R2 -> 0.007622195
A3: Development | B3: 42 | C3: 9 | D3: =SUM(D4:D11) -> 85 | E3: =SUM(E4:E11) -> 80 | F3: =D3-E3 -> 5 | G3: =SUM(B3:D3) -> 136 | I3: =SUM(I4:I11) -> 43 | J3: =SUM(J4:J11) -> 85 | K3: =J3-I3 -> 42 | M3: =SUM(M4:M11) -> 28 | O3: =D3/257 -> 0.3307393 | P3: =G3/329 -> 0.41337386 | R3: =I3/146 -> 0.29452055 | S3: =O3-R3 -> 0.036218752
A4: 205 Development Management | D4: 7 | E4: 2 | F4: =D4-E4 -> 5 | G4: =SUM(B4:D4) -> 7 | I4: 2 | J4: 7 | K4: =J4-I4 -> 5 | M4: 0 | O4: =D4/257 -> 0.027237354 | P4: =G4/329 -> 0.021276596 | R4: =I4/146 -> 0.01369863 | S4: =O4-R4 -> 0.013538724
A5: 210 Clinical Operations | B5: 18 | D5: 25 | E5: 25 | F5: =D5-E5 -> 0 | G5: =SUM(B5:D5) -> 43 | I5: 13 | J5: 25 | K5: =J5-I5 -> 12 | M5: 8 | O5: =D5/257 -> 0.097276265 | P5: =G5/329 -> 0.13069909 | R5: =I5/146 -> 0.089041096 | S5: =O5-R5 -> 0.0082351687
A6: 215 Clinical Development | B6: 3 | D6: 9 | E6: 10 | F6: =D6-E6 -> -1 | G6: =SUM(B6:D6) -> 12 | I6: 5 | J6: 9 | K6: =J6-I6 -> 4 | M6: 4 | O6: =D6/257 -> 0.035019455 | P6: =G6/329 -> 0.036474164 | R6: =I6/146 -> 0.034246575 | S6: =O6-R6 -> 0.00077287991
A7: 220 Clinical Data Science | B7: 21 | D7: 17 | E7: 17 | F7: =D7-E7 -> 0 | G7: =SUM(B7:D7) -> 38 | I7: 11 | J7: 17 | K7: =J7-I7 -> 6 | M7: 6 | O7: =D7/257 -> 0.06614786 | P7: =G7/329 -> 0.11550152 | R7: =I7/146 -> 0.075342466 | S7: =O7-R7 -> -0.0091946058
A8: 225 Early Development | D8: 4 | E8: 4 | F8: =D8-E8 -> 0 | G8: =SUM(B8:D8) -> 4 | I8: 2 | J8: 4 | K8: =J8-I8 -> 2 | M8: 1 | O8: =D8/257 -> 0.015564202 | P8: =G8/329 -> 0.012158055 | R8: =I8/146 -> 0.01369863 | S8: =O8-R8 -> 0.0018655722
A9: 230 Pharmacovigilance | D9: 5 | E9: 5 | F9: =D9-E9 -> 0 | G9: =SUM(B9:D9) -> 5 | I9: 2 | J9: 5 | K9: =J9-I9 -> 3 | M9: 2 | O9: =D9/257 -> 0.019455253 | P9: =G9/329 -> 0.015197568 | R9: =I9/146 -> 0.01369863 | S9: =O9-R9 -> 0.0057566228
A10: 235 Regulatory | C10: 9 | D10: 10 | E10: 10 | F10: =D10-E10 -> 0 | G10: =SUM(B10:D10) -> 19 | I10: 4 | J10: 10 | K10: =J10-I10 -> 6 | M10: 3 | O10: =D10/257 -> 0.038910506 | P10: =G10/329 -> 0.05775076 | R10: =I10/146 -> 0.02739726 | S10: =O10-R10 -> 0.011513246
A11: 505 Medical Affairs | D11: 8 | E11: 7 | F11: =D11-E11 -> 1 | G11: =SUM(B11:D11) -> 8 | I11: 4 | J11: 8 | K11: =J11-I11 -> 4 | M11: 4 | O11: =D11/257 -> 0.031128405 | P11: =G11/329 -> 0.024316109 | R11: =I11/146 -> 0.02739726 | S11: =O11-R11 -> 0.0037311444
A12: G&A | B12: 7 | D12: =SUM(D13:D20) -> 73 | E12: =SUM(E13:E20) -> 71 | F12: =D12-E12 -> 2 | G12: =SUM(B12:D12) -> 80 | I12: =SUM(I13:I20) -> 45 | J12: =SUM(J13:J20) -> 73 | K12: =J12-I12 -> 28 | M12: =SUM(M13:M20) -> 29 | O12: =D12/257 -> 0.28404669 | P12: =G12/329 -> 0.24316109 | R12: =I12/146 -> 0.30821918 | S12: =O12-R12 -> -0.024172485
A13: 901 Executive | D13: 7 | E13: 5 | F13: =D13-E13 -> 2 | G13: =SUM(B13:D13) -> 7 | I13: 2 | J13: 7 | K13: =J13-I13 -> 5 | M13: 0 | O13: =D13/257 -> 0.027237354 | P13: =G13/329 -> 0.021276596 | R13: =I13/146 -> 0.01369863 | S13: =O13-R13 -> 0.013538724
A14: 910 People and Culture | B14: 3 | D14: 14 | E14: 14 | F14: =D14-E14 -> 0 | G14: =SUM(B14:D14) -> 17 | I14: 11 | J14: 14 | K14: =J14-I14 -> 3 | M14: 5 | O14: =D14/257 -> 0.054474708 | P14: =G14/329 -> 0.051671733 | R14: =I14/146 -> 0.075342466 | S14: =O14-R14 -> -0.020867758
A15: 915 Finance & Accounting | D15: 18 | E15: 17 | F15: =D15-E15 -> 1 | G15: =SUM(B15:D15) -> 18 | I15: 13 | J15: 18 | K15: =J15-I15 -> 5 | M15: 11 | O15: =D15/257 -> 0.070038911 | P15: =G15/329 -> 0.054711246 | R15: =I15/146 -> 0.089041096 | S15: =O15-R15 -> -0.019002185
A16: 920 Legal | D16: 12 | E16: 12 | F16: =D16-E16 -> 0 | G16: =SUM(B16:D16) -> 12 | I16: 6 | J16: 12 | K16: =J16-I16 -> 6 | M16: 4 | O16: =D16/257 -> 0.046692607 | P16: =G16/329 -> 0.036474164 | R16: =I16/146 -> 0.04109589 | S16: =O16-R16 -> 0.0055967166
A17: 925 Business Development | D17: 2 | E17: 3 | F17: =D17-E17 -> -1 | G17: =SUM(B17:D17) -> 2 | I17: 1 | J17: 2 | K17: =J17-I17 -> 1 | M17: 0 | O17: =D17/257 -> 0.0077821012 | P17: =G17/329 -> 0.0060790274 | R17: =I17/146 -> 0.0068493151 | S17: =O17-R17 -> 0.0009327861
A18: 930 Communications | D18: 4 | E18: 4 | F18: =D18-E18 -> 0 | G18: =SUM(B18:D18) -> 4 | I18: 2 | J18: 4 | K18: =J18-I18 -> 2 | M18: 1 | O18: =D18/257 -> 0.015564202 | P18: =G18/329 -> 0.012158055 | R18: =I18/146 -> 0.01369863 | S18: =O18-R18 -> 0.0018655722
A19: 960 Facilities | B19: 2 | D19: 6 | E19: 6 | F19: =D19-E19 -> 0 | G19: =SUM(B19:D19) -> 8 | I19: 4 | J19: 6 | K19: =J19-I19 -> 2 | M19: 3 | O19: =D19/257 -> 0.023346304 | P19: =G19/329 -> 0.024316109 | R19: =I19/146 -> 0.02739726 | S19: =O19-R19 -> -0.0040509568
A20: 970 IT | B20: 2 | D20: 10 | E20: 10 | F20: =D20-E20 -> 0 | G20: =SUM(B20:D20) -> 12 | I20: 6 | J20: 10 | K20: =J20-I20 -> 4 | M20: 5 | O20: =D20/257 -> 0.038910506 | P20: =G20/329 -> 0.036474164 | R20: =I20/146 -> 0.04109589 | S20: =O20-R20 -> -0.0021853846
A21: PPM | D21: 9 | E21: 9 | F21: =D21-E21 -> 0 | G21: =SUM(B21:D21) -> 9 | I21: 6 | J21: 9 | K21: =J21-I21 -> 3 | M21: 3 | O21: =D21/257 -> 0.035019455 | P21: =G21/329 -> 0.027355623 | R21: =I21/146 -> 0.04109589 | S21: =O21-R21 -> -0.0060764352
A22: Quality | B22: 9 | D22: 16 | E22: 16 | F22: =D22-E22 -> 0 | G22: =SUM(B22:D22) -> 25 | I22: 12 | J22: 16 | K22: =J22-I22 -> 4 | M22: 9 | O22: =D22/257 -> 0.062256809 | P22: =G22/329 -> 0.075987842 | R22: =I22/146 -> 0.082191781 | S22: =O22-R22 -> -0.019934971
A23: Tech Ops | B23: 2 | D23: 31 | E23: 31 | F23: =D23-E23 -> 0 | G23: =SUM(B23:D23) -> 33 | I23: 15 | J23: 31 | K23: =J23-I23 -> 16 | M23: 12 | O23: =D23/257 -> 0.12062257 | P23: =G23/329 -> 0.10030395 | R23: =I23/146 -> 0.10273973 | S23: =O23-R23 -> 0.017882842
A24: Research - Discovery | D24: 10 | E24: 10 | F24: =D24-E24 -> 0 | G24: =SUM(B24:D24) -> 10 | I24: 7 | J24: 10 | K24: =J24-I24 -> 3 | M24: 5 | O24: =D24/257 -> 0.038910506 | P24: =G24/329 -> 0.030395137 | R24: =I24/146 -> 0.047945205 | S24: =O24-R24 -> -0.0090346996
A25: Research - Translational | B25: 3 | D25: 24 | E25: 24 | F25: =D25-E25 -> 0 | G25: =SUM(B25:D25) -> 27 | I25: 14 | J25: 24 | K25: =J25-I25 -> 10 | M25: 4 | O25: =D25/257 -> 0.093385214 | P25: =G25/329 -> 0.082066869 | R25: =I25/146 -> 0.095890411 | S25: =O25-R25 -> -0.002505197
A26: Grand Total | B26: =SUM(B21:B25)+B2+B3+B12 -> 63 | C26: =SUM(C21:C25)+C2+C3+C12 -> 9 | D26: =SUM(D21:D25)+D2+D3+D12 -> 257 | E26: =SUM(E21:E25)+E2+E3+E12 -> 250 | F26: =SUM(F21:F25)+F2+F3+F12 -> 7 | G26: =SUM(G21:G25)+G2+G3+G12 -> 329 | I26: =SUM(I21:I25)+I2+I3+I12 -> 146 | J26: =SUM(J21:J25)+J2+J3+J12 -> 257 | K26: =SUM(K21:K25)+K2+K3+K12 -> 111 | M26: =SUM(M21:M25)+M2+M3+M12 -> 92 | O26: =SUM(O21:O25)+O2+O3+O12 -> 1 | P26: =SUM(P21:P25)+P2+P3+P12 -> 1 | R26: =SUM(R21:R25)+R2+R3+R12 -> 1 | S26: =SUM(S21:S25)+S2+S3+S12 -> 0
A30: Function / Dept | B30: SSF | C30: PNJ | D30: SSF or PNJ | E30: Chicago | F30: Remote | G30: EU | H30: TBD | I30: Total
A31: Commercial | B31: 9 | I31: 9
A32: G&A | B32: 42 | C32: 17 | E32: 9 | H32: 5 | I32: 73
A33: PPM | B33: 6 | C33: 1 | D33: 2 | I33: 9
A34: Quality | B34: 14 | C34: 2 | I34: 16
A35: Tech Ops | B35: 15 | C35: 16 | I35: 31
A36: Development | B36: 23 | C36: 52 | D36: 3 | F36: 6 | G36: 1 | I36: 85
A37: Research - Discovery | B37: 10 | I37: 10
A38: Research - Translational | B38: 23 | H38: 1 | I38: 24
A39: Total | B39: 142 | C39: 88 | D39: 5 | E39: 9 | F39: 6 | G39: 1 | H39: 6 | I39: 257
A40: Current | B40: 96 | C40: 41 | D40: 0 | E40: 6 | F40: 3 | G40: 0 | H40: 0 | I40: 146
A41: Growth | B41: =(B39-B40)/B40 -> 0.47916667 | C41: =(C39-C40)/C40 -> 1.1463415 | E41: =(E39-E40)/E40 -> 0.5 | F41: =(F39-F40)/F40 -> 1 | I41: =(I39-I40)/I40 -> 0.76027397
A44: Level | B44: Commercial | C44: G&A | D44: PPM | E44: Quality | F44: Tech Ops | G44: Development | H44: Research - Discovery | I44: Research - Translational | J44: Grand Total | K44: % | N44: Current Breakout | O44: % | R44: WFP Total | S44: %
A45: 09 - C-Suite | C45: 6 | E45: 1 | F45: 1 | G45: 1 | J45: =SUM(B45:I45) -> 9 | K45: =J45/257 -> 0.035019455 | N45: 8 | O45: =N45/149 -> 0.053691275 | R45: 1 | S45: =R45/107 -> 0.0093457944
A46: 08 - VP | B46: 2 | C46: 10 | D46: 1 | E46: 1 | F46: 4 | G46: 10 | H46: 1 | I46: 2 | J46: =SUM(B46:I46) -> 31 | K46: =J46/257 -> 0.12062257 | N46: 22 | O46: =N46/149 -> 0.14765101 | R46: 9 | S46: =R46/107 -> 0.08411215 | T46: =SUM(S45:S46) -> 0.093457944
A47: 07 - Exec. Director | C47: 7 | D47: 1 | G47: 6 | J47: =SUM(B47:I47) -> 14 | K47: =J47/257 -> 0.054474708 | L47: =SUM(J45:J47) -> 54 | M47: =L47/257 -> 0.21011673 | N47: 7 | O47: =N47/149 -> 0.046979866 | R47: 7 | S47: =R47/107 -> 0.065420561
A48: 06 - Sr. Director | B48: 5 | C48: 9 | D48: 1 | E48: 5 | F48: 10 | G48: 18 | J48: =SUM(B48:I48) -> 48 | K48: =J48/257 -> 0.18677043 | N48: 28 | O48: =N48/149 -> 0.18791946 | R48: 20 | S48: =R48/107 -> 0.18691589
A49: 05 - Director | C49: 17 | D49: 4 | E49: 5 | F49: 6 | G49: 18 | H49: 2 | I49: 1 | J49: =SUM(B49:I49) -> 53 | K49: =J49/257 -> 0.20622568 | N49: 27 | O49: =N49/149 -> 0.18120805 | R49: 26 | S49: =R49/107 -> 0.24299065
A50: 04 - Assoc. Director | C50: 2 | E50: 1 | F50: 6 | G50: 14 | H50: 2 | I50: 3 | J50: =SUM(B50:I50) -> 28 | K50: =J50/257 -> 0.10894942 | N50: 12 | O50: =N50/149 -> 0.080536913 | P50: =SUM(O47:O50) -> 0.4966443 | R50: 16 | S50: =R50/107 -> 0.14953271 | T50: =SUM(S47:S50) -> 0.64485981
A51: 03 - Sr. Manager | B51: 2 | C51: 15 | D51: 1 | E51: 3 | F51: 4 | G51: 11 | H51: 1 | I51: 4 | J51: =SUM(B51:I51) -> 41 | K51: =J51/257 -> 0.15953307 | N51: 26 | O51: =N51/149 -> 0.17449664 | R51: 15 | S51: =R51/107 -> 0.14018692
A52: 02 - Manager | C52: 7 | D52: 1 | G52: 1 | H52: 2 | I52: 7 | J52: =SUM(B52:I52) -> 18 | K52: =J52/257 -> 0.070038911 | N52: 10 | O52: =N52/149 -> 0.067114094 | R52: 8 | S52: =R52/107 -> 0.074766355
A53: 01 - Below Manager | C53: 5 | G53: 4 | H53: 1 | I53: 4 | J53: =SUM(B53:I53) -> 14 | K53: =J53/257 -> 0.054474708 | N53: 9 | O53: =N53/149 -> 0.060402685 | P53: =SUM(O51:O53) -> 0.30201342 | R53: 5 | S53: =R53/107 -> 0.046728972 | T53: =SUM(S51:S53) -> 0.26168224
A54: Grand Total | B54: =SUM(B45:B53) -> 9 | C54: =SUM(C45:C53) -> 78 | D54: =SUM(D45:D53) -> 9 | E54: =SUM(E45:E53) -> 16 | F54: =SUM(F45:F53) -> 31 | G54: =SUM(G45:G53) -> 83 | H54: =SUM(H45:H53) -> 9 | I54: =SUM(I45:I53) -> 21 | ... K54: =SUM(K45:K53) -> 0.99610895 | N54: =SUM(N45:N53) -> 149 | O54: =SUM(O45:O53) -> 1 | R54: =SUM(R45:R53) -> 107 | S54: =SUM(S45:S53) -> 1 | T54: =SUM(T45:T53) -> 1
A58: Function / Dept | B58: ATA 100% | D58: ATA 50% | E58: ATA 33% | G58: ATA HC Equiv. | H58: ATA Total HC | J58: TLA 100% | L58: TLA 50% | M58: TLA 33% | O58: TLA HC Equiv. | P58: TLA Total HC | R58: Dani 100% | T58: Dani 50% | U58: Dani 33% | W58: Dani HC Equiv. | X58: Dani Total | Z58: Unassigned | AB58: UA Total | AD58: Total EE | AF58: Total
B59: FTE | C59: CW | D59: FTE | E59: FTE | F59: CW | J59: FTE | K59: CW | L59: FTE | M59: FTE | N59: CW | R59: FTE | S59: CW | T59: FTE | U59: FTE | V59: CW | Z59: FTE | AA59: CW | AD59: FTE | AE59: CW
A60: Commercial | B60: 1 | E60: 5 | G60: =B60+C60+(0.5 *D60)+(0.33*(E60+F60)) -> 2.65 | H60: =SUM(B60:F60) -> 6 | L60: 1 | M60: 5 | O60: =J60+K60+(0.5 *L60)+(0.33*(M60+N60)) -> 2.15 | P60: =SUM(J60:N60) -> 6 | R60: 1 | T60: 1 | U60: 5 | W60: =R60+S60+(0.5 *T60)+(0.33*(U60+V60)) -> 3.15 | X60: =SUM(R60:V60) -> 7 | Z60: 1 | AB60: =SUM(Z60:AA60) -> 1 | AD60: =B60+J60+R60+Z60+(0.5*(D60+L60+T60))+0.33*((E60+M60+U60)) -> 8.95 | AE60: =C60+K60+S60+AA60+(0.33*(F60+N60+V60)) -> 0 | AF60: =SUM(AD60:AE60) -> 8.95
A61: 205 Development Management | E61: 1 | G61: =B61+C61+(0.5 *D61)+(0.33*(E61+F61)) -> 0.33 | H61: =SUM(B61:F61) -> 1 | M61: 1 | O61: =J61+K61+(0.5 *L61)+(0.33*(M61+N61)) -> 0.33 | P61: =SUM(J61:N61) -> 1 | U61: 1 | W61: =R61+S61+(0.5 *T61)+(0.33*(U61+V61)) -> 0.33 | X61: =SUM(R61:V61) -> 1 | Z61: 6 | AB61: =SUM(Z61:AA61) -> 6 | AD61: =B61+J61+R61+Z61+(0.5*(D61+L61+T61))+0.33*((E61+M61+U61)) -> 6.99 | AE61: =C61+K61+S61+AA61+(0.33*(F61+N61+V61)) -> 0 | AF61: =SUM(AD61:AE61) -> 6.99
A62: 210 Clinical Operations | B62: 8 | C62: 3 | E62: 2 | F62: 1 | G62: =B62+C62+(0.5 *D62)+(0.33*(E62+F62)) -> 11.99 | H62: =SUM(B62:F62) -> 14 | J62: 5 | K62: 6 | M62: 2 | N62: 1 | O62: =J62+K62+(0.5 *L62)+(0.33*(M62+N62)) -> 11.99 | P62: =SUM(J62:N62) -> 14 | R62: 6 | S62: 3 | U62: 2 | V62: 1 | W62: =R62+S62+(0.5 *T62)+(0.33*(U62+V62)) -> 9.99 | X62: =SUM(R62:V62) -> 12 | Z62: 4 | AA62: 5 | AB62: =SUM(Z62:AA62) -> 9 | AD62: =B62+J62+R62+Z62+(0.5*(D62+L62+T62))+0.33*((E62+M62+U62)) -> 24.98 | AE62: =C62+K62+S62+AA62+(0.33*(F62+N62+V62)) -> 17.99 | AF62: =SUM(AD62:AE62) -> 42.97
A63: 215 Clinical Development | B63: 4 | C63: 1 | G63: =B63+C63+(0.5 *D63)+(0.33*(E63+F63)) -> 5 | H63: =SUM(B63:F63) -> 5 | J63: 2 | K63: 1 | O63: =J63+K63+(0.5 *L63)+(0.33*(M63+N63)) -> 3 | P63: =SUM(J63:N63) -> 3 | R63: 3 | S63: 1 | W63: =R63+S63+(0.5 *T63)+(0.33*(U63+V63)) -> 4 | X63: =SUM(R63:V63) -> 4 | AB63: =SUM(Z63:AA63) -> 0 | AD63: =B63+J63+R63+Z63+(0.5*(D63+L63+T63))+0.33*((E63+M63+U63)) -> 9 | AE63: =C63+K63+S63+AA63+(0.33*(F63+N63+V63)) -> 3 | AF63: =SUM(AD63:AE63) -> 12
A64: 220 Clinical Data Science | B64: 4 | C64: 2 | E64: 2 | F64: 3 | G64: =B64+C64+(0.5 *D64)+(0.33*(E64+F64)) -> 7.65 | H64: =SUM(B64:F64) -> 11 | J64: 4 | K64: 7 | L64: 1 | M64: 2 | N64: 3 | O64: =J64+K64+(0.5 *L64)+(0.33*(M64+N64)) -> 13.15 | P64: =SUM(J64:N64) -> 17 | R64: 5 | S64: 4 | T64: 1 | U64: 2 | V64: 3 | W64: =R64+S64+(0.5 *T64)+(0.33*(U64+V64)) -> 11.15 | X64: =SUM(R64:V64) -> 15 | Z64: 1 | AA64: 5 | AB64: =SUM(Z64:AA64) -> 6 | AD64: =B64+J64+R64+Z64+(0.5*(D64+L64+T64))+0.33*((E64+M64+U64)) -> 16.98 | AE64: =C64+K64+S64+AA64+(0.33*(F64+N64+V64)) -> 20.97 | AF64: =SUM(AD64:AE64) -> 37.95
A65: 225 Early Development | E65: 3 | G65: =B65+C65+(0.5 *D65)+(0.33*(E65+F65)) -> 0.99 | H65: =SUM(B65:F65) -> 3 | M65: 3 | O65: =J65+K65+(0.5 *L65)+(0.33*(M65+N65)) -> 0.99 | P65: =SUM(J65:N65) -> 3 | U65: 3 | W65: =R65+S65+(0.5 *T65)+(0.33*(U65+V65)) -> 0.99 | X65: =SUM(R65:V65) -> 3 | Z65: 1 | AB65: =SUM(Z65:AA65) -> 1 | AD65: =B65+J65+R65+Z65+(0.5*(D65+L65+T65))+0.33*((E65+M65+U65)) -> 3.97 | AE65: =C65+K65+S65+AA65+(0.33*(F65+N65+V65)) -> 0 | AF65: =SUM(AD65:AE65) -> 3.97
A66: 230 Pharmacovigilance | B66: 1 | E66: 2 | G66: =B66+C66+(0.5 *D66)+(0.33*(E66+F66)) -> 1.66 | H66: =SUM(B66:F66) -> 3 | J66: 1 | M66: 2 | O66: =J66+K66+(0.5 *L66)+(0.33*(M66+N66)) -> 1.66 | P66: =SUM(J66:N66) -> 3 | R66: 1 | U66: 2 | W66: =R66+S66+(0.5 *T66)+(0.33*(U66+V66)) -> 1.66 | X66: =SUM(R66:V66) -> 3 | AB66: =SUM(Z66:AA66) -> 0 | AD66: =B66+J66+R66+Z66+(0.5*(D66+L66+T66))+0.33*((E66+M66+U66)) -> 4.98 | AE66: =C66+K66+S66+AA66+(0.33*(F66+N66+V66)) -> 0 | AF66: =SUM(AD66:AE66) -> 4.98
A67: 235 Regulatory | B67: 2 | D67: 1 | G67: =B67+C67+(0.5 *D67)+(0.33*(E67+F67)) -> 2.5 | H67: =SUM(B67:F67) -> 3 | J67: 1 | L67: 2 | O67: =J67+K67+(0.5 *L67)+(0.33*(M67+N67)) -> 2 | P67: =SUM(J67:N67) -> 3 | R67: 2 | T67: 1 | W67: =R67+S67+(0.5 *T67)+(0.33*(U67+V67)) -> 2.5 | X67: =SUM(R67:V67) -> 3 | Z67: 3 | AB67: =SUM(Z67:AA67) -> 3 | AD67: =B67+J67+R67+Z67+(0.5*(D67+L67+T67))+0.33*((E67+M67+U67)) -> 10 | AE67: =C67+K67+S67+AA67+(0.33*(F67+N67+V67)) -> 0 | AF67: =SUM(AD67:AE67) -> 10
A68: 505 Medical Affairs | B68: 2 | E68: 3 | G68: =B68+C68+(0.5 *D68)+(0.33*(E68+F68)) -> 2.99 | H68: =SUM(B68:F68) -> 5 | J68: 1 | M68: 3 | O68: =J68+K68+(0.5 *L68)+(0.33*(M68+N68)) -> 1.99 | P68: =SUM(J68:N68) -> 4 | R68: 1 | U68: 3 | W68: =R68+S68+(0.5 *T68)+(0.33*(U68+V68)) -> 1.99 | X68: =SUM(R68:V68) -> 4 | Z68: 1 | AB68: =SUM(Z68:AA68) -> 1 | AD68: =B68+J68+R68+Z68+(0.5*(D68+L68+T68))+0.33*((E68+M68+U68)) -> 7.97 | AE68: =C68+K68+S68+AA68+(0.33*(F68+N68+V68)) -> 0 | AF68: =SUM(AD68:AE68) -> 7.97
A69: 915 Finance & Accounting | D69: 1 | G69: =B69+C69+(0.5 *D69)+(0.33*(E69+F69)) -> 0.5 | H69: =SUM(B69:F69) -> 1 | L69: 1 | O69: =J69+K69+(0.5 *L69)+(0.33*(M69+N69)) -> 0.5 | P69: =SUM(J69:N69) -> 1 | W69: =R69+S69+(0.5 *T69)+(0.33*(U69+V69)) -> 0 | X69: =SUM(R69:V69) -> 0 | Z69: 17 | AB69: =SUM(Z69:AA69) -> 17 | AD69: =B69+J69+R69+Z69+(0.5*(D69+L69+T69))+0.33*((E69+M69+U69)) -> 18 | AE69: =C69+K69+S69+AA69+(0.33*(F69+N69+V69)) -> 0 | AF69: =SUM(AD69:AE69) -> 18
A70: 920 Legal | E70: 1 | G70: =B70+C70+(0.5 *D70)+(0.33*(E70+F70)) -> 0.33 | H70: =SUM(B70:F70) -> 1 | J70: 1 | M70: 1 | O70: =J70+K70+(0.5 *L70)+(0.33*(M70+N70)) -> 1.33 | P70: =SUM(J70:N70) -> 2 | R70: 1 | U70: 1 | W70: =R70+S70+(0.5 *T70)+(0.33*(U70+V70)) -> 1.33 | X70: =SUM(R70:V70) -> 2 | Z70: 9 | AB70: =SUM(Z70:AA70) -> 9 | AD70: =B70+J70+R70+Z70+(0.5*(D70+L70+T70))+0.33*((E70+M70+U70)) -> 11.99 | AE70: =C70+K70+S70+AA70+(0.33*(F70+N70+V70)) -> 0 | AF70: =SUM(AD70:AE70) -> 11.99
A71: Tech Ops | B71: 6 | D71: 2 | E71: 15 | F71: 2 | G71: =B71+C71+(0.5 *D71)+(0.33*(E71+F71)) -> 12.61 | H71: =SUM(B71:F71) -> 25 | J71: 3 | L71: 3 | M71: 15 | N71: 2 | O71: =J71+K71+(0.5 *L71)+(0.33*(M71+N71)) -> 10.11 | P71: =SUM(J71:N71) -> 23 | R71: 3 | T71: 3 | U71: 15 | V71: 2 | W71: =R71+S71+(0.5 *T71)+(0.33*(U71+V71)) -> 10.11 | X71: =SUM(R71:V71) -> 23 | AB71: =SUM(Z71:AA71) -> 0 | AD71: =B71+J71+R71+Z71+(0.5*(D71+L71+T71))+0.33*((E71+M71+U71)) -> 30.85 | AE71: =C71+K71+S71+AA71+(0.33*(F71+N71+V71)) -> 1.98 | AF71: =SUM(AD71:AE71) -> 32.83
A72: Quality | B72: 1 | D72: 2 | E72: 1 | G72: =B72+C72+(0.5 *D72)+(0.33*(E72+F72)) -> 2.33 | H72: =SUM(B72:F72) -> 4 | L72: 3 | M72: 1 | O72: =J72+K72+(0.5 *L72)+(0.33*(M72+N72)) -> 1.83 | P72: =SUM(J72:N72) -> 4 | S72: 2 | T72: 3 | U72: 1 | W72: =R72+S72+(0.5 *T72)+(0.33*(U72+V72)) -> 3.83 | X72: =SUM(R72:V72) -> 6 | Z72: 10 | AA72: 7 | AB72: =SUM(Z72:AA72) -> 17 | AD72: =B72+J72+R72+Z72+(0.5*(D72+L72+T72))+0.33*((E72+M72+U72)) -> 15.99 | AE72: =C72+K72+S72+AA72+(0.33*(F72+N72+V72)) -> 9 | AF72: =SUM(AD72:AE72) -> 24.99
A73: PPM | B73: 1 | G73: =B73+C73+(0.5 *D73)+(0.33*(E73+F73)) -> 1 | H73: =SUM(B73:F73) -> 1 | J73: 1 | O73: =J73+K73+(0.5 *L73)+(0.33*(M73+N73)) -> 1 | P73: =SUM(J73:N73) -> 1 | R73: 1 | W73: =R73+S73+(0.5 *T73)+(0.33*(U73+V73)) -> 1 | X73: =SUM(R73:V73) -> 1 | Z73: 6 | AB73: =SUM(Z73:AA73) -> 6 | AD73: =B73+J73+R73+Z73+(0.5*(D73+L73+T73))+0.33*((E73+M73+U73)) -> 9 | AE73: =C73+K73+S73+AA73+(0.33*(F73+N73+V73)) -> 0 | AF73: =SUM(AD73:AE73) -> 9
A74: Research - Discovery | E74: 1 | G74: =B74+C74+(0.5 *D74)+(0.33*(E74+F74)) -> 0.33 | H74: =SUM(B74:F74) -> 1 | M74: 1 | O74: =J74+K74+(0.5 *L74)+(0.33*(M74+N74)) -> 0.33 | P74: =SUM(J74:N74) -> 1 | R74: 1 | U74: 1 | W74: =R74+S74+(0.5 *T74)+(0.33*(U74+V74)) -> 1.33 | X74: =SUM(R74:V74) -> 2 | Z74: 8 | AB74: =SUM(Z74:AA74) -> 8 | AD74: =B74+J74+R74+Z74+(0.5*(D74+L74+T74))+0.33*((E74+M74+U74)) -> 9.99 | AE74: =C74+K74+S74+AA74+(0.33*(F74+N74+V74)) -> 0 | AF74: =SUM(AD74:AE74) -> 9.99
